Workbook

Sheet Geral
A1: UF | B1: INSTRUMENTO | C1: NÚMERO | D1: ANO | E1: PROCESSO SEI | F1: VENCIMENTO | G1: QUANT. TA | H1: SOLICITOU PRORROGAÇÃO 2025? | I1: VALOR GLOBAL | J1: VALOR REPASSE | K1: VALOR CONTRAPARTIDA | L1: REPASSE DESEMBOLSADO | M1: RENDIMENTO APROVADO | N1: SALDO DE RENDIMENTOS ATUAL | O1: SALDO RESIDUAL CAPITAL | P1: SALDO RESIDUAL CUSTEIO | Q1: CONTRAPARTIDA INTEGRALIZADA | R1: VALOR EXECUTADO GERAL | S1: VALOR PREVISTO OUVIDORIA | T1: VALOR PREVISTO CORREGEDORIA | U1: VALOR PREVISTO ESCOLA PENAL | V1: VALOR RELATIVO OUVIDORIA | W1: EXECUÇÃO OUVIDORIA | X1: EXECUÇÃO CORREGEDORIA | Y1: EXECUÇÃO ESCOLA PENAL | Z1: SALDO TOTAL DISPONÍVEL PARA DESTINAÇÃO À OUVIDORIA
A2: MT | B2: Convênio | C2: 937698 | D2: 2022 | E2: 08016024910202234 | F2: 46484 | G2: 3 | H2: SIM | I2: 392509.71 | J2: 356000 | K2: 36509.71 | L2: 356000 | N2: 53258.81 | O2: =IFERROR(SUMIFS(INDIRECT("'"&$A2&"'!M:M"),INDIRECT("'"&$A2&"'!F:F"),"CAPITAL"),0) -> 6831.55 | P2: =IFERROR(SUMIFS(INDIRECT("'"&$A2&"'!M:M"),INDIRECT("'"&$A2&"'!F:F"),"CUSTEIO"),0) -> 46000.39 | Q2: 36509.71 | R2: =N3 -> 26067.41 | S2: =IFERROR(SUMIFS(MT!$J:$J, MT!$E:$E, "OUVIDORIA", MT!$A:$A, $A2, MT!$C:$C, $C2), 0) -> 119503.74 | T2: =IFERROR(SUMIFS(MT!$J:$J, MT!$E:$E, "CORREGEDORIA", MT!$A:$A, $A2, MT!$C:$C, $C2), 0) -> 108156 | U2: =IFERROR(SUMIFS(MT!$J:$J, MT!$E:$E, "ESCOLA PENAL", MT!$A:$A, $A2, MT!$C:$C, $C2), 0) -> 164850 | V2: =IFERROR($S2/$I2,0) -> 0.3044606 | W2: =IF($S2<=0,0, SUMIFS(MT!$K:$K, MT!$E:$E, "OUVIDORIA", MT!$A:$A, $A2, MT!$C:$C, $C2) / $S2) -> 0.59108786 | X2: =IF($T2<=0,0, SUMIFS(MT!$K:$K, MT!$E:$E, "CORREGEDORIA", MT!$A:$A, $A2, MT!$C:$C, $C2) / $T2) -> 0.94277396 | Y2: =IF($U2<=0,0, SUMIFS(MT!$K:$K, MT!$E:$E, "ESCOLA PENAL", MT!$A:$A, $A2, MT!$C:$C, $C2) / $U2) -> 1 | Z2: =N2+O2+P2 -> 106090.75
A3: GO | B3: Convênio | C3: 937216 | D3: 2022 | E3: 08016024915202267 | F3: 46484 | G3: 1 | H3: SIM | I3: 388852.48 | J3: 384963.95 | K3: 3888.53 | L3: 384963.95 | N3: 26067.41 | O3: =IFERROR(SUMIFS(INDIRECT("'"&$A3&"'!M:M"),INDIRECT("'"&$A3&"'!F:F"),"CAPITAL"),0) -> 57725.21 | P3: =IFERROR(SUMIFS(INDIRECT("'"&$A3&"'!M:M"),INDIRECT("'"&$A3&"'!F:F"),"CUSTEIO"),0) -> 0 | Q3: 3888.53 | R3: =IFERROR(SUMIFS(GO!$K:$K, GO!$A:$A, $A3, GO!$C:$C, $C3), 0) -> 323819.27 | S3: =IFERROR(SUMIFS(GO!$J:$J, GO!$E:$E, "OUVIDORIA", GO!$A:$A, $A3, GO!$C:$C, $C3), 0) -> 106486 | T3: =IFERROR(SUMIFS(GO!$J:$J, GO!$E:$E, "CORREGEDORIA", GO!$A:$A, $A3, GO!$C:$C, $C3), 0) -> 87246.81 | U3: =IFERROR(SUMIFS(GO!$J:$J, GO!$E:$E, "ESCOLA PENAL", GO!$A:$A, $A3, GO!$C:$C, $C3), 0) -> 161086.33 | V3: =IFERROR($S3/$I3,0) -> 0.27384678 | W3: =IF($S3<=0,0, SUMIFS(GO!$K:$K, GO!$E:$E, "OUVIDORIA", GO!$A:$A, $A3, GO!$C:$C, $C3) / $S3) -> 1 | X3: =IF($T3<=0,0, SUMIFS(GO!$K:$K, GO!$E:$E, "CORREGEDORIA", GO!$A:$A, $A3, GO!$C:$C, $C3) / $T3) -> 0.73634979 | Y3: =IF($U3<=0,0, SUMIFS(GO!$K:$K, GO!$E:$E, "ESCOLA PENAL", GO!$A:$A, $A3, GO!$C:$C, $C3) / $U3) -> 0.95035438 | Z3: =N3+O3+P3 -> 83792.62
A4: PR | B4: Convênio | C4: 937871 | D4: 2022 | E4: 08016025090202206 | F4: 46484 | G4: 1 | H4: SIM | I4: 861700.16 | J4: 794355.17 | K4: 16211.33 | L4: 794355.17 | M4: 51133.66 | N4: 28124.68 | O4: =IFERROR(SUMIFS(INDIRECT("'"&$A4&"'!M:M"),INDIRECT("'"&$A4&"'!F:F"),"CAPITAL"),0) -> 45196.7 | P4: =IFERROR(SUMIFS(INDIRECT("'"&$A4&"'!M:M"),INDIRECT("'"&$A4&"'!F:F"),"CUSTEIO"),0) -> 0 | Q4: 16211.33 | R4: =IFERROR(SUMIFS(PR!$K:$K, PR!$A:$A, $A4, PR!$C:$C, $C4), 0) -> 485239.8 | S4: =IFERROR(SUMIFS(PR!$J:$J, PR!$E:$E, "OUVIDORIA", PR!$A:$A, $A4, PR!$C:$C, $C4), 0) -> 161317.98 | T4: =IFERROR(SUMIFS(PR!$J:$J, PR!$E:$E, "CORREGEDORIA", PR!$A:$A, $A4, PR!$C:$C, $C4), 0) -> 322820.85 | U4: =IFERROR(SUMIFS(PR!$J:$J, PR!$E:$E, "ESCOLA PENAL", PR!$A:$A, $A4, PR!$C:$C, $C4), 0) -> 334677.35 | V4: =IFERROR($S4/$I4,0) -> 0.18720895 | W4: =IF($S4<=0,0, SUMIFS(PR!$K:$K, PR!$E:$E, "OUVIDORIA", PR!$A:$A, $A4, PR!$C:$C, $C4) / $S4) -> 0.096053521 | X4: =IF($T4<=0,0, SUMIFS(PR!$K:$K, PR!$E:$E, "CORREGEDORIA", PR!$A:$A, $A4, PR!$C:$C, $C4) / $T4) -> 0.7990272 | Y4: =IF($U4<=0,0, SUMIFS(PR!$K:$K, PR!$E:$E, "ESCOLA PENAL", PR!$A:$A, $A4, PR!$C:$C, $C4) / $U4) -> 0.6328543 | Z4: =N4+O4+P4 -> 73321.38
A5: AM | B5: Convênio | C5: 937592 | D5: 2022 | E5: 08016024901202243 | F5: 46484 | G5: 1 | H5: SIM | I5: 300300 | J5: 300000 | K5: 300 | L5: 300000 | N5: 14404.99 | O5: =IFERROR(SUMIFS(INDIRECT("'"&$A5&"'!M:M"),INDIRECT("'"&$A5&"'!F:F"),"CAPITAL"),0) -> 47225.22 | P5: =IFERROR(SUMIFS(INDIRECT("'"&$A5&"'!M:M"),INDIRECT("'"&$A5&"'!F:F"),"CUSTEIO"),0) -> 29175 | Q5: 300 | R5: =IFERROR(SUMIFS(AM!$K$1:$K$24, AM!$A$1:$A$24, $A5, AM!$C$1:$C$24, $C5), 0) -> 223899.78 | S5: =IFERROR(SUMIFS(AM!$J$1:$J$24, AM!$E$1:$E$24, "OUVIDORIA", AM!$A$1:$A$24, $A5, AM!$C$1:$C$24, $C5), 0) -> 57507.98 | T5: =IFERROR(SUMIFS(AM!$J$1:$J$24, AM!$E$1:$E$24, "CORREGEDORIA", AM!$A$1:$A$24, $A5, AM!$C$1:$C$24, $C5), 0) -> 15129.7 | U5: =IFERROR(SUMIFS(AM!$J$1:$J$24, AM!$E$1:$E$24, "ESCOLA PENAL", AM!$A$1:$A$24, $A5, AM!$C$1:$C$24, $C5), 0) -> 227662.32 | V5: =IFERROR($S5/$I5,0) -> 0.19150176 | W5: =IF($S5<=0,0, SUMIFS(AM!$K$1:$K$24, AM!$E$1:$E$24, "OUVIDORIA", AM!$A$1:$A$24, $A5, AM!$C$1:$C$24, $C5) / $S5) -> 0.7953677 | X5: =IF($T5<=0,0, SUMIFS(AM!$K$1:$K$24, AM!$E$1:$E$24, "CORREGEDORIA", AM!$A$1:$A$24, $A5, AM!$C$1:$C$24, $C5) / $T5) -> 0.80371653 | Y5: =IF($U5<=0,0, SUMIFS(AM!$K$1:$K$24, AM!$E$1:$E$24, "ESCOLA PENAL", AM!$A$1:$A$24, $A5, AM!$C$1:$C$24, $C5) / $U5) -> 0.72914921 | Z5: =N5+O5+P5 -> 90805.21
A6: AC | B6: Convênio | C6: 937782 | D6: 2022 | E6: 08016024899202211 | F6: 46484 | G6: 1 | H6: SIM | I6: 396423.71 | J6: 396423.71 | K6: 5993.71 | L6: 150000 | N6: 21564.61 | O6: =IFERROR(SUMIFS(INDIRECT("'"&$A6&"'!M:M"),INDIRECT("'"&$A6&"'!F:F"),"CAPITAL"),0) -> 10533.1 | P6: =IFERROR(SUMIFS(INDIRECT("'"&$A6&"'!M:M"),INDIRECT("'"&$A6&"'!F:F"),"CUSTEIO"),0) -> 0 | Q6: 3593.71 | R6: =IFERROR(SUMIFS(AC!$K:$K, AC!$A:$A, $A6, AC!$C:$C, $C6), 0) -> 97141.55 | S6: =IFERROR(SUMIFS(AC!$J:$J, AC!$E:$E, "OUVIDORIA", AC!$A:$A, $A6, AC!$C:$C, $C6), 0) -> 242142.01 | T6: =IFERROR(SUMIFS(AC!$J:$J, AC!$E:$E, "CORREGEDORIA", AC!$A:$A, $A6, AC!$C:$C, $C6), 0) -> 44590.76 | U6: =IFERROR(SUMIFS(AC!$J:$J, AC!$E:$E, "ESCOLA PENAL", AC!$A:$A, $A6, AC!$C:$C, $C6), 0) -> 109681.1 | V6: =IFERROR($S6/$I6,0) -> 0.61081616 | W6: =IF($S6<=0,0, SUMIFS(AC!$K:$K, AC!$E:$E, "OUVIDORIA", AC!$A:$A, $A6, AC!$C:$C, $C6) / $S6) -> 0.14701596 | X6: =IF($T6<=0,0, SUMIFS(AC!$K:$K, AC!$E:$E, "CORREGEDORIA", AC!$A:$A, $A6, AC!$C:$C, $C6) / $T6) -> 0.85938813 | Y6: =IF($U6<=0,0, SUMIFS(AC!$K:$K, AC!$E:$E, "ESCOLA PENAL", AC!$A:$A, $A6, AC!$C:$C, $C6) / $U6) -> 0.21172326 | Z6: =N6+O6+P6 -> 32097.71
A7: MS | B7: Convênio | C7: 937265 | D7: 2022 | E7: 08016025017202226 | F7: 46484 | G7: 1 | H7: SIM | I7: 548000 | J7: 537040 | K7: 10960 | L7: 537040 | N7: 65876.01 | O7: =IFERROR(SUMIFS(INDIRECT("'"&$A7&"'!M:M"),INDIRECT("'"&$A7&"'!F:F"),"CAPITAL"),0) -> -79290.13 | P7: =IFERROR(SUMIFS(INDIRECT("'"&$A7&"'!M:M"),INDIRECT("'"&$A7&"'!F:F"),"CUSTEIO"),0) -> 0 | Q7: 10960 | R7: =IFERROR(SUMIFS(MS!$K:$K, MS!$A:$A, $A7, MS!$C:$C, $C7), 0) -> 311441.88 | S7: =IFERROR(SUMIFS(MS!$J:$J, MS!$E:$E, "OUVIDORIA", MS!$A:$A, $A7, MS!$C:$C, $C7), 0) -> 127595.47 | T7: =IFERROR(SUMIFS(MS!$J:$J, MS!$E:$E, "CORREGEDORIA", MS!$A:$A, $A7, MS!$C:$C, $C7), 0) -> 120294.2 | U7: =IFERROR(SUMIFS(MS!$J:$J, MS!$E:$E, "ESCOLA PENAL", MS!$A:$A, $A7, MS!$C:$C, $C7), 0) -> 300110.33 | V7: =IFERROR($S7/$I7,0) -> 0.23283845 | W7: =IF($S7<=0,0, SUMIFS(MS!$K:$K, MS!$E:$E, "OUVIDORIA", MS!$A:$A, $A7, MS!$C:$C, $C7) / $S7) -> 0.71172817 | X7: =IF($T7<=0,0, SUMIFS(MS!$K:$K, MS!$E:$E, "CORREGEDORIA", MS!$A:$A, $A7, MS!$C:$C, $C7) / $T7) -> 0.063471888 | Y7: =IF($U7<=0,0, SUMIFS(MS!$K:$K, MS!$E:$E, "ESCOLA PENAL", MS!$A:$A, $A7, MS!$C:$C, $C7) / $U7) -> 0.70971662 | Z7: =N7+O7+P7 -> -13414.12
A8: SP | B8: Convênio | C8: 938128 | D8: 2022 | E8: 08016025062202281 | F8: 46752 | G8: 1 | H8: SIM | I8: 3846559.5 | J8: 3769628.3 | K8: 76931.19 | L8: 3769628.3 | N8: 528436.85 | O8: =IFERROR(SUMIFS(INDIRECT("'"&$A8&"'!M:M"),INDIRECT("'"&$A8&"'!F:F"),"CAPITAL"),0) -> 887731.15 | P8: =IFERROR(SUMIFS(INDIRECT("'"&$A8&"'!M:M"),INDIRECT("'"&$A8&"'!F:F"),"CUSTEIO"),0) -> 400731.5 | Q8: 76931.19 | R8: =IFERROR(SUMIFS(SP!$K:$K, SP!$A:$A, $A8, SP!$C:$C, $C8), 0) -> 1068101.9 | S8: =IFERROR(SUMIFS(SP!$J:$J, SP!$E:$E, "OUVIDORIA", SP!$A:$A, $A8, SP!$C:$C, $C8), 0) -> 27513.73 | T8: =IFERROR(SUMIFS(SP!$J:$J, SP!$E:$E, "CORREGEDORIA", SP!$A:$A, $A8, SP!$C:$C, $C8), 0) -> 542449.85 | U8: =IFERROR(SUMIFS(SP!$J:$J, SP!$E:$E, "ESCOLA PENAL", SP!$A:$A, $A8, SP!$C:$C, $C8), 0) -> 2195566.9 | V8: =IFERROR($S8/$I8,0) -> 0.0071528154 | W8: =IF($S8<=0,0, SUMIFS(SP!$K:$K, SP!$E:$E, "OUVIDORIA", SP!$A:$A, $A8, SP!$C:$C, $C8) / $S8) -> 0.72996428 | X8: =IF($T8<=0,0, SUMIFS(SP!$K:$K, SP!$E:$E, "CORREGEDORIA", SP!$A:$A, $A8, SP!$C:$C, $C8) / $T8) -> 0.082606125 | Y8: =IF($U8<=0,0, SUMIFS(SP!$K:$K, SP!$E:$E, "ESCOLA PENAL", SP!$A:$A, $A8, SP!$C:$C, $C8) / $U8) -> 0.45692446 | Z8: =N8+O8+P8 -> 1816899.5
A9: MA | B9: Convênio | C9: 938277 | D9: 2022 | E9: 08016024893202235 | F9: 46484 | G9: 1 | H9: SIM | I9: 346697.9 | J9: 345652.9 | K9: 1045 | L9: 345652.9 | N9: 44991.21 | O9: =IFERROR(SUMIFS(INDIRECT("'"&$A9&"'!M:M"),INDIRECT("'"&$A9&"'!F:F"),"CAPITAL"),0) -> 7267.88 | P9: =IFERROR(SUMIFS(INDIRECT("'"&$A9&"'!M:M"),INDIRECT("'"&$A9&"'!F:F"),"CUSTEIO"),0) -> 41657.21 | Q9: 1045 | R9: =IFERROR(SUMIFS(MA!$K:$K, MA!$A:$A, $A9, MA!$C:$C, $C9), 0) -> 69485.85 | S9: =IFERROR(SUMIFS(MA!$J:$J, MA!$E:$E, "OUVIDORIA", MA!$A:$A, $A9, MA!$C:$C, $C9), 0) -> 105039.86 | T9: =IFERROR(SUMIFS(MA!$J:$J, MA!$E:$E, "CORREGEDORIA", MA!$A:$A, $A9, MA!$C:$C, $C9), 0) -> 108270.24 | U9: =IFERROR(SUMIFS(MA!$J:$J, MA!$E:$E, "ESCOLA PENAL", MA!$A:$A, $A9, MA!$C:$C, $C9), 0) -> 120195.47 | V9: =IFERROR($S9/$I9,0) -> 0.3029723 | W9: =IF($S9<=0,0, SUMIFS(MA!$K:$K, MA!$E:$E, "OUVIDORIA", MA!$A:$A, $A9, MA!$C:$C, $C9) / $S9) -> 0.13849124 | X9: =IF($T9<=0,0, SUMIFS(MA!$K:$K, MA!$E:$E, "CORREGEDORIA", MA!$A:$A, $A9, MA!$C:$C, $C9) / $T9) -> 0.058319257 | Y9: =IF($U9<=0,0, SUMIFS(MA!$K:$K, MA!$E:$E, "ESCOLA PENAL", MA!$A:$A, $A9, MA!$C:$C, $C9) / $U9) -> 0.40454528 | Z9: =N9+O9+P9 -> 93916.3
A10: PB | B10: Convênio | C10: 937818 | D10: 2022 | E10: 08016024920202270 | F10: 46484 | G10: 1 | H10: SIM | I10: 317757.09 | J10: 317439.34 | K10: 317.75 | L10: 317439.34 | N10: 51081.15 | O10: =IFERROR(SUMIFS(INDIRECT("'"&$A10&"'!M:M"),INDIRECT("'"&$A10&"'!F:F"),"CAPITAL"),0) -> 0 | P10: =IFERROR(SUMIFS(INDIRECT("'"&$A10&"'!M:M"),INDIRECT("'"&$A10&"'!F:F"),"CUSTEIO"),0) -> 0 | Q10: 317.75 | R10: =IFERROR(SUMIFS(PB!$K:$K, PB!$A:$A, $A10, PB!$C:$C, $C10), 0) -> 31085 | S10: =IFERROR(SUMIFS(PB!$J:$J, PB!$E:$E, "OUVIDORIA", PB!$A:$A, $A10, PB!$C:$C, $C10), 0) -> 27434.02 | T10: =IFERROR(SUMIFS(PB!$J:$J, PB!$E:$E, "CORREGEDORIA", PB!$A:$A, $A10, PB!$C:$C, $C10), 0) -> 95535.05 | U10: =IFERROR(SUMIFS(PB!$J:$J, PB!$E:$E, "ESCOLA PENAL", PB!$A:$A, $A10, PB!$C:$C, $C10), 0) -> 194788.02 | V10: =IFERROR($S10/$I10,0) -> 0.086336453 | W10: =IF($S10<=0,0, SUMIFS(PB!$K:$K, PB!$E:$E, "OUVIDORIA", PB!$A:$A, $A10, PB!$C:$C, $C10) / $S10) -> 0.096959906 | X10: =IF($T10<=0,0, SUMIFS(PB!$K:$K, PB!$E:$E, "CORREGEDORIA", PB!$A:$A, $A10, PB!$C:$C, $C10) / $T10) -> 0 | Y10: =IF($U10<=0,0, SUMIFS(PB!$K:$K, PB!$E:$E, "ESCOLA PENAL", PB!$A:$A, $A10, PB!$C:$C, $C10) / $U10) -> 0.14592787 | Z10: =N10+O10+P10 -> 51081.15
A11: PI | B11: Convênio | C11: 937780 | D11: 2022 | E11: 08016024995202251 | F11: 46484 | G11: 1 | H11: SIM | I11: 408371.26 | J11: 387952.7 | K11: 20418.56 | L11: 387952.7 | N11: 39771.71 | O11: =IFERROR(SUMIFS(INDIRECT("'"&$A11&"'!M:M"),INDIRECT("'"&$A11&"'!F:F"),"CAPITAL"),0) -> 5.03 | P11: =IFERROR(SUMIFS(INDIRECT("'"&$A11&"'!M:M"),INDIRECT("'"&$A11&"'!F:F"),"CUSTEIO"),0) -> 98.2 | Q11: 20418.56 | R11: =IFERROR(SUMIFS(PI!$K:$K, PI!$A:$A, $A11, PI!$C:$C, $C11), 0) -> 26473.8 | S11: =IFERROR(SUMIFS(PI!$J:$J, PI!$E:$E, "OUVIDORIA", PI!$A:$A, $A11, PI!$C:$C, $C11), 0) -> 44450.77 | T11: =IFERROR(SUMIFS(PI!$J:$J, PI!$E:$E, "CORREGEDORIA", PI!$A:$A, $A11, PI!$C:$C, $C11), 0) -> 169138 | U11: =IFERROR(SUMIFS(PI!$J:$J, PI!$E:$E, "ESCOLA PENAL", PI!$A:$A, $A11, PI!$C:$C, $C11), 0) -> 194777.46 | V11: =IFERROR($S11/$I11,0) -> 0.10884892 | W11: =IF($S11<=0,0, SUMIFS(PI!$K:$K, PI!$E:$E, "OUVIDORIA", PI!$A:$A, $A11, PI!$C:$C, $C11) / $S11) -> 0 | X11: =IF($T11<=0,0, SUMIFS(PI!$K:$K, PI!$E:$E, "CORREGEDORIA", PI!$A:$A, $A11, PI!$C:$C, $C11) / $T11) -> 0 | Y11: =IF($U11<=0,0, SUMIFS(PI!$K:$K, PI!$E:$E, "ESCOLA PENAL", PI!$A:$A, $A11, PI!$C:$C, $C11) / $U11) -> 0.13591819 | Z11: =N11+O11+P11 -> 39874.94
A12: RO | B12: Convênio | C12: 937917 | D12: 2022 | E12: 08016024924202258 | F12: 46484 | G12: 1 | H12: SIM | I12: 234072.01 | J12: 233837.94 | K12: 234.07 | L12: 233837.94 | N12: 29398.8 | O12: =IFERROR(SUMIFS(INDIRECT("'"&$A12&"'!M:M"),INDIRECT("'"&$A12&"'!F:F"),"CAPITAL"),0) -> 0 | P12: =IFERROR(SUMIFS(INDIRECT("'"&$A12&"'!M:M"),INDIRECT("'"&$A12&"'!F:F"),"CUSTEIO"),0) -> 15004.16 | Q12: 234.07 | R12: =IFERROR(SUMIFS(RO!$K:$K, RO!$A:$A, $A12, RO!$C:$C, $C12), 0) -> 13450 | S12: =IFERROR(SUMIFS(RO!$J:$J, RO!$E:$E, "OUVIDORIA", RO!$A:$A, $A12, RO!$C:$C, $C12), 0) -> 86734.48 | T12: =IFERROR(SUMIFS(RO!$J:$J, RO!$E:$E, "CORREGEDORIA", RO!$A:$A, $A12, RO!$C:$C, $C12), 0) -> 61475.44 | U12: =IFERROR(SUMIFS(RO!$J:$J, RO!$E:$E, "ESCOLA PENAL", RO!$A:$A, $A12, RO!$C:$C, $C12), 0) -> 85862.09 | V12: =IFERROR($S12/$I12,0) -> 0.37054614 | W12: =IF($S12<=0,0, SUMIFS(RO!$K:$K, RO!$E:$E, "OUVIDORIA", RO!$A:$A, $A12, RO!$C:$C, $C12) / $S12) -> 0.15507097 | X12: =IF($T12<=0,0, SUMIFS(RO!$K:$K, RO!$E:$E, "CORREGEDORIA", RO!$A:$A, $A12, RO!$C:$C, $C12) / $T12) -> 0 | Y12: =IF($U12<=0,0, SUMIFS(RO!$K:$K, RO!$E:$E, "ESCOLA PENAL", RO!$A:$A, $A12, RO!$C:$C, $C12) / $U12) -> 0 | Z12: =N12+O12+P12 -> 44402.96
A13: TO | B13: Convênio | C13: 937468 | D13: 2022 | E13: 08016024985202215 | F13: 46484 | G13: 1 | H13: SIM | I13: 265260.78 | J13: 259498.63 | K13: 5762.15 | L13: 259498.63 | N13: 26794.48 | O13: =IFERROR(SUMIFS(INDIRECT("'"&$A13&"'!M:M"),INDIRECT("'"&$A13&"'!F:F"),"CAPITAL"),0) -> -1118.97 | P13: =IFERROR(SUMIFS(INDIRECT("'"&$A13&"'!M:M"),INDIRECT("'"&$A13&"'!F:F"),"CUSTEIO"),0) -> 13594.58 | Q13: 5762.15 | R13: =IFERROR(SUMIFS(TO!$K:$K, TO!$A:$A, $A13, TO!$C:$C, $C13), 0) -> 17125.91 | S13: =IFERROR(SUMIFS(TO!$J:$J, TO!$E:$E, "OUVIDORIA", TO!$A:$A, $A13, TO!$C:$C, $C13), 0) -> 61018.73 | T13: =IFERROR(SUMIFS(TO!$J:$J, TO!$E:$E, "CORREGEDORIA", TO!$A:$A, $A13, TO!$C:$C, $C13), 0) -> 105826.66 | U13: =IFERROR(SUMIFS(TO!$J:$J, TO!$E:$E, "ESCOLA PENAL", TO!$A:$A, $A13, TO!$C:$C, $C13), 0) -> 104267.81 | V13: =IFERROR($S13/$I13,0) -> 0.23003299 | W13: =IF($S13<=0,0, SUMIFS(TO!$K:$K, TO!$E:$E, "OUVIDORIA", TO!$A:$A, $A13, TO!$C:$C, $C13) / $S13) -> 0.022026024 | X13: =IF($T13<=0,0, SUMIFS(TO!$K:$K, TO!$E:$E, "CORREGEDORIA", TO!$A:$A, $A13, TO!$C:$C, $C13) / $T13) -> 0.11305195 | Y13: =IF($U13<=0,0, SUMIFS(TO!$K:$K, TO!$E:$E, "ESCOLA PENAL", TO!$A:$A, $A13, TO!$C:$C, $C13) / $U13) -> 0.036617246 | Z13: =N13+O13+P13 -> 39270.09
A14: RJ | B14: Convênio | C14: 937817 | D14: 2022 | E14: 08016024874202217 | F14: 46484 | G14: 3 | H14: SIM | I14: 1583018.9 | J14: 1415055.8 | K14: 66621.71 | L14: 1415055.8 | M14: 101341.43 | N14: 85306.29 | O14: =IFERROR(SUMIFS(INDIRECT("'"&$A14&"'!M:M"),INDIRECT("'"&$A14&"'!F:F"),"CAPITAL"),0) -> 69167.97 | P14: =IFERROR(SUMIFS(INDIRECT("'"&$A14&"'!M:M"),INDIRECT("'"&$A14&"'!F:F"),"CUSTEIO"),0) -> 27463.27 | Q14: 66621.71 | R14: =IFERROR(SUMIFS(RJ!$K:$K, RJ!$A:$A, $A14, RJ!$C:$C, $C14), 0) -> 153079.45 | S14: =IFERROR(SUMIFS(RJ!$J:$J, RJ!$E:$E, "OUVIDORIA", RJ!$A:$A, $A14, RJ!$C:$C, $C14), 0) -> 323838.9 | T14: =IFERROR(SUMIFS(RJ!$J:$J, RJ!$E:$E, "CORREGEDORIA", RJ!$A:$A, $A14, RJ!$C:$C, $C14), 0) -> 601790.9 | U14: =IFERROR(SUMIFS(RJ!$J:$J, RJ!$E:$E, "ESCOLA PENAL", RJ!$A:$A, $A14, RJ!$C:$C, $C14), 0) -> 657205.77 | V14: =IFERROR($S14/$I14,0) -> 0.20457045 | W14: =IF($S14<=0,0, SUMIFS(RJ!$K:$K, RJ!$E:$E, "OUVIDORIA", RJ!$A:$A, $A14, RJ!$C:$C, $C14) / $S14) -> 0 | X14: =IF($T14<=0,0, SUMIFS(RJ!$K:$K, RJ!$E:$E, "CORREGEDORIA", RJ!$A:$A, $A14, RJ!$C:$C, $C14) / $T14) -> 0 | Y14: =IF($U14<=0,0, SUMIFS(RJ!$K:$K, RJ!$E:$E, "ESCOLA PENAL", RJ!$A:$A, $A14, RJ!$C:$C, $C14) / $U14) -> 0.23292469 | Z14: =N14+O14+P14 -> 181937.53
A15: AL | B15: Convênio | C15: 937221 | D15: 2022 | E15: 08016025053202290 | F15: 46484 | G15: 1 | H15: SIM | I15: 171603.5 | J15: 156000 | K15: 15600 | L15: 156000 | M15: 3.5 | N15: 17567.06 | O15: =IFERROR(SUMIFS(INDIRECT("'"&$A15&"'!M:M"),INDIRECT("'"&$A15&"'!F:F"),"CAPITAL"),0) -> 3.5 | P15: =IFERROR(SUMIFS(INDIRECT("'"&$A15&"'!M:M"),INDIRECT("'"&$A15&"'!F:F"),"CUSTEIO"),0) -> 0 | Q15: 15600 | R15: =IFERROR(SUMIFS(AL!$K:$K, AL!$A:$A, $A15, AL!$C:$C, $C15), 0) -> 0 | S15: =IFERROR(SUMIFS(AL!$J:$J, AL!$E:$E, "OUVIDORIA", AL!$A:$A, $A15, AL!$C:$C, $C15), 0) -> 39023.53 | T15: =IFERROR(SUMIFS(AL!$J:$J, AL!$E:$E, "CORREGEDORIA", AL!$A:$A, $A15, AL!$C:$C, $C15), 0) -> 63936.47 | U15: =IFERROR(SUMIFS(AL!$J:$J, AL!$E:$E, "ESCOLA PENAL", AL!$A:$A, $A15, AL!$C:$C, $C15), 0) -> 68640 | V15: =IFERROR($S15/$I15,0) -> 0.22740521 | W15: =IF($S15<=0,0, SUMIFS(AL!$K:$K, AL!$E:$E, "OUVIDORIA", AL!$A:$A, $A15, AL!$C:$C, $C15) / $S15) -> 0 | X15: =IF($T15<=0,0, SUMIFS(AL!$K:$K, AL!$E:$E, "CORREGEDORIA", AL!$A:$A, $A15, AL!$C:$C, $C15) / $T15) -> 0 | Y15: =IF($U15<=0,0, SUMIFS(AL!$K:$K, AL!$E:$E, "ESCOLA PENAL", AL!$A:$A, $A15, AL!$C:$C, $C15) / $U15) -> 0 | Z15: =N15+O15+P15 -> 17570.56
A16: SC | B16: Convênio | C16: 937783 | D16: 2022 | E16: 08016025010202212 | F16: 46484 | G16: 1 | H16: SIM | I16: 581020.22 | J16: 569399.82 | K16: 11620.4 | L16: 569399.82 | N16: 8232.23 | O16: =IFERROR(SUMIFS(INDIRECT("'"&$A16&"'!M:M"),INDIRECT("'"&$A16&"'!F:F"),"CAPITAL"),0) -> 18488.15 | P16: =IFERROR(SUMIFS(INDIRECT("'"&$A16&"'!M:M"),INDIRECT("'"&$A16&"'!F:F"),"CUSTEIO"),0) -> 92886.88 | Q16: 11620.4 | R16: =IFERROR(SUMIFS(SC!$K:$K, SC!$A:$A, $A16, SC!$C:$C, $C16), 0) -> 44897.82 | S16: =IFERROR(SUMIFS(SC!$J:$J, SC!$E:$E, "OUVIDORIA", SC!$A:$A, $A16, SC!$C:$C, $C16), 0) -> 140216.7 | T16: =IFERROR(SUMIFS(SC!$J:$J, SC!$E:$E, "CORREGEDORIA", SC!$A:$A, $A16, SC!$C:$C, $C16), 0) -> 147416.7 | U16: =IFERROR(SUMIFS(SC!$J:$J, SC!$E:$E, "ESCOLA PENAL", SC!$A:$A, $A16, SC!$C:$C, $C16), 0) -> 182011.85 | V16: =IFERROR($S16/$I16,0) -> 0.24132843 | W16: =IF($S16<=0,0, SUMIFS(SC!$K:$K, SC!$E:$E, "OUVIDORIA", SC!$A:$A, $A16, SC!$C:$C, $C16) / $S16) -> 0 | X16: =IF($T16<=0,0, SUMIFS(SC!$K:$K, SC!$E:$E, "CORREGEDORIA", SC!$A:$A, $A16, SC!$C:$C, $C16) / $T16) -> 0 | Y16: =IF($U16<=0,0, SUMIFS(SC!$K:$K, SC!$E:$E, "ESCOLA PENAL", SC!$A:$A, $A16, SC!$C:$C, $C16) / $U16) -> 0.24667526 | Z16: =N16+O16+P16 -> 119607.26

Sheet IND_PRORROG
A1: DADOS GERAIS | H1: INDICADORES GERAIS | N1: OUVIDORIA | P1: CORREGEDORIA | R1: ESCOLA PENAL
A2: UF | B2: NÚMERO | C2: VALOR GLOBAL | D2: VALOR EXECUTADO GERAL | E2: VALOR PREVISTO OUVIDORIA | F2: VALOR PREVISTO CORREGEDORIA | G2: VALOR PREVISTO ESCOLA PENAL | H2: IND 01 EXECUÇÃO | I2: IND 02 COMPLEX. DESPESA RESIDUAL | J2: IND 03 REGULAR. RSE | K2: IND 04 CONCENTRAÇÃO PROCESSUAL | L2: IND 05 MATURIDADE PROCESSUAL RESIDUAL | M2: IND 06 TEMPESTIVIDADE RELATIVA DA LICITAÇÃO | N2: IND 07 EXECUÇÃO OUVIDORIA | O2: IND 08 COMPLEX. DESPESA RESIDUAL | P2: IND 09 EXECUÇÃO CORREGEDORIA | Q2: IND 10 COMPLEX. DESPESA RESIDUAL | R2: IND 11 EXECUÇÃO ESCOLA PENAL | S2: IND 12 COMPLEX. DESPESA RESIDUAL
A3: MT | B3: 937698 | C3: 392509.71 | D3: =IFERROR(SUMIFS(MT!$K:$K, MT!$A:$A, $A3, MT!$C:$C, $B3), 0) -> 337453.87 | E3: =IFERROR(SUMIFS(MT!$J:$J, MT!$E:$E, "OUVIDORIA", MT!$A:$A, $A3, MT!$C:$C, $B3), 0) -> 119503.74 | F3: =IFERROR(SUMIFS(MT!$J:$J, MT!$E:$E, "CORREGEDORIA", MT!$A:$A, $A3, MT!$C:$C, $B3), 0) -> 108156 | G3: =IFERROR(SUMIFS(MT!$J:$J, MT!$E:$E, "ESCOLA PENAL", MT!$A:$A, $A3, MT!$C:$C, $B3), 0) -> 164850 | H3: =D3/C3 -> 0.85973381 | I3: Baixa Complexidade Apenas bens | J3: SIM | K3: Alta Concentração (Eficiente) Todos os itens pendentes estão agrupados em 1 único processo | L3: Alta Maturidade (Favorável) Licitação Publicada, Homologada ou Adesão a ARP confirmada | M3: Tempestivo Dentro de 12 meses do último ajuste | N3: =IF($E3<=0,0, SUMIFS(MT!$K:$K, MT!$E:$E, "OUVIDORIA", MT!$A:$A, $A3, MT!$C:$C, $B3) / $E3) -> 0.59108786 | O3: Baixa Complexidade Apenas bens | P3: =IF($F3<=0,0, SUMIFS(MT!$K:$K, MT!$E:$E, "CORREGEDORIA", MT!$A:$A, $A3, MT!$C:$C, $B3) / $F3) -> 0.94277396 | Q3: Baixa Complexidade Apenas bens | R3: =IF($G3<=0,0, SUMIFS(MT!$K:$K, MT!$E:$E, "ESCOLA PENAL", MT!$A:$A, $A3, MT!$C:$C, $B3) / $G3) -> 1 | S3: Baixa Complexidade Apenas bens
A4: GO | B4: 937216 | C4: 388852.48 | D4: =IFERROR(SUMIFS(GO!$K:$K, GO!$A:$A, $A4, GO!$C:$C, $B4), 0) -> 323819.27 | E4: =IFERROR(SUMIFS(GO!$J:$J, GO!$E:$E, "OUVIDORIA", GO!$A:$A, $A4, GO!$C:$C, $B4), 0) -> 106486 | F4: =IFERROR(SUMIFS(GO!$J:$J, GO!$E:$E, "CORREGEDORIA", GO!$A:$A, $A4, GO!$C:$C, $B4), 0) -> 87246.81 | G4: =IFERROR(SUMIFS(GO!$J:$J, GO!$E:$E, "ESCOLA PENAL", GO!$A:$A, $A4, GO!$C:$C, $B4), 0) -> 161086.33 | H4: =D4/C4 -> 0.83275609 | I4: Baixa Complexidade Apenas bens | J4: SIM | K4: Alta Concentração (Eficiente) Todos os itens pendentes estão agrupados em 1 único processo | L4: Alta Maturidade (Favorável) Licitação Publicada, Homologada ou Adesão a ARP confirmada | M4: Tempestivo Dentro de 12 meses do último ajuste | N4: =IF($E4<=0,0, SUMIFS(GO!$K:$K, GO!$E:$E, "OUVIDORIA", GO!$A:$A, $A4, GO!$C:$C, $B4) / $E4) -> 1 | O4: Baixa Complexidade Apenas bens | P4: =IF($F4<=0,0, SUMIFS(GO!$K:$K, GO!$E:$E, "CORREGEDORIA", GO!$A:$A, $A4, GO!$C:$C, $B4) / $F4) -> 0.73634979 | Q4: Baixa Complexidade Apenas bens | R4: =IF($G4<=0,0, SUMIFS(GO!$K:$K, GO!$E:$E, "ESCOLA PENAL", GO!$A:$A, $A4, GO!$C:$C, $B4) / $G4) -> 0.95035438 | S4: Baixa Complexidade Apenas bens
A5: PR | B5: 937871 | C5: 861700.16 | D5: =IFERROR(SUMIFS(PR!$K:$K, PR!$A:$A, $A5, PR!$C:$C, $B5), 0) -> 485239.8 | E5: =IFERROR(SUMIFS(PR!$J:$J, PR!$E:$E, "OUVIDORIA", PR!$A:$A, $A5, PR!$C:$C, $B5), 0) -> 161317.98 | F5: =IFERROR(SUMIFS(PR!$J:$J, PR!$E:$E, "CORREGEDORIA", PR!$A:$A, $A5, PR!$C:$C, $B5), 0) -> 322820.85 | G5: =IFERROR(SUMIFS(PR!$J:$J, PR!$E:$E, "ESCOLA PENAL", PR!$A:$A, $A5, PR!$C:$C, $B5), 0) -> 334677.35 | H5: =D5/C5 -> 0.56311908 | I5: Média Complexidade Majoritariamente bens | J5: SIM | K5: Dispersão Processual Necessidade de mais de 4 processos ou processos não abertos | L5: Alta Maturidade (Favorável) Licitação Publicada, Homologada ou Adesão a ARP confirmada | M5: Tempestivo Dentro de 12 meses do último ajuste | N5: =IF($E5<=0,0, SUMIFS(PR!$K:$K, PR!$E:$E, "OUVIDORIA", PR!$A:$A, $A5, PR!$C:$C, $B5) / $E5) -> 0.096053521 | O5: Média Complexidade Majoritariamente bens | P5: =IF($F5<=0,0, SUMIFS(PR!$K:$K, PR!$E:$E, "CORREGEDORIA", PR!$A:$A, $A5, PR!$C:$C, $B5) / $F5) -> 0.7990272 | Q5: Média Complexidade Majoritariamente bens | R5: =IF($G5<=0,0, SUMIFS(PR!$K:$K, PR!$E:$E, "ESCOLA PENAL", PR!$A:$A, $A5, PR!$C:$C, $B5) / $G5) -> 0.6328543 | S5: Baixa Complexidade Apenas bens
A6: AM | B6: 937592 | C6: 300300 | D6: =IFERROR(SUMIFS(AM!$K$1:$K$24, AM!$A$1:$A$24, $A6, AM!$C$1:$C$24, $B6), 0) -> 223899.78 | E6: =IFERROR(SUMIFS(AM!$J$1:$J$24, AM!$E$1:$E$24, "OUVIDORIA", AM!$A$1:$A$24, $A6, AM!$C$1:$C$24, $B6), 0) -> 57507.98 | F6: =IFERROR(SUMIFS(AM!$J$1:$J$24, AM!$E$1:$E$24, "CORREGEDORIA", AM!$A$1:$A$24, $A6, AM!$C$1:$C$24, $B6), 0) -> 15129.7 | G6: =IFERROR(SUMIFS(AM!$J$1:$J$24, AM!$E$1:$E$24, "ESCOLA PENAL", AM!$A$1:$A$24, $A6, AM!$C$1:$C$24, $B6), 0) -> 227662.32 | H6: =D6/C6 -> 0.74558701 | I6: Alta Complexidade Bens e serviços ou apenas serviços | J6: SIM | K6: Alta Concentração (Eficiente) Todos os itens pendentes estão agrupados em 1 único processo | L6: Média Maturidade Termo de Referência (TR) inserido ou em análise jurídica local | M6: Atrasado Mais de 18 meses desde o último ajuste | N6: =IF($E6<=0,0, SUMIFS(AM!$K$1:$K$24, AM!$E$1:$E$24, "OUVIDORIA", AM!$A$1:$A$24, $A6, AM!$C$1:$C$24, $B6) / $E6) -> 0.7953677 | O6: - | P6: =IF($F6<=0,0, SUMIFS(AM!$K$1:$K$24, AM!$E$1:$E$24, "CORREGEDORIA", AM!$A$1:$A$24, $A6, AM!$C$1:$C$24, $B6) / $F6) -> 0.80371653 | Q6: - | R6: =IF($G6<=0,0, SUMIFS(AM!$K$1:$K$24, AM!$E$1:$E$24, "ESCOLA PENAL", AM!$A$1:$A$24, $A6, AM!$C$1:$C$24, $B6) / $G6) -> 0.72914921 | S6: Alta Complexidade Bens e serviços ou apenas serviços
A7: RS | B7: 937925 | C7: 1273294.7 | D7: =IFERROR(SUMIFS(#REF!,#REF!, $A7,#REF!, $B7), 0) -> 0 | E7: =IFERROR(SUMIFS(#REF!,#REF!, "OUVIDORIA",#REF!, $A7,#REF!, $B7), 0) -> 0 | F7: =IFERROR(SUMIFS(#REF!,#REF!, "CORREGEDORIA",#REF!, $A7,#REF!, $B7), 0) -> 0 | G7: =IFERROR(SUMIFS(#REF!,#REF!, "ESCOLA PENAL",#REF!, $A7,#REF!, $B7), 0) -> 0 | H7: =D7/C7 -> 0 | I7: Alta Complexidade Bens e serviços ou apenas serviços | J7: SIM | K7: Dispersão Processual Necessidade de mais de 4 processos ou processos não abertos | L7: Baixa Maturidade (Risco) Processo não iniciado ou sem registro na Plataforma | M7: Atrasado Mais de 18 meses desde o último ajuste | N7: - | O7: - | P7: =IF($F7<=0,0, SUMIFS(#REF!,#REF!, "CORREGEDORIA",#REF!, $A7,#REF!, $B7) / $F7) -> 0 | Q7: Alta Complexidade Bens e serviços ou apenas serviços | R7: =IF($G7<=0,0, SUMIFS(#REF!,#REF!, "ESCOLA PENAL",#REF!, $A7,#REF!, $B7) / $G7) -> 0 | S7: Baixa Complexidade Apenas bens
A8: AC | B8: 937782 | C8: 153593.71 | D8: =IFERROR(SUMIFS(AC!$L:$L, AC!$A:$A, $A8, AC!$C:$C, $B8), 0) -> 299282.16 | E8: =IFERROR(SUMIFS(AC!$J:$J, AC!$E:$E, "OUVIDORIA", AC!$A:$A, $A8, AC!$C:$C, $B8), 0) -> 242142.01 | F8: =IFERROR(SUMIFS(AC!$J:$J, AC!$E:$E, "CORREGEDORIA", AC!$A:$A, $A8, AC!$C:$C, $B8), 0) -> 44590.76 | G8: =IFERROR(SUMIFS(AC!$J:$J, AC!$E:$E, "ESCOLA PENAL", AC!$A:$A, $A8, AC!$C:$C, $B8), 0) -> 109681.1 | H8: =D8/C8 -> 1.9485314 | I8: Média Complexidade Majoritariamente bens | J8: SIM | K8: Dispersão Processual Necessidade de mais de 4 processos ou processos não abertos | L8: Alta Maturidade (Favorável) Licitação Publicada, Homologada ou Adesão a ARP confirmada | M8: Tempestivo Dentro de 12 meses do último ajuste | N8: =IF($E8<=0,0, SUMIFS(AC!$K:$K, AC!$E:$E, "OUVIDORIA", AC!$A:$A, $A8, AC!$C:$C, $B8) / $E8) -> 0.14701596 | O8: Baixa Complexidade Apenas bens | P8: =IF($F8<=0,0, SUMIFS(AC!$K:$K, AC!$E:$E, "CORREGEDORIA", AC!$A:$A, $A8, AC!$C:$C, $B8) / $F8) -> 0.85938813 | Q8: Baixa Complexidade Apenas bens | R8: =IF($G8<=0,0, SUMIFS(AC!$K:$K, AC!$E:$E, "ESCOLA PENAL", AC!$A:$A, $A8, AC!$C:$C, $B8) / $G8) -> 0.21172326 | S8: Média Complexidade Majoritariamente bens
A9: MG | B9: 937878 | C9: 968858.15 | D9: =IFERROR(SUMIFS(#REF!,#REF!, $A9,#REF!, $B9), 0) -> 0 | E9: =IFERROR(SUMIFS(#REF!,#REF!, "OUVIDORIA",#REF!, $A9,#REF!, $B9), 0) -> 0 | F9: =IFERROR(SUMIFS(#REF!,#REF!, "CORREGEDORIA",#REF!, $A9,#REF!, $B9), 0) -> 0 | G9: =IFERROR(SUMIFS(#REF!,#REF!, "ESCOLA PENAL",#REF!, $A9,#REF!, $B9), 0) -> 0 | H9: =D9/C9 -> 0 | I9: Alta Complexidade Bens e serviços ou apenas serviços | J9: SIM | K9: Dispersão Processual Necessidade de mais de 4 processos ou processos não abertos | L9: Baixa Maturidade (Risco) Processo não iniciado ou sem registro na Plataforma | M9: Atenção 12 a 18 meses na fase interna. | N9: - | O9: - | P9: =IF($F9<=0,0, SUMIFS(#REF!,#REF!, "CORREGEDORIA",#REF!, $A9,#REF!, $B9) / $F9) -> 0 | Q9: Alta Complexidade Bens e serviços ou apenas serviços | R9: =IF($G9<=0,0, SUMIFS(#REF!,#REF!, "ESCOLA PENAL",#REF!, $A9,#REF!, $B9) / $G9) -> 0 | S9: Baixa Complexidade Apenas bens
A10: MS | B10: 937265 | C10: 548000 | D10: =IFERROR(SUMIFS(MS!$K:$K, MS!$A:$A, $A10, MS!$C:$C, $B10), 0) -> 311441.88 | E10: =IFERROR(SUMIFS(MS!$J:$J, MS!$E:$E, "OUVIDORIA", MS!$A:$A, $A10, MS!$C:$C, $B10), 0) -> 127595.47 | F10: =IFERROR(SUMIFS(MS!$J:$J, MS!$E:$E, "CORREGEDORIA", MS!$A:$A, $A10, MS!$C:$C, $B10), 0) -> 120294.2 | G10: =IFERROR(SUMIFS(MS!$J:$J, MS!$E:$E, "ESCOLA PENAL", MS!$A:$A, $A10, MS!$C:$C, $B10), 0) -> 300110.33 | H10: =D10/C10 -> 0.5683246 | I10: Baixa Complexidade Apenas bens | J10: SIM | K10: Dispersão Processual Necessidade de mais de 4 processos ou processos não abertos | L10: Alta Maturidade (Favorável) Licitação Publicada, Homologada ou Adesão a ARP confirmada | M10: Tempestivo Dentro de 12 meses do último ajuste | N10: =IF($E10<=0,0, SUMIFS(MS!$K:$K, MS!$E:$E, "OUVIDORIA", MS!$A:$A, $A10, MS!$C:$C, $B10) / $E10) -> 0.71172817 | O10: Baixa Complexidade Apenas bens | P10: =IF($F10<=0,0, SUMIFS(MS!$K:$K, MS!$E:$E, "CORREGEDORIA", MS!$A:$A, $A10, MS!$C:$C, $B10) / $F10) -> 0.063471888 | Q10: Baixa Complexidade Apenas bens | R10: =IF($G10<=0,0, SUMIFS(MS!$K:$K, MS!$E:$E, "ESCOLA PENAL", MS!$A:$A, $A10, MS!$C:$C, $B10) / $G10) -> 0.70971662 | S10: Baixa Complexidade Apenas bens
A11: SP | B11: 938128 | C11: 3846559.5 | D11: =IFERROR(SUMIFS(SP!$K:$K, SP!$A:$A, $A11, SP!$C:$C, $B11), 0) -> 1068101.9 | E11: =IFERROR(SUMIFS(SP!$J:$J, SP!$E:$E, "OUVIDORIA", SP!$A:$A, $A11, SP!$C:$C, $B11), 0) -> 27513.73 | F11: =IFERROR(SUMIFS(SP!$J:$J, SP!$E:$E, "CORREGEDORIA", SP!$A:$A, $A11, SP!$C:$C, $B11), 0) -> 542449.85 | G11: =IFERROR(SUMIFS(SP!$J:$J, SP!$E:$E, "ESCOLA PENAL", SP!$A:$A, $A11, SP!$C:$C, $B11), 0) -> 2195566.9 | H11: =D11/C11 -> 0.27767721 | I11: Alta Complexidade Bens e serviços ou apenas serviços | J11: SIM | K11: Dispersão Processual Necessidade de mais de 4 processos ou processos não abertos | L11: Alta Maturidade (Favorável) Licitação Publicada, Homologada ou Adesão a ARP confirmada | M11: Atenção 12 a 18 meses na fase interna. | N11: =IF($E11<=0,0, SUMIFS(SP!$K:$K, SP!$E:$E, "OUVIDORIA", SP!$A:$A, $A11, SP!$C:$C, $B11) / $E11) -> 0.72996428 | O11: Baixa Complexidade Apenas bens | P11: =IF($F11<=0,0, SUMIFS(SP!$K:$K, SP!$E:$E, "CORREGEDORIA", SP!$A:$A, $A11, SP!$C:$C, $B11) / $F11) -> 0.082606125 | Q11: Alta Complexidade Bens e serviços ou apenas serviços | R11: =IF($G11<=0,0, SUMIFS(SP!$K:$K, SP!$E:$E, "ESCOLA PENAL", SP!$A:$A, $A11, SP!$C:$C, $B11) / $G11) -> 0.45692446 | S11: Média Complexidade Majoritariamente bens
A12: MA | B12: 938277 | C12: 346697.9 | D12: =IFERROR(SUMIFS(MA!$K:$K, MA!$A:$A, $A12, MA!$C:$C, $B12), 0) -> 69485.85 | E12: =IFERROR(SUMIFS(MA!$J:$J, MA!$E:$E, "OUVIDORIA", MA!$A:$A, $A12, MA!$C:$C, $B12), 0) -> 105039.86 | F12: =IFERROR(SUMIFS(MA!$J:$J, MA!$E:$E, "CORREGEDORIA", MA!$A:$A, $A12, MA!$C:$C, $B12), 0) -> 108270.24 | G12: =IFERROR(SUMIFS(MA!$J:$J, MA!$E:$E, "ESCOLA PENAL", MA!$A:$A, $A12, MA!$C:$C, $B12), 0) -> 120195.47 | H12: =D12/C12 -> 0.20042189 | I12: Média Complexidade Majoritariamente bens | J12: NÃO | K12: Dispersão Processual Necessidade de mais de 4 processos ou processos não abertos | L12: Baixa Maturidade (Risco) Processo não iniciado ou sem registro na Plataforma | M12: Atrasado Mais de 18 meses desde o último ajuste | N12: =IF($E12<=0,0, SUMIFS(MA!$K:$K, MA!$E:$E, "OUVIDORIA", MA!$A:$A, $A12, MA!$C:$C, $B12) / $E12) -> 0.13849124 | O12: Baixa Complexidade Apenas bens | P12: =IF($F12<=0,0, SUMIFS(MA!$K:$K, MA!$E:$E, "CORREGEDORIA", MA!$A:$A, $A12, MA!$C:$C, $B12) / $F12) -> 0.058319257 | Q12: Média Complexidade Majoritariamente bens | R12: =IF($G12<=0,0, SUMIFS(MA!$K:$K, MA!$E:$E, "ESCOLA PENAL", MA!$A:$A, $A12, MA!$C:$C, $B12) / $G12) -> 0.40454528 | S12: Baixa Complexidade Apenas bens
A13: PB | B13: 937818 | C13: 317757.09 | D13: =IFERROR(SUMIFS(PB!$K:$K, PB!$A:$A, $A13, PB!$C:$C, $B13), 0) -> 31085 | E13: =IFERROR(SUMIFS(PB!$J:$J, PB!$E:$E, "OUVIDORIA", PB!$A:$A, $A13, PB!$C:$C, $B13), 0) -> 27434.02 | F13: =IFERROR(SUMIFS(PB!$J:$J, PB!$E:$E, "CORREGEDORIA", PB!$A:$A, $A13, PB!$C:$C, $B13), 0) -> 95535.05 | G13: =IFERROR(SUMIFS(PB!$J:$J, PB!$E:$E, "ESCOLA PENAL", PB!$A:$A, $A13, PB!$C:$C, $B13), 0) -> 194788.02 | H13: =D13/C13 -> 0.097826299 | I13: Alta Complexidade Bens e serviços ou apenas serviços | J13: NÃO | K13: Dispersão Processual Necessidade de mais de 4 processos ou processos não abertos | L13: Baixa Maturidade (Risco) Processo não iniciado ou sem registro na Plataforma | M13: Tempestivo Dentro de 12 meses do último ajuste | N13: =IF($E13<=0,0, SUMIFS(PB!$K:$K, PB!$E:$E, "OUVIDORIA", PB!$A:$A, $A13, PB!$C:$C, $B13) / $E13) -> 0.096959906 | O13: Baixa Complexidade Apenas bens | P13: =IF($F13<=0,0, SUMIFS(PB!$K:$K, PB!$E:$E, "CORREGEDORIA", PB!$A:$A, $A13, PB!$C:$C, $B13) / $F13) -> 0 | Q13: Alta Complexidade Bens e serviços ou apenas serviços | R13: =IF($G13<=0,0, SUMIFS(PB!$K:$K, PB!$E:$E, "ESCOLA PENAL", PB!$A:$A, $A13, PB!$C:$C, $B13) / $G13) -> 0.14592787 | S13: Baixa Complexidade Apenas bens
A14: PI | B14: 937780 | C14: 408371.26 | D14: =IFERROR(SUMIFS(PI!$K:$K, PI!$A:$A, $A14, PI!$C:$C, $B14), 0) -> 26473.8 | E14: =IFERROR(SUMIFS(PI!$J:$J, PI!$E:$E, "OUVIDORIA", PI!$A:$A, $A14, PI!$C:$C, $B14), 0) -> 44450.77 | F14: =IFERROR(SUMIFS(PI!$J:$J, PI!$E:$E, "CORREGEDORIA", PI!$A:$A, $A14, PI!$C:$C, $B14), 0) -> 169138 | G14: =IFERROR(SUMIFS(PI!$J:$J, PI!$E:$E, "ESCOLA PENAL", PI!$A:$A, $A14, PI!$C:$C, $B14), 0) -> 194777.46 | H14: =D14/C14 -> 0.064827775 | I14: Média Complexidade Majoritariamente bens | J14: SIM | K14: Dispersão Processual Necessidade de mais de 4 processos ou processos não abertos | L14: Baixa Maturidade (Risco) Processo não iniciado ou sem registro na Plataforma | M14: Atrasado Mais de 18 meses desde o último ajuste | N14: =IF($E14<=0,0, SUMIFS(PI!$K:$K, PI!$E:$E, "OUVIDORIA", PI!$A:$A, $A14, PI!$C:$C, $B14) / $E14) -> 0 | O14: Baixa Complexidade Apenas bens | P14: =IF($F14<=0,0, SUMIFS(PI!$K:$K, PI!$E:$E, "CORREGEDORIA", PI!$A:$A, $A14, PI!$C:$C, $B14) / $F14) -> 0 | Q14: Média Complexidade Majoritariamente bens | R14: =IF($G14<=0,0, SUMIFS(PI!$K:$K, PI!$E:$E, "ESCOLA PENAL", PI!$A:$A, $A14, PI!$C:$C, $B14) / $G14) -> 0.13591819 | S14: Baixa Complexidade Apenas bens
A15: RO | B15: 937917 | C15: 234072.01 | D15: =IFERROR(SUMIFS(RO!$K:$K, RO!$A:$A, $A15, RO!$C:$C, $B15), 0) -> 13450 | E15: =IFERROR(SUMIFS(RO!$J:$J, RO!$E:$E, "OUVIDORIA", RO!$A:$A, $A15, RO!$C:$C, $B15), 0) -> 86734.48 | F15: =IFERROR(SUMIFS(RO!$J:$J, RO!$E:$E, "CORREGEDORIA", RO!$A:$A, $A15, RO!$C:$C, $B15), 0) -> 61475.44 | G15: =IFERROR(SUMIFS(RO!$J:$J, RO!$E:$E, "ESCOLA PENAL", RO!$A:$A, $A15, RO!$C:$C, $B15), 0) -> 85862.09 | H15: =D15/C15 -> 0.05746095 | I15: Baixa Complexidade Apenas bens | J15: SIM | K15: Dispersão Processual Necessidade de mais de 4 processos ou processos não abertos | L15: Baixa Maturidade (Risco) Processo não iniciado ou sem registro na Plataforma | M15: Atrasado Mais de 18 meses desde o último ajuste | N15: =IF($E15<=0,0, SUMIFS(RO!$K:$K, RO!$E:$E, "OUVIDORIA", RO!$A:$A, $A15, RO!$C:$C, $B15) / $E15) -> 0.15507097 | O15: Baixa Complexidade Apenas bens | P15: =IF($F15<=0,0, SUMIFS(RO!$K:$K, RO!$E:$E, "CORREGEDORIA", RO!$A:$A, $A15, RO!$C:$C, $B15) / $F15) -> 0 | Q15: Baixa Complexidade Apenas bens | R15: =IF($G15<=0,0, SUMIFS(RO!$K:$K, RO!$E:$E, "ESCOLA PENAL", RO!$A:$A, $A15, RO!$C:$C, $B15) / $G15) -> 0 | S15: Baixa Complexidade Apenas bens
A16: TO | B16: 937468 | C16: 265260.78 | D16: =IFERROR(SUMIFS(TO!$K:$K, TO!$A:$A, $A16, TO!$C:$C, $B16), 0) -> 17125.91 | E16: =IFERROR(SUMIFS(TO!$J:$J, TO!$E:$E, "OUVIDORIA", TO!$A:$A, $A16, TO!$C:$C, $B16), 0) -> 61018.73 | F16: =IFERROR(SUMIFS(TO!$J:$J, TO!$E:$E, "CORREGEDORIA", TO!$A:$A, $A16, TO!$C:$C, $B16), 0) -> 105826.66 | G16: =IFERROR(SUMIFS(TO!$J:$J, TO!$E:$E, "ESCOLA PENAL", TO!$A:$A, $A16, TO!$C:$C, $B16), 0) -> 104267.81 | H16: =D16/C16 -> 0.064562541 | I16: Baixa Complexidade Apenas bens | J16: NÃO | K16: Dispersão Processual Necessidade de mais de 4 processos ou processos não abertos | L16: Baixa Maturidade (Risco) Processo não iniciado ou sem registro na Plataforma | M16: Atrasado Mais de 18 meses desde o último ajuste | N16: =IF($E16<=0,0, SUMIFS(TO!$K:$K, TO!$E:$E, "OUVIDORIA", TO!$A:$A, $A16, TO!$C:$C, $B16) / $E16) -> 0.022026024 | O16: Baixa Complexidade Apenas bens | P16: =IF($F16<=0,0, SUMIFS(TO!$K:$K, TO!$E:$E, "CORREGEDORIA", TO!$A:$A, $A16, TO!$C:$C, $B16) / $F16) -> 0.11305195 | Q16: Baixa Complexidade Apenas bens | R16: =IF($G16<=0,0, SUMIFS(TO!$K:$K, TO!$E:$E, "ESCOLA PENAL", TO!$A:$A, $A16, TO!$C:$C, $B16) / $G16) -> 0.036617246 | S16: Baixa Complexidade Apenas bens
A17: RJ | B17: 937817 | C17: 1583018.9 | D17: =IFERROR(SUMIFS(RJ!$K:$K, RJ!$A:$A, $A17, RJ!$C:$C, $B17), 0) -> 153079.45 | E17: =IFERROR(SUMIFS(RJ!$J:$J, RJ!$E:$E, "OUVIDORIA", RJ!$A:$A, $A17, RJ!$C:$C, $B17), 0) -> 323838.9 | F17: =IFERROR(SUMIFS(RJ!$J:$J, RJ!$E:$E, "CORREGEDORIA", RJ!$A:$A, $A17, RJ!$C:$C, $B17), 0) -> 601790.9 | G17: =IFERROR(SUMIFS(RJ!$J:$J, RJ!$E:$E, "ESCOLA PENAL", RJ!$A:$A, $A17, RJ!$C:$C, $B17), 0) -> 657205.77 | H17: =D17/C17 -> 0.09670096 | I17: Baixa Complexidade Apenas bens | J17: SIM | K17: Dispersão Processual Necessidade de mais de 4 processos ou processos não abertos | L17: Alta Maturidade (Favorável) Licitação Publicada, Homologada ou Adesão a ARP confirmada | M17: Atrasado Mais de 18 meses desde o último ajuste | N17: =IF($E17<=0,0, SUMIFS(RJ!$K:$K, RJ!$E:$E, "OUVIDORIA", RJ!$A:$A, $A17, RJ!$C:$C, $B17) / $E17) -> 0 | O17: Baixa Complexidade Apenas bens | P17: =IF($F17<=0,0, SUMIFS(RJ!$K:$K, RJ!$E:$E, "CORREGEDORIA", RJ!$A:$A, $A17, RJ!$C:$C, $B17) / $F17) -> 0 | Q17: Baixa Complexidade Apenas bens | R17: =IF($G17<=0,0, SUMIFS(RJ!$K:$K, RJ!$E:$E, "ESCOLA PENAL", RJ!$A:$A, $A17, RJ!$C:$C, $B17) / $G17) -> 0.23292469 | S17: Baixa Complexidade Apenas bens
A18: SC | B18: 937783 | C18: 581020.22 | D18: =IFERROR(SUMIFS(SC!$K:$K, SC!$A:$A, $A18, SC!$C:$C, $B18), 0) -> 44897.82 | E18: =IFERROR(SUMIFS(SC!$J:$J, SC!$E:$E, "OUVIDORIA", SC!$A:$A, $A18, SC!$C:$C, $B18), 0) -> 140216.7 | F18: =IFERROR(SUMIFS(SC!$J:$J, SC!$E:$E, "CORREGEDORIA", SC!$A:$A, $A18, SC!$C:$C, $B18), 0) -> 147416.7 | G18: =IFERROR(SUMIFS(SC!$J:$J, SC!$E:$E, "ESCOLA PENAL", SC!$A:$A, $A18, SC!$C:$C, $B18), 0) -> 182011.85 | H18: =D18/C18 -> 0.077274109 | I18: Baixa Complexidade Apenas bens | J18: SIM | K18: Dispersão Processual Necessidade de mais de 4 processos ou processos não abertos | L18: Baixa Maturidade (Risco) Processo não iniciado ou sem registro na Plataforma | M18: Atrasado Mais de 18 meses desde o último ajuste | N18: =IF($E18<=0,0, SUMIFS(SC!$K:$K, SC!$E:$E, "OUVIDORIA", SC!$A:$A, $A18, SC!$C:$C, $B18) / $E18) -> 0 | O18: Baixa Complexidade Apenas bens | P18: =IF($F18<=0,0, SUMIFS(SC!$K:$K, SC!$E:$E, "CORREGEDORIA", SC!$A:$A, $A18, SC!$C:$C, $B18) / $F18) -> 0 | Q18: Baixa Complexidade Apenas bens | R18: =IF($G18<=0,0, SUMIFS(SC!$K:$K, SC!$E:$E, "ESCOLA PENAL", SC!$A:$A, $A18, SC!$C:$C, $B18) / $G18) -> 0.24667526 | S18: Alta Complexidade Bens e serviços ou apenas serviços
A19: AL | B19: 937221 | C19: 171603.5 | D19: =IFERROR(SUMIFS(AL!$K:$K, AL!$A:$A, $A19, AL!$C:$C, $B19), 0) -> 0 | E19: =IFERROR(SUMIFS(AL!$J:$J, AL!$E:$E, "OUVIDORIA", AL!$A:$A, $A19, AL!$C:$C, $B19), 0) -> 39023.53 | F19: =IFERROR(SUMIFS(AL!$J:$J, AL!$E:$E, "CORREGEDORIA", AL!$A:$A, $A19, AL!$C:$C, $B19), 0) -> 63936.47 | G19: =IFERROR(SUMIFS(AL!$J:$J, AL!$E:$E, "ESCOLA PENAL", AL!$A:$A, $A19, AL!$C:$C, $B19), 0) -> 68640 | H19: =D19/C19 -> 0 | I19: Alta Complexidade Bens e serviços ou apenas serviços | J19: SIM | K19: Dispersão Processual Necessidade de mais de 4 processos ou processos não abertos | L19: Alta Maturidade (Favorável) Licitação Publicada, Homologada ou Adesão a ARP confirmada | M19: Atrasado Mais de 18 meses desde o último ajuste | N19: =IF($E19<=0,0, SUMIFS(AL!$K:$K, AL!$E:$E, "OUVIDORIA", AL!$A:$A, $A19, AL!$C:$C, $B19) / $E19) -> 0 | O19: Baixa Complexidade Apenas bens | P19: =IF($F19<=0,0, SUMIFS(AL!$K:$K, AL!$E:$E, "CORREGEDORIA", AL!$A:$A, $A19, AL!$C:$C, $B19) / $F19) -> 0 | Q19: Baixa Complexidade Apenas bens | R19: =IF($G19<=0,0, SUMIFS(AL!$K:$K, AL!$E:$E, "ESCOLA PENAL", AL!$A:$A, $A19, AL!$C:$C, $B19) / $G19) -> 0 | S19: Média Complexidade Majoritariamente bens
A20: RN | B20: 937263 | C20: 191556.03 | D20: =IFERROR(SUMIFS(#REF!,#REF!, $A20,#REF!, $B20), 0) -> 0 | E20: =IFERROR(SUMIFS(#REF!,#REF!, "OUVIDORIA",#REF!, $A20,#REF!, $B20), 0) -> 0 | F20: =IFERROR(SUMIFS(#REF!,#REF!, "CORREGEDORIA",#REF!, $A20,#REF!, $B20), 0) -> 0 | G20: =IFERROR(SUMIFS(#REF!,#REF!, "ESCOLA PENAL",#REF!, $A20,#REF!, $B20), 0) -> 0 | H20: =D20/C20 -> 0 | I20: Baixa Complexidade Apenas bens | J20: SIM | K20: Alta Concentração (Eficiente) Todos os itens pendentes estão agrupados em 1 único processo | L20: Alta Maturidade (Favorável) Licitação Publicada, Homologada ou Adesão a ARP confirmada | M20: Tempestivo Dentro de 12 meses do último ajuste | N20: =IF($E20<=0,0, SUMIFS(#REF!,#REF!, "OUVIDORIA",#REF!, $A20,#REF!, $B20) / $E20) -> 0 | O20: Baixa Complexidade Apenas bens | P20: =IF($F20<=0,0, SUMIFS(#REF!,#REF!, "CORREGEDORIA",#REF!, $A20,#REF!, $B20) / $F20) -> 0 | Q20: Baixa Complexidade Apenas bens | R20: =IF($G20<=0,0, SUMIFS(#REF!,#REF!, "ESCOLA PENAL",#REF!, $A20,#REF!, $B20) / $G20) -> 0 | S20: Baixa Complexidade Apenas bens
A21: RR | B21: 937781 | C21: 300000 | D21: =IFERROR(SUMIFS(#REF!,#REF!, $A21,#REF!, $B21), 0) -> 0 | E21: =IFERROR(SUMIFS(#REF!,#REF!, "OUVIDORIA",#REF!, $A21,#REF!, $B21), 0) -> 0 | F21: =IFERROR(SUMIFS(#REF!,#REF!, "CORREGEDORIA",#REF!, $A21,#REF!, $B21), 0) -> 0 | G21: =IFERROR(SUMIFS(#REF!,#REF!, "ESCOLA PENAL",#REF!, $A21,#REF!, $B21), 0) -> 0 | H21: =D21/C21 -> 0 | I21: Média Complexidade Majoritariamente bens | J21: NÃO | K21: Dispersão Processual Necessidade de mais de 4 processos ou processos não abertos | L21: Baixa Maturidade (Risco) Processo não iniciado ou sem registro na Plataforma | M21: Atrasado Mais de 18 meses desde o último ajuste | N21: =IF($E21<=0,0, SUMIFS(#REF!,#REF!, "OUVIDORIA",#REF!, $A21,#REF!, $B21) / $E21) -> 0 | O21: Média Complexidade Majoritariamente bens | P21: =IF($F21<=0,0, SUMIFS(#REF!,#REF!, "CORREGEDORIA",#REF!, $A21,#REF!, $B21) / $F21) -> 0 | Q21: Média Complexidade Majoritariamente bens | R21: =IF($G21<=0,0, SUMIFS(#REF!,#REF!, "ESCOLA PENAL",#REF!, $A21,#REF!, $B21) / $G21) -> 0 | S21: Baixa Complexidade Apenas bens
A22: PA | B22: 938161 | C22: 300579 | D22: =IFERROR(SUMIFS(#REF!,#REF!, $A22,#REF!, $B22), 0) -> 0 | E22: =IFERROR(SUMIFS(#REF!,#REF!, "OUVIDORIA",#REF!, $A22,#REF!, $B22), 0) -> 0 | F22: =IFERROR(SUMIFS(#REF!,#REF!, "CORREGEDORIA",#REF!, $A22,#REF!, $B22), 0) -> 0 | G22: =IFERROR(SUMIFS(#REF!,#REF!, "ESCOLA PENAL",#REF!, $A22,#REF!, $B22), 0) -> 0 | H22: =D22/C22 -> 0 | I22: Baixa Complexidade Apenas bens | J22: SIM | K22: Média Concentração Os itens estão divididos em 2 a 3 processos distintos | L22: Média Maturidade Termo de Referência (TR) inserido ou em análise jurídica local | M22: Atrasado Mais de 18 meses desde o último ajuste | N22: - | O22: - | P22: =IF($F22<=0,0, SUMIFS(#REF!,#REF!, "CORREGEDORIA",#REF!, $A22,#REF!, $B22) / $F22) -> 0 | Q22: Baixa Complexidade Apenas bens | R22: =IF($G22<=0,0, SUMIFS(#REF!,#REF!, "ESCOLA PENAL",#REF!, $A22,#REF!, $B22) / $G22) -> 0 | S22: Baixa Complexidade Apenas bens

Sheet MT
A1: UF | B1: INSTRUMENTO | C1: NÚMERO | D1: ANO | E1: ÁREA | F1: NATUREZA | G1: DESCRIÇÃO | H1: QUANTIDADE | I1: VALOR UNITÁRIO | J1: VALOR TOTAL PREVISTO | K1: VALOR TOTAL EXECUTADO | L1: SALDO | M1: SALDO ECONOMICIDADE
A2: MT | B2: Convênio | C2: 937698 | D2: 2022 | E2: OUVIDORIA | F2: CUSTEIO | G2: Cartilhas, Capa: 29,7x42,2cm, 4x4 cores, | H2: 5700.0 | I2: 7.32 | J2: 41743 | K2: 33573 | L2: 8170 | M2: =IF(E2="N/A", J2, IF(OR(K2=0, ISBLANK(K2), K2=""), 0, J2-K2)) -> 8170
A3: MT | B3: Convênio | C3: 937698 | D3: 2022 | E3: OUVIDORIA | F3: CUSTEIO | G3: Serviço de confecção de Banner, 90x120cm | H3: 316.0 | I3: 75 | J3: 23700 | K3: 7997.96 | L3: 15702.04 | M3: =IF(E3="N/A", J3, IF(OR(K3=0, ISBLANK(K3), K3=""), 0, J3-K3)) -> 15702.04
A4: MT | B4: Convênio | C4: 937698 | D4: 2022 | E4: OUVIDORIA | F4: CUSTEIO | G4: Serviço de confecção de Folders, 45x45cm | H4: 5713.0 | I4: 4.12 | J4: 23556.6 | K4: 1428.25 | L4: 22128.35 | M4: =IF(E4="N/A", J4, IF(OR(K4=0, ISBLANK(K4), K4=""), 0, J4-K4)) -> 22128.35
A5: MT | B5: Convênio | C5: 937698 | D5: 2022 | E5: OUVIDORIA | F5: CAPITAL | G5: ** TA Contrapartida - Computador Desktop | H5: 4.0 | I5: 3462.23 | J5: 13848.91 | K5: 13848.91 | L5: 0 | M5: =IF(E5="N/A", J5, IF(OR(K5=0, ISBLANK(K5), K5=""), 0, J5-K5)) -> 0
A6: MT | B6: Convênio | C6: 937698 | D6: 2022 | E6: OUVIDORIA | F6: CAPITAL | G6: ** TA Contrapartida - Fone ouvido tipo: | H6: 5.0 | I6: 8.58 | J6: 42.88 | K6: 0 | L6: 42.88 | M6: =IF(E6="N/A", J6, IF(OR(K6=0, ISBLANK(K6), K6=""), 0, J6-K6)) -> 0
A7: MT | B7: Convênio | C7: 937698 | D7: 2022 | E7: OUVIDORIA | F7: CAPITAL | G7: Celulares smartphone, 128gb-5g - octa-co | H7: 1.0 | I7: 2057.93 | J7: 2057.93 | K7: 1743 | L7: 314.93 | M7: =IF(E7="N/A", J7, IF(OR(K7=0, ISBLANK(K7), K7=""), 0, J7-K7)) -> 314.93
A8: MT | B8: Convênio | C8: 937698 | D8: 2022 | E8: OUVIDORIA | F8: CAPITAL | G8: Fone ouvido tipo: fechado, dinâmico , im | H8: 5.0 | I8: 170.42 | J8: 852.12 | K8: 895 | L8: -42.88 | M8: =IF(E8="N/A", J8, IF(OR(K8=0, ISBLANK(K8), K8=""), 0, J8-K8)) -> -42.88
A9: MT | B9: Convênio | C9: 937698 | D9: 2022 | E9: OUVIDORIA | F9: CAPITAL | G9: Webcan Full HD para chamadas e gravações | H9: 4.0 | I9: 545.26 | J9: 2181.05 | L9: 2181.05 | M9: =IF(E9="N/A", J9, IF(OR(K9=0, ISBLANK(K9), K9=""), 0, J9-K9)) -> 0
A10: MT | B10: Convênio | C10: 937698 | D10: 2022 | E10: OUVIDORIA | F10: CAPITAL | G10: ** Contrapartida - Computador Desktop Bá | H10: 4.0 | I10: 1996.92 | J10: 7987.69 | K10: 7987.69 | L10: 0 | M10: =IF(E10="N/A", J10, IF(OR(K10=0, ISBLANK(K10), K10=""), 0, J10-K10)) -> 0
A11: MT | B11: Convênio | C11: 937698 | D11: 2022 | E11: ESCOLA PENAL | F11: CAPITAL | G11: ** - Contrapartida - AMBULÂNCIA TIPO FIO | H11: 1.0 | I11: 164850 | J11: 164850 | K11: 164850 | L11: 0 | M11: =IF(E11="N/A", J11, IF(OR(K11=0, ISBLANK(K11), K11=""), 0, J11-K11)) -> 0
A12: MT | B12: Convênio | C12: 937698 | D12: 2022 | E12: CORREGEDORIA | F12: CAPITAL | G12: Veículo transporte pessoal, câmbio: manu | H12: 1.0 | I12: 108156 | J12: 108156 | K12: 101966.66 | L12: 6189.31 | M12: =IF(E12="N/A", J12, IF(OR(K12=0, ISBLANK(K12), K12=""), 0, J12-K12)) -> 6189.34
A13: MT | B13: Convênio | C13: 937698 | D13: 2022 | E13: OUVIDORIA | F13: CAPITAL | G13: Nobreak, alimentador automático de tensã | H13: 5.0 | I13: 706.71 | J13: 3533.56 | K13: 3163.4 | L13: 370.16 | M13: =IF(E13="N/A", J13, IF(OR(K13=0, ISBLANK(K13), K13=""), 0, J13-K13)) -> 370.16

Sheet GO
A1: UF | B1: INSTRUMENTO | C1: NÚMERO | D1: ANO | E1: ÁREA | F1: NATUREZA | G1: DESCRIÇÃO | H1: QUANTIDADE | I1: VALOR UNITÁRIO | J1: VALOR TOTAL PREVISTO | K1: VALOR TOTAL EXECUTADO | L1: SALDO | M1: SALDO ECONOMICIDADE | N1: TOTAL EXECUTADO OUVIDORIA | O1: % OUVIDORIA | P1: TOTAL EXECUTADO OUVIDORIA | Q1: % OUVIDORIA | R1: TOTAL EXECUTADO OUVIDORIA | S1: % OUVIDORIA
A2: GO | B2: Convênio | C2: 937216 | D2: 2022 | E2: ESCOLA PENAL | F2: CUSTEIO | G2: Cola para espuma acústica, cola de conta | H2: 10.0 | I2: 40.58 | J2: 405.8 | K2: 405.8 | M2: =IF(E2="N/A", J2, IF(OR(K2=0, ISBLANK(K2), K2=""), 0, J2-K2)) -> 0
A3: GO | B3: Convênio | C3: 937216 | D3: 2022 | E3: ESCOLA PENAL | F3: CUSTEIO | G3: Espuma Acústica Antichamas, 10 placas, 5 | H3: 10.0 | I3: 340 | J3: 3400 | K3: 3400 | M3: =IF(E3="N/A", J3, IF(OR(K3=0, ISBLANK(K3), K3=""), 0, J3-K3)) -> 0
A4: GO | B4: Convênio | C4: 937216 | D4: 2022 | E4: ESCOLA PENAL | F4: CUSTEIO | G4: Jogo de Pilhas recarregável 1000 Mah AAA | H4: 4.0 | I4: 29 | J4: 116 | K4: 116 | M4: =IF(E4="N/A", J4, IF(OR(K4=0, ISBLANK(K4), K4=""), 0, J4-K4)) -> 0
A5: GO | B5: Convênio | C5: 937216 | D5: 2022 | E5: ESCOLA PENAL | F5: CUSTEIO | G5: Jogo de Pilhas recarregável 2700 Mah AA | H5: 4.0 | I5: 16.6 | J5: 66.4 | K5: 66.4 | M5: =IF(E5="N/A", J5, IF(OR(K5=0, ISBLANK(K5), K5=""), 0, J5-K5)) -> 0
A6: GO | B6: Convênio | C6: 937216 | D6: 2022 | E6: ESCOLA PENAL | F6: CUSTEIO | G6: Munição CBC 5,56X45 COMUM M193 (TREINA) A | H6: 10000.0 | I6: 5.72 | J6: 57200 | K6: 57200 | M6: =IF(E6="N/A", J6, IF(OR(K6=0, ISBLANK(K6), K6=""), 0, J6-K6)) -> 0
A7: GO | B7: Convênio | C7: 937216 | D7: 2022 | E7: ESCOLA PENAL | F7: CUSTEIO | G7: Placas de isopor, forro isolamento termo | H7: 2.0 | I7: 121.76 | J7: 243.52 | K7: 243.52 | M7: =IF(E7="N/A", J7, IF(OR(K7=0, ISBLANK(K7), K7=""), 0, J7-K7)) -> 0
A8: GO | B8: Convênio | C8: 937216 | D8: 2022 | E8: N/A | F8: CAPITAL | G8: Saldo Remanescente - Conforme NOTA TÉCNI | H8: 1.0 | I8: 34033.34 | J8: 34033.34 | K8: 0 | L8: 34033.34 | M8: =IF(E8="N/A", J8, IF(OR(K8=0, ISBLANK(K8), K8=""), 0, J8-K8)) -> 34033.34
A9: GO | B9: Convênio | C9: 937216 | D9: 2022 | E9: ESCOLA PENAL | F9: CAPITAL | G9: Apresentador/Passador de slides, sem fio | H9: 3.0 | I9: 162.88 | J9: 488.64 | K9: 359.94 | L9: 128.7 | M9: =IF(E9="N/A", J9, IF(OR(K9=0, ISBLANK(K9), K9=""), 0, J9-K9)) -> 128.7
A10: GO | B10: Convênio | C10: 937216 | D10: 2022 | E10: ESCOLA PENAL | F10: CAPITAL | G10: Câmera DSLR: com lente EF-S 18-55mm, cap | H10: 1.0 | I10: 5343.33 | J10: 5343.33 | K10: 4679.99 | L10: 663.34 | M10: =IF(E10="N/A", J10, IF(OR(K10=0, ISBLANK(K10), K10=""), 0, J10-K10)) -> 663.34
A11: GO | B11: Convênio | C11: 937216 | D11: 2022 | E11: ESCOLA PENAL | F11: CAPITAL | G11: Câmera de Vídeo, Gravação de vídeos em F | H11: 1.0 | I11: 12064 | J11: 12064 | K11: 6249.99 | L11: 5814.01 | M11: =IF(E11="N/A", J11, IF(OR(K11=0, ISBLANK(K11), K11=""), 0, J11-K11)) -> 5814.01
A12: GO | B12: Convênio | C12: 937216 | D12: 2022 | E12: ESCOLA PENAL | F12: CAPITAL | G12: Estação de trabalho para edição de vídeo | H12: 2.0 | I12: 8390 | J12: 16780 | K12: 16600 | L12: 180 | M12: =IF(E12="N/A", J12, IF(OR(K12=0, ISBLANK(K12), K12=""), 0, J12-K12)) -> 180
A13: GO | B13: Convênio | C13: 937216 | D13: 2022 | E13: ESCOLA PENAL | F13: CAPITAL | G13: Gimbal Estabilizador para câmera DSLR, c | H13: 1.0 | I13: 2006.67 | J13: 2006.67 | K13: 1979.99 | L13: 26.68 | M13: =IF(E13="N/A", J13, IF(OR(K13=0, ISBLANK(K13), K13=""), 0, J13-K13)) -> 26.68
A14: GO | B14: Convênio | C14: 937216 | D14: 2022 | E14: ESCOLA PENAL | F14: CAPITAL | G14: Gravador de Aúdio Portátil, equipado com | H14: 2.0 | I14: 1357.82 | J14: 2715.64 | K14: 2715.62 | L14: 0.02 | M14: =IF(E14="N/A", J14, IF(OR(K14=0, ISBLANK(K14), K14=""), 0, J14-K14)) -> 0.02
A15: GO | B15: Convênio | C15: 937216 | D15: 2022 | E15: ESCOLA PENAL | F15: CAPITAL | G15: Headset, com transdutor dinâmico 53mm co | H15: 5.0 | I15: 425 | J15: 2125 | K15: 1900 | L15: 225 | M15: =IF(E15="N/A", J15, IF(OR(K15=0, ISBLANK(K15), K15=""), 0, J15-K15)) -> 225
A16: GO | B16: Convênio | C16: 937216 | D16: 2022 | E16: CORREGEDORIA | F16: CAPITAL | G16: Kit NVR com 4 câmeras, fonte de energia, | H16: 1.0 | I16: 956.28 | J16: 956.28 | K16: 937.99 | L16: 18.29 | M16: =IF(E16="N/A", J16, IF(OR(K16=0, ISBLANK(K16), K16=""), 0, J16-K16)) -> 18.29
A17: GO | B17: Convênio | C17: 937216 | D17: 2022 | E17: ESCOLA PENAL | F17: CAPITAL | G17: Kit Refletor Led Luz Fria para Estúdio c | H17: 1.0 | I17: 1155.22 | J17: 1155.22 | K17: 1155.21 | L17: 0.01 | M17: =IF(E17="N/A", J17, IF(OR(K17=0, ISBLANK(K17), K17=""), 0, J17-K17)) -> 0.01
A18: GO | B18: Convênio | C18: 937216 | D18: 2022 | E18: ESCOLA PENAL | F18: CAPITAL | G18: Kit Teleprompter (TP), Kit com Estrutura | H18: 1.0 | I18: 657.5 | J18: 657.5 | K18: 629.99 | L18: 27.51 | M18: =IF(E18="N/A", J18, IF(OR(K18=0, ISBLANK(K18), K18=""), 0, J18-K18)) -> 27.51
A19: GO | B19: Convênio | C19: 937216 | D19: 2022 | E19: ESCOLA PENAL | F19: CAPITAL | G19: Kit de tripé de vídeo profissional com c | H19: 1.0 | I19: 1189.91 | J19: 1189.91 | K19: 1169.99 | L19: 19.92 | M19: =IF(E19="N/A", J19, IF(OR(K19=0, ISBLANK(K19), K19=""), 0, J19-K19)) -> 19.92
A20: GO | B20: Convênio | C20: 937216 | D20: 2022 | E20: ESCOLA PENAL | F20: CAPITAL | G20: Lente zoom telefoto, distância focal 70- | H20: 1.0 | I20: 16640 | J20: 16640 | K20: 16640 | M20: =IF(E20="N/A", J20, IF(OR(K20=0, ISBLANK(K20), K20=""), 0, J20-K20)) -> 0
A21: GO | B21: Convênio | C21: 937216 | D21: 2022 | E21: ESCOLA PENAL | F21: CAPITAL | G21: Mesa de som com 6 canais, sendo 4 canais | H21: 1.0 | I21: 699.59 | J21: 699.59 | K21: 690 | L21: 9.59 | M21: =IF(E21="N/A", J21, IF(OR(K21=0, ISBLANK(K21), K21=""), 0, J21-K21)) -> 9.59
A22: GO | B22: Convênio | C22: 937216 | D22: 2022 | E22: ESCOLA PENAL | F22: CAPITAL | G22: Microfone super uni-direcional para uso | H22: 2.0 | I22: 242 | J22: 484 | K22: 419.98 | L22: 64.02 | M22: =IF(E22="N/A", J22, IF(OR(K22=0, ISBLANK(K22), K22=""), 0, J22-K22)) -> 64.02
A23: GO | B23: Convênio | C23: 937216 | D23: 2022 | E23: ESCOLA PENAL | F23: CAPITAL | G23: Monitor LED, mínimo 27, conexões DVI-D ( | H23: 4.0 | I23: 1805.33 | J23: 7221.32 | K23: 3270.64 | L23: 7221.32 | M23: =IF(E23="N/A", J23, IF(OR(K23=0, ISBLANK(K23), K23=""), 0, J23-K23)) -> 3950.68
A24: GO | B24: Convênio | C24: 937216 | D24: 2022 | E24: ESCOLA PENAL | F24: CAPITAL | G24: Monitor de Áudio, amplificador com potên | H24: 1.0 | I24: 890.65 | J24: 890.65 | K24: 849.99 | L24: 40.66 | M24: =IF(E24="N/A", J24, IF(OR(K24=0, ISBLANK(K24), K24=""), 0, J24-K24)) -> 40.66
A25: GO | B25: Convênio | C25: 937216 | D25: 2022 | E25: CORREGEDORIA | F25: CAPITAL | G25: Projetor 3.400 Lumens (no mínimo) Conexã | H25: 2.0 | I25: 4509.64 | J25: 9019.28 | K25: 7360 | L25: 1659.28 | M25: =IF(E25="N/A", J25, IF(OR(K25=0, ISBLANK(K25), K25=""), 0, J25-K25)) -> 1659.28
A26: GO | B26: Convênio | C26: 937216 | D26: 2022 | E26: ESCOLA PENAL | F26: CAPITAL | G26: Sistema de microfone headset (sem fio), | H26: 1.0 | I26: 1571.77 | J26: 1571.77 | K26: 1289.99 | L26: 281.78 | M26: =IF(E26="N/A", J26, IF(OR(K26=0, ISBLANK(K26), K26=""), 0, J26-K26)) -> 281.78
A27: GO | B27: Convênio | C27: 937216 | D27: 2022 | E27: ESCOLA PENAL | F27: CAPITAL | G27: Switcher de vídeo com barra de transição | H27: 1.0 | I27: 3800 | J27: 3800 | K27: 3200 | L27: 600 | M27: =IF(E27="N/A", J27, IF(OR(K27=0, ISBLANK(K27), K27=""), 0, J27-K27)) -> 600
A28: GO | B28: Convênio | C28: 937216 | D28: 2022 | E28: CORREGEDORIA | F28: CAPITAL | G28: TV 42, Recursos/Funcionalidades, Resolu | H28: 1.0 | I28: 1775.9 | J28: 1775.9 | K28: 1533.2 | L28: 242.7 | M28: =IF(E28="N/A", J28, IF(OR(K28=0, ISBLANK(K28), K28=""), 0, J28-K28)) -> 242.7
A29: GO | B29: Convênio | C29: 937216 | D29: 2022 | E29: ESCOLA PENAL | F29: CAPITAL | G29: TV 55, 4K UHD, mínimo 3 entradas HDMI 2. | H29: 2.0 | I29: 2753.03 | J29: 5506.06 | K29: 4666.8 | L29: 839.26 | M29: =IF(E29="N/A", J29, IF(OR(K29=0, ISBLANK(K29), K29=""), 0, J29-K29)) -> 839.26
A30: GO | B30: Convênio | C30: 937216 | D30: 2022 | E30: ESCOLA PENAL | F30: CAPITAL | G30: Tecido Fundo Infinito Verde, 3,00m Largu | H30: 2.0 | I30: 539.56 | J30: 1079.12 | K30: 1079.1 | L30: 0.02 | M30: =IF(E30="N/A", J30, IF(OR(K30=0, ISBLANK(K30), K30=""), 0, J30-K30)) -> 0.02
A31: GO | B31: Convênio | C31: 937216 | D31: 2022 | E31: CORREGEDORIA | F31: CAPITAL | G31: Webcam, Especificações: - Resolução máxi | H31: 12.0 | I31: 326.33 | J31: 3915.96 | K31: 3480 | L31: 435.96 | M31: =IF(E31="N/A", J31, IF(OR(K31=0, ISBLANK(K31), K31=""), 0, J31-K31)) -> 435.96
A32: GO | B32: Convênio | C32: 937216 | D32: 2022 | E32: ESCOLA PENAL | F32: CAPITAL | G32: Cartão de Memória Micro SD, 32Gb, com ad | H32: 4.0 | I32: 35.58 | J32: 142.32 | K32: 148 | L32: -5.68 | M32: =IF(E32="N/A", J32, IF(OR(K32=0, ISBLANK(K32), K32=""), 0, J32-K32)) -> -5.68
A33: GO | B33: Convênio | C33: 937216 | D33: 2022 | E33: ESCOLA PENAL | F33: CAPITAL | G33: Cartão de memória SD 32Gb, classe 10 | H33: 4.0 | I33: 37.83 | J33: 151.32 | K33: 139.96 | L33: 11.36 | M33: =IF(E33="N/A", J33, IF(OR(K33=0, ISBLANK(K33), K33=""), 0, J33-K33)) -> 11.36
A34: GO | B34: Convênio | C34: 937216 | D34: 2022 | E34: CORREGEDORIA | F34: CAPITAL | G34: HD Externo, Características: Capacidade: | H34: 9.0 | I34: 650 | J34: 5850 | K34: 5850 | M34: =IF(E34="N/A", J34, IF(OR(K34=0, ISBLANK(K34), K34=""), 0, J34-K34)) -> 0
A35: GO | B35: Convênio | C35: 937216 | D35: 2022 | E35: ESCOLA PENAL | F35: CAPITAL | G35: Kit mouse + teclado com fio, padrão ABNT2 | H35: 2.0 | I35: 73.33 | J35: 146.66 | K35: 115.98 | L35: 30.68 | M35: =IF(E35="N/A", J35, IF(OR(K35=0, ISBLANK(K35), K35=""), 0, J35-K35)) -> 30.68
A36: GO | B36: Convênio | C36: 937216 | D36: 2022 | E36: CORREGEDORIA | F36: CAPITAL | G36: Notebook, Com arquitetura x86 corporativ | H36: 6.0 | I36: 5146.52 | J36: 30879.12 | K36: 27000 | L36: 3879.12 | M36: =IF(E36="N/A", J36, IF(OR(K36=0, ISBLANK(K36), K36=""), 0, J36-K36)) -> 3879.12
A37: GO | B37: Convênio | C37: 937216 | D37: 2022 | E37: ESCOLA PENAL | F37: CAPITAL | G37: Notebook; Sistema Operacional: Proprietá | H37: 1.0 | I37: 3949.83 | J37: 3949.83 | K37: 3750 | L37: 3949.83 | M37: =IF(E37="N/A", J37, IF(OR(K37=0, ISBLANK(K37), K37=""), 0, J37-K37)) -> 199.83
A38: GO | B38: Convênio | C38: 937216 | D38: 2022 | E38: ESCOLA PENAL | F38: CAPITAL | G38: Tablet, Display Super AMOLED 14,6, TFT, | H38: 1.0 | I38: 5263.33 | J38: 5263.33 | K38: 10394.56 | L38: 83.33 | M38: =IF(E38="N/A", J38, IF(OR(K38=0, ISBLANK(K38), K38=""), 0, J38-K38)) -> -5131.23
A39: GO | B39: Convênio | C39: 937216 | D39: 2022 | E39: CORREGEDORIA | F39: CAPITAL | G39: Tablet, características mínimas: Process | H39: 4.0 | I39: 1827 | J39: 7308 | K39: 0 | L39: 7308 | M39: =IF(E39="N/A", J39, IF(OR(K39=0, ISBLANK(K39), K39=""), 0, J39-K39)) -> 0
A40: GO | B40: Convênio | C40: 937216 | D40: 2022 | E40: CORREGEDORIA | F40: CAPITAL | G40: Armário tipo Locker Roupeiro 20 Portas A | H40: 1.0 | I40: 1510.39 | J40: 1510.39 | K40: 1490 | L40: 20.39 | M40: =IF(E40="N/A", J40, IF(OR(K40=0, ISBLANK(K40), K40=""), 0, J40-K40)) -> 20.39
A41: GO | B41: Convênio | C41: 937216 | D41: 2022 | E41: CORREGEDORIA | F41: CAPITAL | G41: Cadeira Base Giratória Cor: Preto Materi | H41: 6.0 | I41: 789.2 | J41: 4735.2 | K41: 1500 | L41: 3235.2 | M41: =IF(E41="N/A", J41, IF(OR(K41=0, ISBLANK(K41), K41=""), 0, J41-K41)) -> 3235.2
A42: GO | B42: Convênio | C42: 937216 | D42: 2022 | E42: CORREGEDORIA | F42: CAPITAL | G42: Cadeira Escritório Presidente Giratória. | H42: 10.0 | I42: 924.4 | J42: 9244 | K42: 4600 | L42: 4644 | M42: =IF(E42="N/A", J42, IF(OR(K42=0, ISBLANK(K42), K42=""), 0, J42-K42)) -> 4644
A43: GO | B43: Convênio | C43: 937216 | D43: 2022 | E43: CORREGEDORIA | F43: CAPITAL | G43: Cadeira fixa de Palito - tubular em aço | H43: 15.0 | I43: 232.35 | J43: 3485.25 | K43: 2910 | L43: 575.25 | M43: =IF(E43="N/A", J43, IF(OR(K43=0, ISBLANK(K43), K43=""), 0, J43-K43)) -> 575.25
A44: GO | B44: Convênio | C44: 937216 | D44: 2022 | E44: ESCOLA PENAL | F44: CAPITAL | G44: Cadeira tipo Gamer; Acompanhada de 1 alm | H44: 5.0 | I44: 1417.26 | J44: 7086.3 | K44: 7086.25 | L44: 0.05 | M44: =IF(E44="N/A", J44, IF(OR(K44=0, ISBLANK(K44), K44=""), 0, J44-K44)) -> 0.05
A45: GO | B45: Convênio | C45: 937216 | D45: 2022 | E45: OUVIDORIA | F45: CAPITAL | G45: Automóvel de transporte de passageiros - | H45: 1.0 | I45: 106486 | J45: 106486 | K45: 106486 | M45: =IF(E45="N/A", J45, IF(OR(K45=0, ISBLANK(K45), K45=""), 0, J45-K45)) -> 0
A46: GO | B46: Convênio | C46: 937216 | D46: 2022 | E46: ESCOLA PENAL | F46: CAPITAL | G46: Carregador de Pilhas recarregáveis forma | H46: 1.0 | I46: 91.1 | J46: 91.1 | K46: 91.1 | M46: =IF(E46="N/A", J46, IF(OR(K46=0, ISBLANK(K46), K46=""), 0, J46-K46)) -> 0
A47: GO | B47: Convênio | C47: 937216 | D47: 2022 | E47: CORREGEDORIA | F47: CAPITAL | G47: Fechadura Eletrônica. Especificação Técn | H47: 4.0 | I47: 1189.51 | J47: 4758.04 | K47: 3795 | L47: 963.04 | M47: =IF(E47="N/A", J47, IF(OR(K47=0, ISBLANK(K47), K47=""), 0, J47-K47)) -> 963.04
A48: GO | B48: Convênio | C48: 937216 | D48: 2022 | E48: CORREGEDORIA | F48: CAPITAL | G48: Filtro Bebedouro. Características, Gabin | H48: 1.0 | I48: 770.73 | J48: 770.73 | K48: 770 | L48: 0.73 | M48: =IF(E48="N/A", J48, IF(OR(K48=0, ISBLANK(K48), K48=""), 0, J48-K48)) -> 0.73
A49: GO | B49: Convênio | C49: 937216 | D49: 2022 | E49: ESCOLA PENAL | F49: CAPITAL | G49: Fonte Adaptador AC Eliminador de bateri | H49: 1.0 | I49: 74.33 | J49: 74.33 | K49: 74.32 | L49: 0.01 | M49: =IF(E49="N/A", J49, IF(OR(K49=0, ISBLANK(K49), K49=""), 0, J49-K49)) -> 0.01
A50: GO | B50: Convênio | C50: 937216 | D50: 2022 | E50: CORREGEDORIA | F50: CAPITAL | G50: Fragmentadora de papel com as seguintes | H50: 2.0 | I50: 1519.33 | J50: 3038.66 | K50: 3017.98 | L50: 20.68 | M50: =IF(E50="N/A", J50, IF(OR(K50=0, ISBLANK(K50), K50=""), 0, J50-K50)) -> 20.68
A51: GO | B51: Convênio | C51: 937216 | D51: 2022 | E51: ESCOLA PENAL | F51: CAPITAL | G51: Mochila para transporte de Câmera, capac | H51: 1.0 | I51: 331 | J51: 331 | K51: 309.99 | L51: 21.01 | M51: =IF(E51="N/A", J51, IF(OR(K51=0, ISBLANK(K51), K51=""), 0, J51-K51)) -> 21.01

Sheet PR
A1: UF | B1: INSTRUMENTO | C1: NÚMERO | D1: ANO | E1: ÁREA | F1: NATUREZA | G1: DESCRIÇÃO | H1: QUANTIDADE | I1: VALOR UNITÁRIO | J1: VALOR TOTAL PREVISTO | K1: VALOR TOTAL EXECUTADO | L1: SALDO | M1: SALDO ECONOMICIDADE
A2: PR | B2: Convênio | C2: 937871 | D2: 2022 | E2: CORREGEDORIA | F2: CUSTEIO | G2: * Curso de Pós Graduação Processo Admini | H2: 20.0 | I2: 2555.28 | J2: 51105.53 | L2: =J2-K2 -> 51105.53 | M2: =IF(E2="N/A", J2, IF(OR(K2=0, ISBLANK(K2), K2=""), 0, J2-K2)) -> 0
A3: PR | B3: Convênio | C3: 937871 | D3: 2022 | E3: OUVIDORIA | F3: CUSTEIO | G3: Curso de Pós Graduação em Compliance e L | H3: 2.0 | I3: 4224.67 | J3: 8449.33 | L3: =J3-K3 -> 8449.33 | M3: =IF(E3="N/A", J3, IF(OR(K3=0, ISBLANK(K3), K3=""), 0, J3-K3)) -> 0
A4: PR | B4: Convênio | C4: 937871 | D4: 2022 | E4: CORREGEDORIA | F4: CAPITAL | G4: Ar Condicionado | H4: 2 | I4: 2195.72 | J4: =H4*I4 -> 4391.44 | L4: =J4-K4 -> 4391.44 | M4: =IF(E4="N/A", J4, IF(OR(K4=0, ISBLANK(K4), K4=""), 0, J4-K4)) -> 0
A5: PR | B5: Convênio | C5: 937871 | D5: 2022 | E5: ESCOLA PENAL | F5: CAPITAL | G5: Ar Condicionado | H5: 5 | I5: 2195.72 | J5: =H5*I5 -> 10978.6 | L5: =J5-K5 -> 10978.6 | M5: =IF(E5="N/A", J5, IF(OR(K5=0, ISBLANK(K5), K5=""), 0, J5-K5)) -> 0
A6: PR | B6: Convênio | C6: 937871 | D6: 2022 | E6: OUVIDORIA | F6: CAPITAL | G6: Ar Condicionado | H6: 1 | I6: 2195.72 | J6: =H6*I6 -> 2195.72 | L6: =J6-K6 -> 2195.72 | M6: =IF(E6="N/A", J6, IF(OR(K6=0, ISBLANK(K6), K6=""), 0, J6-K6)) -> 0
A7: PR | B7: Convênio | C7: 937871 | D7: 2022 | E7: CORREGEDORIA | F7: CAPITAL | G7: Gravador de Voz | H7: 12 | I7: 390.53 | J7: =H7*I7 -> 4686.36 | K7: 2951.88 | L7: =J7-K7 -> 1734.48 | M7: =IF(E7="N/A", J7, IF(OR(K7=0, ISBLANK(K7), K7=""), 0, J7-K7)) -> 1734.48
A8: PR | B8: Convênio | C8: 937871 | D8: 2022 | E8: OUVIDORIA | F8: CAPITAL | G8: Gravador de Voz | H8: 4 | I8: 390.53 | J8: =H8*I8 -> 1562.12 | K8: 983.96 | L8: =J8-K8 -> 578.16 | M8: =IF(E8="N/A", J8, IF(OR(K8=0, ISBLANK(K8), K8=""), 0, J8-K8)) -> 578.16
A9: PR | B9: Convênio | C9: 937871 | D9: 2022 | E9: N/A | F9: CAPITAL | G9: Saldo Remanescente de Capital 44 | H9: 1.0 | I9: 42884.02 | J9: 42884.02 | K9: 0 | L9: =J9-K9 -> 42884.02 | M9: =IF(E9="N/A", J9, IF(OR(K9=0, ISBLANK(K9), K9=""), 0, J9-K9)) -> 42884.02
A10: PR | B10: Convênio | C10: 937871 | D10: 2022 | E10: OUVIDORIA | F10: CAPITAL | G10: Televisão | H10: 1.0 | I10: 3351.47 | J10: 3351.47 | L10: =J10-K10 -> 3351.47 | M10: =IF(E10="N/A", J10, IF(OR(K10=0, ISBLANK(K10), K10=""), 0, J10-K10)) -> 0
A11: PR | B11: Convênio | C11: 937871 | D11: 2022 | E11: CORREGEDORIA | F11: CAPITAL | G11: Viva-Voz | H11: 4.0 | I11: 1112.78 | J11: 4451.12 | L11: =J11-K11 -> 4451.12 | M11: =IF(E11="N/A", J11, IF(OR(K11=0, ISBLANK(K11), K11=""), 0, J11-K11)) -> 0
A12: PR | B12: Convênio | C12: 937871 | D12: 2022 | E12: CORREGEDORIA | F12: CAPITAL | G12: Fone de Ouvido | H12: 12 | I12: 70.8 | J12: =H12*I12 -> 849.6 | K12: 849.6 | L12: =J12-K12 -> 0 | M12: =IF(E12="N/A", J12, IF(OR(K12=0, ISBLANK(K12), K12=""), 0, J12-K12)) -> 0
A13: PR | B13: Convênio | C13: 937871 | D13: 2022 | E13: OUVIDORIA | F13: CAPITAL | G13: Fone de Ouvido | H13: 4 | I13: 70.8 | J13: =H13*I13 -> 283.2 | K13: 283.2 | L13: =J13-K13 -> 0 | M13: =IF(E13="N/A", J13, IF(OR(K13=0, ISBLANK(K13), K13=""), 0, J13-K13)) -> 0
A14: PR | B14: Convênio | C14: 937871 | D14: 2022 | E14: ESCOLA PENAL | F14: CAPITAL | G14: Projetor de Vídeo | H14: 12 | I14: 4682.86 | J14: =H14*I14 -> 56194.32 | L14: =J14-K14 -> 56194.32 | M14: =IF(E14="N/A", J14, IF(OR(K14=0, ISBLANK(K14), K14=""), 0, J14-K14)) -> 0
A15: PR | B15: Convênio | C15: 937871 | D15: 2022 | E15: OUVIDORIA | F15: CAPITAL | G15: Projetor de Vídeo | H15: 1 | I15: 4682.86 | J15: =H15*I15 -> 4682.86 | L15: =J15-K15 -> 4682.86 | M15: =IF(E15="N/A", J15, IF(OR(K15=0, ISBLANK(K15), K15=""), 0, J15-K15)) -> 0
A16: PR | B16: Convênio | C16: 937871 | D16: 2022 | E16: CORREGEDORIA | F16: CAPITAL | G16: Web Cam | H16: 12 | I16: 266.3 | J16: =H16*I16 -> 3195.6 | L16: =J16-K16 -> 3195.6 | M16: =IF(E16="N/A", J16, IF(OR(K16=0, ISBLANK(K16), K16=""), 0, J16-K16)) -> 0
A17: PR | B17: Convênio | C17: 937871 | D17: 2022 | E17: OUVIDORIA | F17: CAPITAL | G17: Web Cam | H17: 4 | I17: 266.3 | J17: =H17*I17 -> 1065.2 | L17: =J17-K17 -> 1065.2 | M17: =IF(E17="N/A", J17, IF(OR(K17=0, ISBLANK(K17), K17=""), 0, J17-K17)) -> 0
A18: PR | B18: Convênio | C18: 937871 | D18: 2022 | E18: ESCOLA PENAL | F18: CAPITAL | G18: Notebook | H18: 12 | I18: 3557 | J18: =H18*I18 -> 42684 | K18: 42684 | L18: =J18-K18 -> 0 | M18: =IF(E18="N/A", J18, IF(OR(K18=0, ISBLANK(K18), K18=""), 0, J18-K18)) -> 0
A19: PR | B19: Convênio | C19: 937871 | D19: 2022 | E19: CORREGEDORIA | F19: CAPITAL | G19: Notebook | H19: 12 | I19: 3557 | J19: =H19*I19 -> 42684 | K19: 42684 | L19: =J19-K19 -> 0 | M19: =IF(E19="N/A", J19, IF(OR(K19=0, ISBLANK(K19), K19=""), 0, J19-K19)) -> 0
A20: PR | B20: Convênio | C20: 937871 | D20: 2022 | E20: OUVIDORIA | F20: CAPITAL | G20: Notebook | H20: 4 | I20: 3557 | J20: =H20*I20 -> 14228 | K20: 14228 | L20: =J20-K20 -> 0 | M20: =IF(E20="N/A", J20, IF(OR(K20=0, ISBLANK(K20), K20=""), 0, J20-K20)) -> 0
A21: PR | B21: Convênio | C21: 937871 | D21: 2022 | E21: OUVIDORIA | F21: CAPITAL | G21: Veículo tipo SUV | H21: 1.0 | I21: 51133.66 | J21: 51133.66 | L21: =J21-K21 -> 51133.66 | M21: =IF(E21="N/A", J21, IF(OR(K21=0, ISBLANK(K21), K21=""), 0, J21-K21)) -> 0
A22: PR | B22: Convênio | C22: 937871 | D22: 2022 | E22: OUVIDORIA | F22: CAPITAL | G22: Veículo tipo SUV | H22: 1.0 | I22: 74366.42 | J22: 74366.42 | L22: =J22-K22 -> 74366.42 | M22: =IF(E22="N/A", J22, IF(OR(K22=0, ISBLANK(K22), K22=""), 0, J22-K22)) -> 0
A23: PR | B23: Convênio | C23: 937871 | D23: 2022 | E23: CORREGEDORIA | F23: CAPITAL | G23: Viatura Descaracterizada (SUV) | H23: 2.0 | I23: 105728.6 | J23: 211457.2 | K23: 211457.16 | L23: =J23-K23 -> 0.04 | M23: =IF(E23="N/A", J23, IF(OR(K23=0, ISBLANK(K23), K23=""), 0, J23-K23)) -> 0.04
A24: PR | B24: Convênio | C24: 937871 | D24: 2022 | E24: ESCOLA PENAL | F24: CAPITAL | G24: Viatura Descaracterizada - (Pick - Up) | H24: 1.0 | I24: 169118 | J24: 169118 | K24: 169118 | L24: =J24-K24 -> 0 | M24: =IF(E24="N/A", J24, IF(OR(K24=0, ISBLANK(K24), K24=""), 0, J24-K24)) -> 0
A25: PR | B25: Convênio | C25: 937871 | D25: 2022 | E25: ESCOLA PENAL | F25: CAPITAL | G25: Tela Digital | H25: 1.0 | I25: 19389.93 | J25: 19389.93 | L25: =J25-K25 -> 19389.93 | M25: =IF(E25="N/A", J25, IF(OR(K25=0, ISBLANK(K25), K25=""), 0, J25-K25)) -> 0
A26: PR | B26: Convênio | C26: 937871 | D26: 2022 | E26: ESCOLA PENAL | F26: CAPITAL | G26: Tela Elétrica | H26: 10.0 | I26: 3631.25 | J26: 36312.5 | L26: =J26-K26 -> 36312.5 | M26: =IF(E26="N/A", J26, IF(OR(K26=0, ISBLANK(K26), K26=""), 0, J26-K26)) -> 0

Sheet AM
A1: UF | B1: INSTRUMENTO | C1: NÚMERO | D1: ANO | E1: ÁREA | F1: NATUREZA | G1: DESCRIÇÃO | H1: QUANTIDADE | I1: VALOR UNITÁRIO | J1: VALOR TOTAL PREVISTO | K1: VALOR TOTAL EXECUTADO | L1: SALDO | M1: SALDO ECONOMICIDADE
A2: AM | B2: Convênio | C2: 937592 | D2: 2022 | E2: ESCOLA PENAL | F2: CUSTEIO | G2: Contratação de serviço de pessoa jurídic | H2: 1.0 | I2: 75075 | J2: 75075 | K2: 45900 | L2: 29175 | M2: =IF(E2="N/A", J2, IF(OR(K2=0, ISBLANK(K2), K2=""), 0, J2-K2)) -> 29175
A3: AM | B3: Convênio | C3: 937592 | D3: 2022 | E3: OUVIDORIA | F3: CAPITAL | G3: APARELHO AR-CONDICIONADO, 18.000 BTUs | H3: 1 | I3: 3463.8 | J3: 3463.8 | K3: 3299.99 | L3: 163.81 | M3: =IF(E3="N/A", J3, IF(OR(K3=0, ISBLANK(K3), K3=""), 0, J3-K3)) -> 163.81
A4: AM | B4: Convênio | C4: 937592 | D4: 2022 | E4: ESCOLA PENAL | F4: CAPITAL | G4: CAIXA DE SOM amplificada | H4: 2.0 | I4: 2018.32 | J4: 4036.64 | K4: 3840 | L4: 196.64 | M4: =IF(E4="N/A", J4, IF(OR(K4=0, ISBLANK(K4), K4=""), 0, J4-K4)) -> 196.64
A5: AM | B5: Convênio | C5: 937592 | D5: 2022 | E5: ESCOLA PENAL | F5: CAPITAL | G5: PROJETOR MULTIMÍDIA / Datashow | H5: 2.0 | I5: 3790 | J5: 7580 | K5: 7580 | L5: 0 | M5: =IF(E5="N/A", J5, IF(OR(K5=0, ISBLANK(K5), K5=""), 0, J5-K5)) -> 0
A6: AM | B6: Convênio | C6: 937592 | D6: 2022 | E6: ESCOLA PENAL | F6: CAPITAL | G6: MICROCOMPUTADOR, tipo: Estação de trabalho | H6: 20.0 | I6: 5493.81 | J6: 109876.1 | K6: 79999.8 | L6: 29876.3 | M6: =IF(E6="N/A", J6, IF(OR(K6=0, ISBLANK(K6), K6=""), 0, J6-K6)) -> 29876.3
A7: AM | B7: Convênio | C7: 937592 | D7: 2022 | E7: OUVIDORIA | F7: CAPITAL | G7: NOTEBOOK | H7: 6.0 | I7: 5540.11 | J7: 33240.66 | K7: 27900 | L7: 5340.66 | M7: =IF(E7="N/A", J7, IF(OR(K7=0, ISBLANK(K7), K7=""), 0, J7-K7)) -> 5340.66
A8: AM | B8: Convênio | C8: 937592 | D8: 2022 | E8: ESCOLA PENAL | F8: CAPITAL | G8: CADEIRA FIXA para auditório | H8: 36.0 | I8: 600 | J8: 21600 | K8: 21600 | L8: 0 | M8: =IF(E8="N/A", J8, IF(OR(K8=0, ISBLANK(K8), K8=""), 0, J8-K8)) -> 0
A9: AM | B9: Convênio | C9: 937592 | D9: 2022 | E9: OUVIDORIA | F9: CAPITAL | G9: CADEIRA GIRATÓRIA, modelo: secretária | H9: 4 | I9: 343.13 | J9: =AM!$H9*AM!$I9 -> 1372.52 | K9: 1200 | L9: =AM!$J9-AM!$K9 -> 172.52 | M9: =IF(E9="N/A", J9, IF(OR(K9=0, ISBLANK(K9), K9=""), 0, J9-K9)) -> 172.52
A10: AM | B10: Convênio | C10: 937592 | D10: 2022 | E10: OUVIDORIA | F10: CAPITAL | G10: MESA PARA ESCRITÓRIO, formato: retangular | H10: 7 | I10: 798.8 | J10: =AM!$H10*AM!$I10 -> 5591.6 | K10: 4060 | L10: =AM!$J10-AM!$K10 -> 1531.6 | M10: =IF(E10="N/A", J10, IF(OR(K10=0, ISBLANK(K10), K10=""), 0, J10-K10)) -> 1531.6
A11: AM | B11: Convênio | C11: 937592 | D11: 2022 | E11: OUVIDORIA | F11: CAPITAL | G11: MESA PARA ESCRITÓRIO, tipo 'L' | H11: 8.0 | I11: 1076.9 | J11: 8615.2 | K11: 5280 | L11: 3335.2 | M11: =IF(E11="N/A", J11, IF(OR(K11=0, ISBLANK(K11), K11=""), 0, J11-K11)) -> 3335.2
A12: AM | B12: Convênio | C12: 937592 | D12: 2022 | E12: CORREGEDORIA | F12: CAPITAL | G12: APARELHO AR-CONDICIONADO, 18.000 BTUs | H12: 1 | I12: 3463.8 | J12: 3463.8 | K12: 3299.99 | L12: 163.81 | M12: =IF(E12="N/A", J12, IF(OR(K12=0, ISBLANK(K12), K12=""), 0, J12-K12)) -> 163.81
A13: AM | B13: Convênio | C13: 937592 | D13: 2022 | E13: CORREGEDORIA | F13: CAPITAL | G13: MESA PARA ESCRITÓRIO, formato: retangular | H13: 7 | I13: 798.8 | J13: =AM!$H13*AM!$I13 -> 5591.6 | K13: 4060 | L13: =AM!$J13-AM!$K13 -> 1531.6 | M13: =IF(E13="N/A", J13, IF(OR(K13=0, ISBLANK(K13), K13=""), 0, J13-K13)) -> 1531.6
A14: AM | B14: Convênio | C14: 937592 | D14: 2022 | E14: ESCOLA PENAL | F14: CAPITAL | G14: MESA PARA ESCRITÓRIO, formato: retangular | H14: 6 | I14: 798.8 | J14: =AM!$H14*AM!$I14 -> 4792.8 | K14: 3480 | L14: =AM!$J14-AM!$K14 -> 1312.8 | M14: =IF(E14="N/A", J14, IF(OR(K14=0, ISBLANK(K14), K14=""), 0, J14-K14)) -> 1312.8
A15: AM | B15: Convênio | C15: 937592 | D15: 2022 | E15: CORREGEDORIA | F15: CAPITAL | G15: CADEIRA GIRATÓRIA, modelo: secretária | H15: 4 | I15: 343.13 | J15: =AM!$H15*AM!$I15 -> 1372.52 | K15: 1200 | L15: =AM!$J15-AM!$K15 -> 172.52 | M15: =IF(E15="N/A", J15, IF(OR(K15=0, ISBLANK(K15), K15=""), 0, J15-K15)) -> 172.52
A16: AM | B16: Convênio | C16: 937592 | D16: 2022 | E16: OUVIDORIA | F16: CAPITAL | G16: CADEIRA FIXA, Sem braço, 04 pés, tipo es | H16: 10 | I16: 522.42 | J16: =AM!$H16*AM!$I16 -> 5224.2 | K16: 4000 | L16: =AM!$J16-AM!$K16 -> 1224.2 | M16: =IF(E16="N/A", J16, IF(OR(K16=0, ISBLANK(K16), K16=""), 0, J16-K16)) -> 1224.2
A17: AM | B17: Convênio | C17: 937592 | D17: 2022 | E17: CORREGEDORIA | F17: CAPITAL | G17: CADEIRA FIXA, Sem braço, 04 pés, tipo es | H17: 9 | I17: 522.42 | J17: =AM!$H17*AM!$I17 -> 4701.78 | K17: 3600 | L17: =AM!$J17-AM!$K17 -> 1101.78 | M17: =IF(E17="N/A", J17, IF(OR(K17=0, ISBLANK(K17), K17=""), 0, J17-K17)) -> 1101.78
A18: AM | B18: Convênio | C18: 937592 | D18: 2022 | E18: ESCOLA PENAL | F18: CAPITAL | G18: CADEIRA FIXA, Sem braço, 04 pés, tipo es | H18: 9 | I18: 522.42 | J18: =AM!$H18*AM!$I18 -> 4701.78 | K18: 3600 | L18: =AM!$J18-AM!$K18 -> 1101.78 | M18: =IF(E18="N/A", J18, IF(OR(K18=0, ISBLANK(K18), K18=""), 0, J18-K18)) -> 1101.78

Sheet AC
A1: UF | B1: INSTRUMENTO | C1: NÚMERO | D1: ANO | E1: ÁREA | F1: NATUREZA | G1: DESCRIÇÃO | H1: QUANTIDADE | I1: VALOR UNITÁRIO | J1: VALOR TOTAL PREVISTO | K1: VALOR TOTAL EXECUTADO | L1: SALDO | M1: SALDO ECONOMICIDADE
A2: AC | B2: Convênio | C2: 937782 | D2: 2022 | E2: OUVIDORIA | F2: CUSTEIO | G2: Aplicação de Palestras com diferentes te | H2: 1 | I2: 11400 | J2: =H2*I2 -> 11400 | K2: 11400 | L2: =J2-K2 -> 0 | M2: =IF(E2="N/A", J2, IF(OR(K2=0, ISBLANK(K2), K2=""), 0, J2-K2)) -> 0
A3: AC | B3: Convênio | C3: 937782 | D3: 2022 | E3: CORREGEDORIA | F3: CUSTEIO | G3: Aplicação de Seminário com 2 palestras c | H3: 1 | I3: 11400 | J3: =H3*I3 -> 11400 | K3: 11400 | L3: =J3-K3 -> 0 | M3: =IF(E3="N/A", J3, IF(OR(K3=0, ISBLANK(K3), K3=""), 0, J3-K3)) -> 0
A4: AC | B4: Convênio | C4: 937782 | D4: 2022 | E4: ESCOLA PENAL | F4: CUSTEIO | G4: Curso de Edição de Vídeos | H4: 1 | I4: 14700 | J4: =H4*I4 -> 14700 | L4: =J4-K4 -> 14700 | M4: =IF(E4="N/A", J4, IF(OR(K4=0, ISBLANK(K4), K4=""), 0, J4-K4)) -> 0
A5: AC | B5: Convênio | C5: 937782 | D5: 2022 | E5: OUVIDORIA | F5: CAPITAL | G5: Cadeira de escritório para mesa de reunião | H5: 6 | I5: 699.99 | J5: =H5*I5 -> 4199.94 | K5: 4199.94 | L5: =J5-K5 -> 0 | M5: =IF(E5="N/A", J5, IF(OR(K5=0, ISBLANK(K5), K5=""), 0, J5-K5)) -> 9.094947e-13
A6: AC | B6: Convênio | C6: 937782 | D6: 2022 | E6: OUVIDORIA | F6: CAPITAL | G6: Coletes de Identificação | H6: 15 | I6: 251.25 | J6: =H6*I6 -> 3768.75 | K6: 1169.61 | L6: =J6-K6 -> 2599.14 | M6: =IF(E6="N/A", J6, IF(OR(K6=0, ISBLANK(K6), K6=""), 0, J6-K6)) -> 2599.14
A7: AC | B7: Convênio | C7: 937782 | D7: 2022 | E7: CORREGEDORIA | F7: CAPITAL | G7: Coletes de Identificação | H7: 14 | I7: 251.25 | J7: =H7*I7 -> 3517.5 | K7: 1091.64 | L7: =J7-K7 -> 2425.86 | M7: =IF(E7="N/A", J7, IF(OR(K7=0, ISBLANK(K7), K7=""), 0, J7-K7)) -> 2425.86
A8: AC | B8: Convênio | C8: 937782 | D8: 2022 | E8: OUVIDORIA | F8: CAPITAL | G8: Computador Desktop completo | H8: 1 | I8: 6552.67 | J8: =H8*I8 -> 6552.67 | K8: 6040.9 | L8: =J8-K8 -> 511.77 | M8: =IF(E8="N/A", J8, IF(OR(K8=0, ISBLANK(K8), K8=""), 0, J8-K8)) -> 511.77
A9: AC | B9: Convênio | C9: 937782 | D9: 2022 | E9: CORREGEDORIA | F9: CAPITAL | G9: Computador Desktop completo | H9: 1 | I9: 6552.67 | J9: =H9*I9 -> 6552.67 | K9: 6040.9 | L9: =J9-K9 -> 511.77 | M9: =IF(E9="N/A", J9, IF(OR(K9=0, ISBLANK(K9), K9=""), 0, J9-K9)) -> 511.77
A10: AC | B10: Convênio | C10: 937782 | D10: 2022 | E10: OUVIDORIA | F10: CAPITAL | G10: Câmera de videoconferencia (webcam) | H10: 2 | I10: 547.5 | J10: =H10*I10 -> 1095 | L10: =J10-K10 -> 1095 | M10: =IF(E10="N/A", J10, IF(OR(K10=0, ISBLANK(K10), K10=""), 0, J10-K10)) -> 0
A11: AC | B11: Convênio | C11: 937782 | D11: 2022 | E11: CORREGEDORIA | F11: CAPITAL | G11: Câmera de videoconferencia (webcam) | H11: 2 | I11: 547.5 | J11: =H11*I11 -> 1095 | L11: =J11-K11 -> 1095 | M11: =IF(E11="N/A", J11, IF(OR(K11=0, ISBLANK(K11), K11=""), 0, J11-K11)) -> 0
A12: AC | B12: Convênio | C12: 937782 | D12: 2022 | E12: ESCOLA PENAL | F12: CAPITAL | G12: Desktop para edição de video | H12: 1 | I12: 14849 | J12: =H12*I12 -> 14849 | L12: =J12-K12 -> 14849 | M12: =IF(E12="N/A", J12, IF(OR(K12=0, ISBLANK(K12), K12=""), 0, J12-K12)) -> 0
A13: AC | B13: Convênio | C13: 937782 | D13: 2022 | E13: ESCOLA PENAL | F13: CAPITAL | G13: Estabilizador 3KVA | H13: 2 | I13: 638.25 | J13: =H13*I13 -> 1276.5 | K13: 1276.5 | L13: =J13-K13 -> 0 | M13: =IF(E13="N/A", J13, IF(OR(K13=0, ISBLANK(K13), K13=""), 0, J13-K13)) -> 0
A14: AC | B14: Convênio | C14: 937782 | D14: 2022 | E14: ESCOLA PENAL | F14: CAPITAL | G14: Estabilizador para Câmera | H14: 2 | I14: 1611.06 | J14: =H14*I14 -> 3222.12 | L14: =J14-K14 -> 3222.12 | M14: =IF(E14="N/A", J14, IF(OR(K14=0, ISBLANK(K14), K14=""), 0, J14-K14)) -> 0
A15: AC | B15: Convênio | C15: 937782 | D15: 2022 | E15: OUVIDORIA | F15: CAPITAL | G15: Filmadora Profissional | H15: 1 | I15: 2250 | J15: =H15*I15 -> 2250 | K15: 2250 | L15: =J15-K15 -> 0 | M15: =IF(E15="N/A", J15, IF(OR(K15=0, ISBLANK(K15), K15=""), 0, J15-K15)) -> 0
A16: AC | B16: Convênio | C16: 937782 | D16: 2022 | E16: CORREGEDORIA | F16: CAPITAL | G16: Filmadora Profissional | H16: 1 | I16: 2250 | J16: =H16*I16 -> 2250 | K16: 2250 | L16: =J16-K16 -> 0 | M16: =IF(E16="N/A", J16, IF(OR(K16=0, ISBLANK(K16), K16=""), 0, J16-K16)) -> 0
A17: AC | B17: Convênio | C17: 937782 | D17: 2022 | E17: ESCOLA PENAL | F17: CAPITAL | G17: Filmadora Profissional | H17: 2 | I17: 2250 | J17: =H17*I17 -> 4500 | K17: 4500 | L17: =J17-K17 -> 0 | M17: =IF(E17="N/A", J17, IF(OR(K17=0, ISBLANK(K17), K17=""), 0, J17-K17)) -> 0
A18: AC | B18: Convênio | C18: 937782 | D18: 2022 | E18: OUVIDORIA | F18: CAPITAL | G18: Gravador e reprodutor de áudio | H18: 1 | I18: 489.65 | J18: =H18*I18 -> 489.65 | K18: 489.65 | L18: =J18-K18 -> 0 | M18: =IF(E18="N/A", J18, IF(OR(K18=0, ISBLANK(K18), K18=""), 0, J18-K18)) -> 0
A19: AC | B19: Convênio | C19: 937782 | D19: 2022 | E19: CORREGEDORIA | F19: CAPITAL | G19: Gravador e reprodutor de áudio | H19: 1 | I19: 489.65 | J19: =H19*I19 -> 489.65 | K19: 489.65 | L19: =J19-K19 -> 0 | M19: =IF(E19="N/A", J19, IF(OR(K19=0, ISBLANK(K19), K19=""), 0, J19-K19)) -> 0
A20: AC | B20: Convênio | C20: 937782 | D20: 2022 | E20: ESCOLA PENAL | F20: CAPITAL | G20: Gravador e reprodutor de áudio | H20: 2 | I20: 489.65 | J20: =H20*I20 -> 979.3 | K20: 979.3 | L20: =J20-K20 -> 0 | M20: =IF(E20="N/A", J20, IF(OR(K20=0, ISBLANK(K20), K20=""), 0, J20-K20)) -> 0
A21: AC | B21: Convênio | C21: 937782 | D21: 2022 | E21: ESCOLA PENAL | F21: CAPITAL | G21: HD externo de 1tb portátil | H21: 4 | I21: 373.02 | J21: =H21*I21 -> 1492.08 | K21: 1492.08 | L21: =J21-K21 -> 0 | M21: =IF(E21="N/A", J21, IF(OR(K21=0, ISBLANK(K21), K21=""), 0, J21-K21)) -> 0
A22: AC | B22: Convênio | C22: 937782 | D22: 2022 | E22: ESCOLA PENAL | F22: CAPITAL | G22: Lousa digital | H22: 1 | I22: 5000 | J22: =H22*I22 -> 5000 | K22: 5000 | L22: =J22-K22 -> 0 | M22: =IF(E22="N/A", J22, IF(OR(K22=0, ISBLANK(K22), K22=""), 0, J22-K22)) -> 0
A23: AC | B23: Convênio | C23: 937782 | D23: 2022 | E23: OUVIDORIA | F23: CAPITAL | G23: Mesa de Reunião Retangular 2m de comprimento | H23: 1 | I23: 2699.95 | J23: =H23*I23 -> 2699.95 | K23: 2338.89 | L23: =J23-K23 -> 361.06 | M23: =IF(E23="N/A", J23, IF(OR(K23=0, ISBLANK(K23), K23=""), 0, J23-K23)) -> 361.06
A24: AC | B24: Convênio | C24: 937782 | D24: 2022 | E24: CORREGEDORIA | F24: CAPITAL | G24: Mesa de Reunião Retangular 2m de comprimento | H24: 1 | I24: 2699.95 | J24: =H24*I24 -> 2699.95 | K24: 2338.89 | L24: =J24-K24 -> 361.06 | M24: =IF(E24="N/A", J24, IF(OR(K24=0, ISBLANK(K24), K24=""), 0, J24-K24)) -> 361.06
A25: AC | B25: Convênio | C25: 937782 | D25: 2022 | E25: OUVIDORIA | F25: CAPITAL | G25: Microfone direcional de mesa | H25: 2 | I25: 349.75 | J25: =H25*I25 -> 699.5 | K25: 699.5 | L25: =J25-K25 -> 0 | M25: =IF(E25="N/A", J25, IF(OR(K25=0, ISBLANK(K25), K25=""), 0, J25-K25)) -> 0
A26: AC | B26: Convênio | C26: 937782 | D26: 2022 | E26: CORREGEDORIA | F26: CAPITAL | G26: Microfone direcional de mesa | H26: 2 | I26: 349.75 | J26: =H26*I26 -> 699.5 | K26: 699.5 | L26: =J26-K26 -> 0 | M26: =IF(E26="N/A", J26, IF(OR(K26=0, ISBLANK(K26), K26=""), 0, J26-K26)) -> 0
... A51: AC | B51: Convênio | C51: 937782 | D51: 2022 | E51: ESCOLA PENAL | F51: CAPITAL | G51: Sofá de espera, 2(dois) lugares | H51: 1 | I51: 5380 | J51: =H51*I51 -> 5380 | K51: 0 | L51: =J51-K51 -> 5380 | M51: =IF(E51="N/A", J51, IF(OR(K51=0, ISBLANK(K51), K51=""), 0, J51-K51)) -> 0

Sheet MS
A1: UF | B1: INSTRUMENTO | C1: NÚMERO | D1: ANO | E1: ÁREA | F1: NATUREZA | G1: DESCRIÇÃO | H1: QUANTIDADE | I1: VALOR UNITÁRIO | J1: VALOR TOTAL PREVISTO | K1: VALOR TOTAL EXECUTADO | L1: SALDO | M1: SALDO ECONOMICIDADE
A2: MS | B2: Convênio | C2: 937265 | D2: 2022 | E2: ESCOLA PENAL | F2: CUSTEIO | G2: Alvo Silhueta padrão SAT/ANP cx com 1.000 | H2: 300.0 | I2: 7.94 | J2: 2381 | K2: 0 | L2: 2381 | M2: =IF(E2="N/A", J2, IF(OR(K2=0, ISBLANK(K2), K2=""), 0, J2-K2)) -> 0
A3: MS | B3: Convênio | C3: 937265 | D3: 2022 | E3: ESCOLA PENAL | F3: CUSTEIO | G3: Alvo percepção c/ 4 cores SAT c/100unid | H3: 300.0 | I3: 1.87 | J3: 560 | K3: 0 | L3: 560 | M3: =IF(E3="N/A", J3, IF(OR(K3=0, ISBLANK(K3), K3=""), 0, J3-K3)) -> 0
A4: MS | B4: Convênio | C4: 937265 | D4: 2022 | E4: ESCOLA PENAL | F4: CUSTEIO | G4: Alvos Metálicos plates | H4: 20.0 | I4: 188.89 | J4: 3777.87 | K4: 0 | L4: 3777.87 | M4: =IF(E4="N/A", J4, IF(OR(K4=0, ISBLANK(K4), K4=""), 0, J4-K4)) -> 0
A5: MS | B5: Convênio | C5: 937265 | D5: 2022 | E5: ESCOLA PENAL | F5: CUSTEIO | G5: Alvos Metálicos popper | H5: 9.0 | I5: 482 | J5: 4338 | K5: 0 | L5: 4338 | M5: =IF(E5="N/A", J5, IF(OR(K5=0, ISBLANK(K5), K5=""), 0, J5-K5)) -> 0
A6: MS | B6: Convênio | C6: 937265 | D6: 2022 | E6: ESCOLA PENAL | F6: CUSTEIO | G6: Caixa arquivo em plástico PP corrugado d | H6: 21.0 | I6: 7.15 | J6: 150.15 | K6: 0 | L6: 150.15 | M6: =IF(E6="N/A", J6, IF(OR(K6=0, ISBLANK(K6), K6=""), 0, J6-K6)) -> 0
A7: MS | B7: Convênio | C7: 937265 | D7: 2022 | E7: OUVIDORIA | F7: CUSTEIO | G7: Caixa organizadora mínimo 20 L | H7: 20.0 | I7: 73.15 | J7: 1463 | K7: 0 | L7: 1463 | M7: =IF(E7="N/A", J7, IF(OR(K7=0, ISBLANK(K7), K7=""), 0, J7-K7)) -> 0
A8: MS | B8: Convênio | C8: 937265 | D8: 2022 | E8: OUVIDORIA | F8: CUSTEIO | G8: Calça Tática | H8: 20.0 | I8: 330.53 | J8: 6610.53 | K8: 0 | L8: 9915.8 | M8: =IF(E8="N/A", J8, IF(OR(K8=0, ISBLANK(K8), K8=""), 0, J8-K8)) -> 0
A9: MS | B9: Convênio | C9: 937265 | D9: 2022 | E9: CORREGEDORIA | F9: CUSTEIO | G9: Calça Tática | H9: 30.0 | I9: 330.53 | J9: 9915.8 | K9: 0 | L9: 6610.53 | M9: =IF(E9="N/A", J9, IF(OR(K9=0, ISBLANK(K9), K9=""), 0, J9-K9)) -> 0
A10: MS | B10: Convênio | C10: 937265 | D10: 2022 | E10: CORREGEDORIA | F10: CUSTEIO | G10: Camisa Tática | H10: 30.0 | I10: 198.38 | J10: 5951.5 | K10: 0 | L10: 5951.5 | M10: =IF(E10="N/A", J10, IF(OR(K10=0, ISBLANK(K10), K10=""), 0, J10-K10)) -> 0
A11: MS | B11: Convênio | C11: 937265 | D11: 2022 | E11: ESCOLA PENAL | F11: CUSTEIO | G11: Capacete para treino boxe, artes marciai | H11: 15.0 | I11: 104.48 | J11: 1567.2 | K11: 0 | L11: 1567.2 | M11: =IF(E11="N/A", J11, IF(OR(K11=0, ISBLANK(K11), K11=""), 0, J11-K11)) -> 0
A12: MS | B12: Convênio | C12: 937265 | D12: 2022 | E12: ESCOLA PENAL | F12: CUSTEIO | G12: Cartão de memória, com capacidade de arm | H12: 1.0 | I12: 475.99 | J12: 475.99 | K12: 0 | L12: 475.99 | M12: =IF(E12="N/A", J12, IF(OR(K12=0, ISBLANK(K12), K12=""), 0, J12-K12)) -> 0
A13: MS | B13: Convênio | C13: 937265 | D13: 2022 | E13: CORREGEDORIA | F13: CUSTEIO | G13: Cinto Tático | H13: 30.0 | I13: 209.13 | J13: 6273.98 | K13: 0 | L13: 4182.65 | M13: =IF(E13="N/A", J13, IF(OR(K13=0, ISBLANK(K13), K13=""), 0, J13-K13)) -> 0
... A73: MS | B73: Convênio | C73: 937265 | D73: 2022 | E73: OUVIDORIA | F73: CAPITAL | G73: porteiro eletrônico com fechadura eletrônica | H73: 1.0 | I73: 1664.54 | J73: 1664.54 | K73: 0 | L73: 1664.54 | M73: =IF(E73="N/A", J73, IF(OR(K73=0, ISBLANK(K73), K73=""), 0, J73-K73)) -> 0

Sheet SP
A1: UF | B1: INSTRUMENTO | C1: NÚMERO | D1: ANO | E1: ÁREA | F1: NATUREZA | G1: DESCRIÇÃO | H1: QUANTIDADE | I1: VALOR UNITÁRIO | J1: VALOR TOTAL PREVISTO | K1: VALOR TOTAL EXECUTADO | L1: SALDO | M1: SALDO ECONOMICIDADE
A2: SP | B2: Convênio | C2: 938128 | D2: 2022 | E2: CORREGEDORIA | F2: CUSTEIO | G2: Capa e Case Protetora para Câmera GoPro | H2: 2.0 | I2: 112.37 | J2: 224.74 | L2: =J2-K2 -> 224.74 | M2: =IF(E2="N/A", J2, IF(OR(K2=0, ISBLANK(K2), K2=""), 0, J2-K2)) -> 0
A3: SP | B3: Convênio | C3: 938128 | D3: 2022 | E3: CORREGEDORIA | F3: CUSTEIO | G3: Cartão de Memória Dispositivo de Armazen | H3: 3.0 | I3: 127.23 | J3: 381.69 | L3: =J3-K3 -> 381.69 | M3: =IF(E3="N/A", J3, IF(OR(K3=0, ISBLANK(K3), K3=""), 0, J3-K3)) -> 0
A4: SP | B4: Convênio | C4: 938128 | D4: 2022 | E4: ESCOLA PENAL | F4: CUSTEIO | G4: Curso de Pós Graduação Direitos Humanos | H4: 250.0 | I4: 2181.34 | J4: 545334.9 | K4: 190837.22 | L4: =J4-K4 -> 354497.68 | M4: =IF(E4="N/A", J4, IF(OR(K4=0, ISBLANK(K4), K4=""), 0, J4-K4)) -> 354497.68
A5: SP | B5: Convênio | C5: 938128 | D5: 2022 | E5: CORREGEDORIA | F5: CUSTEIO | G5: Curso de Pós Graduação em Direito Admin | H5: 40 | I5: 11425 | J5: =H5*I5 -> 457000 | K5: 0 | L5: =J5-K5 -> 457000 | M5: =IF(E5="N/A", J5, IF(OR(K5=0, ISBLANK(K5), K5=""), 0, J5-K5)) -> 0
A6: SP | B6: Convênio | C6: 938128 | D6: 2022 | E6: N/A | F6: CUSTEIO | G6: Saldo Residual Serviços EAP | H6: 1.0 | I6: 46233.82 | J6: 46233.82 | K6: 0 | L6: =J6-K6 -> 46233.82 | M6: =IF(E6="N/A", J6, IF(OR(K6=0, ISBLANK(K6), K6=""), 0, J6-K6)) -> 46233.82
A7: SP | B7: Convênio | C7: 938128 | D7: 2022 | E7: ESCOLA PENAL | F7: CUSTEIO | G7: Serviço de INSTALAÇÃO APARELHO DE AR CON | H7: 25.0 | I7: 1350 | J7: 33750 | K7: 33750 | L7: =J7-K7 -> 0 | M7: =IF(E7="N/A", J7, IF(OR(K7=0, ISBLANK(K7), K7=""), 0, J7-K7)) -> 0
A8: SP | B8: Convênio | C8: 938128 | D8: 2022 | E8: ESCOLA PENAL | F8: CAPITAL | G8: ALGEMA DE PUNHO DOBRADIÇA DUPLA | H8: 100.0 | I8: 107 | J8: 10700 | K8: 10700 | L8: =J8-K8 -> 0 | M8: =IF(E8="N/A", J8, IF(OR(K8=0, ISBLANK(K8), K8=""), 0, J8-K8)) -> 0
A9: SP | B9: Convênio | C9: 938128 | D9: 2022 | E9: ESCOLA PENAL | F9: CAPITAL | G9: ALGEMA DE TORNOZELO | H9: 100.0 | I9: 143 | J9: 14300 | K9: 14300 | L9: =J9-K9 -> 0 | M9: =IF(E9="N/A", J9, IF(OR(K9=0, ISBLANK(K9), K9=""), 0, J9-K9)) -> 0
A10: SP | B10: Convênio | C10: 938128 | D10: 2022 | E10: N/A | F10: CAPITAL | G10: sobra de saldo residual | H10: 1.0 | I10: 32765.74 | J10: 32765.74 | K10: 0 | L10: =J10-K10 -> 32765.74 | M10: =IF(E10="N/A", J10, IF(OR(K10=0, ISBLANK(K10), K10=""), 0, J10-K10)) -> 32765.74
A11: SP | B11: Convênio | C11: 938128 | D11: 2022 | E11: ESCOLA PENAL | F11: CAPITAL | G11: Algemas de aço inox Pulso Treinamentos p | H11: 500.0 | I11: 186.6 | J11: 93300 | K11: 93000 | L11: =J11-K11 -> 300 | M11: =IF(E11="N/A", J11, IF(OR(K11=0, ISBLANK(K11), K11=""), 0, J11-K11)) -> 300
A12: SP | B12: Convênio | C12: 938128 | D12: 2022 | E12: ESCOLA PENAL | F12: CAPITAL | G12: Ar Condicionado Teto Daikin Inverter 48K | H12: 8.0 | I12: 14365.02 | J12: 114920.16 | K12: 84220.08 | L12: =J12-K12 -> 30700.08 | M12: =IF(E12="N/A", J12, IF(OR(K12=0, ISBLANK(K12), K12=""), 0, J12-K12)) -> 30700.08
A13: SP | B13: Convênio | C13: 938128 | D13: 2022 | E13: ESCOLA PENAL | F13: CAPITAL | G13: Ar condicionado de Parede Dual Inverter | H13: 25.0 | I13: 8730.12 | J13: 218253 | K13: 185000 | L13: =J13-K13 -> 33253 | M13: =IF(E13="N/A", J13, IF(OR(K13=0, ISBLANK(K13), K13=""), 0, J13-K13)) -> 33253
A14: SP | B14: Convênio | C14: 938128 | D14: 2022 | E14: OUVIDORIA | F14: CAPITAL | G14: Armário de Escritório com 02 portas Ouvi | H14: 5.0 | I14: 688.43 | J14: 3442.17 | K14: 3435 | L14: =J14-K14 -> 7.17 | M14: =IF(E14="N/A", J14, IF(OR(K14=0, ISBLANK(K14), K14=""), 0, J14-K14)) -> 7.17
A15: SP | B15: Convênio | C15: 938128 | D15: 2022 | E15: ESCOLA PENAL | F15: CAPITAL | G15: Beacons Eddystone Ble, para Escola Adm. | H15: 63.0 | I15: 460.09 | J15: 28985.67 | K15: 0 | L15: =J15-K15 -> 28985.67 | M15: =IF(E15="N/A", J15, IF(OR(K15=0, ISBLANK(K15), K15=""), 0, J15-K15)) -> 0
A16: SP | B16: Convênio | C16: 938128 | D16: 2022 | E16: CORREGEDORIA | F16: CAPITAL | G16: Cadeira Giratória Modelo Presidente - Co | H16: 28.0 | I16: 720.31 | J16: 20168.59 | K16: 13076 | L16: =J16-K16 -> 7092.59 | M16: =IF(E16="N/A", J16, IF(OR(K16=0, ISBLANK(K16), K16=""), 0, J16-K16)) -> 7092.59
A17: SP | B17: Convênio | C17: 938128 | D17: 2022 | E17: ESCOLA PENAL | F17: CAPITAL | G17: Cadeira Giratória com braço, para Escola | H17: 50.0 | I17: 617.8 | J17: 30890 | K17: 23500 | L17: =J17-K17 -> 7390 | M17: =IF(E17="N/A", J17, IF(OR(K17=0, ISBLANK(K17), K17=""), 0, J17-K17)) -> 7390
... A23: SP | B23: Convênio | C23: 938128 | D23: 2022 | E23: OUVIDORIA | F23: CAPITAL | G23: Estante de aço para arquivo morto, para | H23: 8.0 | I23: 429.42 | J23: 3435.36 | K23: 3435.36 | L23: =J23-K23 -> 0 | M23: =IF(E23="N/A", J23, IF(OR(K23=0, ISBLANK(K23), K23=""), 0, J23-K23)) -> 0
A24: SP | B24: Convênio | C24: 938128 | D24: 2022 | E24: CORREGEDORIA | F24: CAPITAL | G24: Forno Micro-Ondas 01 para Corregedoria; | H24: 2 | I24: 1267.46 | J24: =H24*I24 -> 2534.92 | K24: 2520 | L24: =J24-K24 -> 14.92 | M24: =IF(E24="N/A", J24, IF(OR(K24=0, ISBLANK(K24), K24=""), 0, J24-K24)) -> 14.92
A25: SP | B25: Convênio | C25: 938128 | D25: 2022 | E25: OUVIDORIA | F25: CAPITAL | G25: GSMARTPHONE 128GB MEMORIA INTERNA, 8GB R | H25: 1.0 | I25: 2716.25 | J25: 2716.25 | K25: 2450 | L25: =J25-K25 -> 266.25 | M25: =IF(E25="N/A", J25, IF(OR(K25=0, ISBLANK(K25), K25=""), 0, J25-K25)) -> 266.25
A26: SP | B26: Convênio | C26: 938128 | D26: 2022 | E26: CORREGEDORIA | F26: CAPITAL | G26: Gaveteiro de 2 gavetas e 1 gavetão para | H26: 28.0 | I26: 346.94 | J26: 9714.32 | K26: 11032 | L26: =J26-K26 -> -1317.68 | M26: =J26-K26 -> -1317.68
A27: SP | B27: Convênio | C27: 938128 | D27: 2022 | E27: CORREGEDORIA | F27: CAPITAL | G27: Livro Reforma da Lei de Improbabilidade | H27: 1.0 | I27: 126.24 | J27: 126.24 | K27: 0 | L27: =J27-K27 -> 126.24 | M27: =IF(E27="N/A", J27, IF(OR(K27=0, ISBLANK(K27), K27=""), 0, J27-K27)) -> 0
A28: SP | B28: Convênio | C28: 938128 | D28: 2022 | E28: CORREGEDORIA | F28: CAPITAL | G28: Livro Comentários à Lei de Licitação e C | H28: 1.0 | I28: 354.33 | J28: 354.33 | K28: 0 | L28: =J28-K28 -> 354.33 | M28: =IF(E28="N/A", J28, IF(OR(K28=0, ISBLANK(K28), K28=""), 0, J28-K28)) -> 0
A29: SP | B29: Convênio | C29: 938128 | D29: 2022 | E29: CORREGEDORIA | F29: CAPITAL | G29: Livro nova Lei de Licitações e Contrato | H29: 1.0 | I29: 142.13 | J29: 142.13 | K29: 0 | L29: =J29-K29 -> 142.13 | M29: =IF(E29="N/A", J29, IF(OR(K29=0, ISBLANK(K29), K29=""), 0, J29-K29)) -> 0
A30: SP | B30: Convênio | C30: 938128 | D30: 2022 | E30: ESCOLA PENAL | F30: CAPITAL | G30: Livros para o acervo da Biblioteca da Es | H30: 51.0 | I30: 6679.38 | J30: 340648.4 | K30: 5910.9 | L30: =J30-K30 -> 334737.5 | M30: =IF(E30="N/A", J30, IF(OR(K30=0, ISBLANK(K30), K30=""), 0, J30-K30)) -> 334737.5
A31: SP | B31: Convênio | C31: 938128 | D31: 2022 | E31: ESCOLA PENAL | F31: CAPITAL | G31: Lousa Digital 55 inteligente com conexão | H31: 9.0 | I31: 7800 | J31: 70200 | K31: 70200 | L31: =J31-K31 -> 0 | M31: =IF(E31="N/A", J31, IF(OR(K31=0, ISBLANK(K31), K31=""), 0, J31-K31)) -> 0
A32: SP | B32: Convênio | C32: 938128 | D32: 2022 | E32: CORREGEDORIA | F32: CAPITAL | G32: Mesa de Centro para Escritório - para Co | H32: 2.0 | I32: 583.3 | J32: 1166.6 | K32: 1166.6 | L32: =J32-K32 -> 0 | M32: =IF(E32="N/A", J32, IF(OR(K32=0, ISBLANK(K32), K32=""), 0, J32-K32)) -> 0
A33: SP | B33: Convênio | C33: 938128 | D33: 2022 | E33: ESCOLA PENAL | F33: CAPITAL | G33: Mesa de Reunião Redonda para Escritório, | H33: 4.0 | I33: 426.25 | J33: 1705 | K33: 3280 | L33: =J33-K33 -> -1575 | M33: =IF(E33="N/A", J33, IF(OR(K33=0, ISBLANK(K33), K33=""), 0, J33-K33)) -> -1575
A34: SP | B34: Convênio | C34: 938128 | D34: 2022 | E34: ESCOLA PENAL | F34: CAPITAL | G34: Monitor DE Vídeo 23,8 61F9kbr1BR, para | H34: 27.0 | I34: 767.04 | J34: 20710.08 | K34: 0 | L34: =J34-K34 -> 20710.08 | M34: =IF(E34="N/A", J34, IF(OR(K34=0, ISBLANK(K34), K34=""), 0, J34-K34)) -> 0
A35: SP | B35: Convênio | C35: 938128 | D35: 2022 | E35: CORREGEDORIA | F35: CAPITAL | G35: Monitor Vídeo 32 - para Corregedoria - CASP | H35: 28.0 | I35: 1732.33 | J35: 48505.33 | K35: 15232 | L35: =J35-K35 -> 33273.33 | M35: =IF(E35="N/A", J35, IF(OR(K35=0, ISBLANK(K35), K35=""), 0, J35-K35)) -> 33273.33
A36: SP | B36: Convênio | C36: 938128 | D36: 2022 | E36: ESCOLA PENAL | F36: CAPITAL | G36: Poltronas para o Auditório com Prancheta | H36: 200.0 | I36: 1784 | J36: 356800 | K36: 138000 | L36: =J36-K36 -> 218800 | M36: =IF(E36="N/A", J36, IF(OR(K36=0, ISBLANK(K36), K36=""), 0, J36-K36)) -> 218800
A37: SP | B37: Convênio | C37: 938128 | D37: 2022 | E37: ESCOLA PENAL | F37: CAPITAL | G37: Radio Portátil HP - para Escola Adm Peni | H37: 20.0 | I37: 3251.22 | J37: 65024.4 | K37: 8000 | L37: =J37-K37 -> 57024.4 | M37: =IF(E37="N/A", J37, IF(OR(K37=0, ISBLANK(K37), K37=""), 0, J37-K37)) -> 57024.4
A38: SP | B38: Convênio | C38: 938128 | D38: 2022 | E38: ESCOLA PENAL | F38: CAPITAL | G38: SMART TV 55, para Escola Adm. Penitenciária | H38: 15.0 | I38: 3009.87 | J38: 45148.05 | K38: 32760 | L38: =J38-K38 -> 12388.05 | M38: =IF(E38="N/A", J38, IF(OR(K38=0, ISBLANK(K38), K38=""), 0, J38-K38)) -> 12388.05
... A41: SP | B41: Convênio | C41: 938128 | D41: 2022 | E41: OUVIDORIA | F41: CAPITAL | G41: Sofa de recepção 03 lugares, para Ouvidoria | H41: 1.0 | I41: 2190.01 | J41: 2190.01 | K41: 2190.01 | L41: =J41-K41 -> 0 | M41: =IF(E41="N/A", J41, IF(OR(K41=0, ISBLANK(K41), K41=""), 0, J41-K41)) -> 0
B42: Convênio | C42: 938128 | D42: 2022 | F42: CAPITAL | G42: Agenda Planner | H42: 10 | I42: 113.43 | J42: =H42*I42 -> 1134.3 | K42: 0 | L42: =J42-K42 -> 1134.3 | M42: =IF(E42="N/A", J42, IF(OR(K42=0, ISBLANK(K42), K42=""), 0, J42-K42)) -> 0
B43: Convênio | C43: 938128 | D43: 2022 | F43: CAPITAL | G43: Saldo Residual | H43: 1 | I43: 71.36 | J43: 71.36 | K43: 0 | L43: =J43-K43 -> 71.36 | M43: =IF(E43="N/A", J43, IF(OR(K43=0, ISBLANK(K43), K43=""), 0, J43-K43)) -> 0
B44: Convênio | C44: 938128 | D44: 2022 | F44: CUSTEIO | G44: Contratação de serviços de digitalização | H44: 1 | I44: 505000 | J44: =H44*I44 -> 505000 | K44: 0 | L44: =J44-K44 -> 505000 | M44: =IF(E44="N/A", J44, IF(OR(K44=0, ISBLANK(K44), K44=""), 0, J44-K44)) -> 0
B45: Convênio | C45: 938128 | D45: 2022 | F45: CUSTEIO | G45: Serviço de operacionalização de sistema | H45: 1 | I45: 426666.67 | J45: 426666.67 | K45: 0 | L45: =J45-K45 -> 426666.67 | M45: =IF(E45="N/A", J45, IF(OR(K45=0, ISBLANK(K45), K45=""), 0, J45-K45)) -> 0
B46: Convênio | C46: 938128 | D46: 2022 | E46: OUVIDORIA | F46: CAPITAL | G46: Câmera Digital, para a Ouvidoria | H46: 1 | I46: 4287.7 | J46: 4287.7 | K46: 0 | L46: =J46-K46 -> 4287.7 | M46: =IF(E46="N/A", J46, IF(OR(K46=0, ISBLANK(K46), K46=""), 0, J46-K46)) -> 0
B47: Convênio | C47: 938128 | D47: 2022 | E47: OUVIDORIA | F47: CAPITAL | G47: Estação de Trabalho (Mesa em L), para Ou | H47: 12 | I47: 2524.35 | J47: =H47*I47 -> 30292.2 | K47: 0 | L47: =J47-K47 -> 30292.2 | M47: =IF(E47="N/A", J47, IF(OR(K47=0, ISBLANK(K47), K47=""), 0, J47-K47)) -> 0
B48: Convênio | C48: 938128 | D48: 2022 | E48: OUVIDORIA | F48: CAPITAL | G48: Gaveteiros, Ouvidoria | H48: 12 | I48: 1024.8 | J48: =H48*I48 -> 12297.6 | K48: 0 | L48: =J48-K48 -> 12297.6 | M48: =IF(E48="N/A", J48, IF(OR(K48=0, ISBLANK(K48), K48=""), 0, J48-K48)) -> 0

Sheet MA
A1: UF | B1: INSTRUMENTO | C1: NÚMERO | D1: ANO | E1: ÁREA | F1: NATUREZA | G1: DESCRIÇÃO | H1: QUANTIDADE | I1: VALOR UNITÁRIO | J1: VALOR TOTAL PREVISTO | K1: VALOR TOTAL EXECUTADO | L1: SALDO | M1: SALDO ECONOMICIDADE
A2: MA | B2: Convênio | C2: 938277 | D2: 2022 | E2: ESCOLA PENAL | F2: CUSTEIO | G2: Cabo HDMI | H2: 1.0 | I2: 251.6 | J2: 251.6 | L2: =J2-K2 -> 251.6 | M2: =IF(E2="N/A", J2, IF(OR(K2=0, ISBLANK(K2), K2=""), 0, J2-K2)) -> 0
A3: MA | B3: Convênio | C3: 938277 | D3: 2022 | E3: ESCOLA PENAL | F3: CUSTEIO | G3: Cabo LW XLR P10 | H3: 1.0 | I3: 87.62 | J3: 87.62 | L3: =J3-K3 -> 87.62 | M3: =IF(E3="N/A", J3, IF(OR(K3=0, ISBLANK(K3), K3=""), 0, J3-K3)) -> 0
A4: MA | B4: Convênio | C4: 938277 | D4: 2022 | E4: ESCOLA PENAL | F4: CUSTEIO | G4: Cabo NM E-20 P10 MONO/XLR Macho | H4: 1.0 | I4: 106.5 | J4: 106.5 | L4: =J4-K4 -> 106.5 | M4: =IF(E4="N/A", J4, IF(OR(K4=0, ISBLANK(K4), K4=""), 0, J4-K4)) -> 0
A5: MA | B5: Convênio | C5: 938277 | D5: 2022 | E5: ESCOLA PENAL | F5: CUSTEIO | G5: Cabo P10 Stereo XLR Fêmea | H5: 1.0 | I5: 99.8 | J5: 99.8 | L5: =J5-K5 -> 99.8 | M5: =IF(E5="N/A", J5, IF(OR(K5=0, ISBLANK(K5), K5=""), 0, J5-K5)) -> 0
A6: MA | B6: Convênio | C6: 938277 | D6: 2022 | E6: ESCOLA PENAL | F6: CUSTEIO | G6: Cabo balanceado XLR2XLR SC20 15M | H6: 1.0 | I6: 277.8 | J6: 277.8 | L6: =J6-K6 -> 277.8 | M6: =IF(E6="N/A", J6, IF(OR(K6=0, ISBLANK(K6), K6=""), 0, J6-K6)) -> 0
A7: MA | B7: Convênio | C7: 938277 | D7: 2022 | E7: ESCOLA PENAL | F7: CUSTEIO | G7: Cabo balanceado XLR2XLR SC20 20M | H7: 1.0 | I7: 347 | J7: 347 | L7: =J7-K7 -> 347 | M7: =IF(E7="N/A", J7, IF(OR(K7=0, ISBLANK(K7), K7=""), 0, J7-K7)) -> 0
A8: MA | B8: Convênio | C8: 938277 | D8: 2022 | E8: ESCOLA PENAL | F8: CUSTEIO | G8: Cabo de microfone XLR/P10 HG | H8: 1.0 | I8: 116.2 | J8: 116.2 | L8: =J8-K8 -> 116.2 | M8: =IF(E8="N/A", J8, IF(OR(K8=0, ISBLANK(K8), K8=""), 0, J8-K8)) -> 0
A9: MA | B9: Convênio | C9: 938277 | D9: 2022 | E9: ESCOLA PENAL | F9: CUSTEIO | G9: Cabo microfone TX HG P10/XLR | H9: 1.0 | I9: 145.3 | J9: 145.3 | L9: =J9-K9 -> 145.3 | M9: =IF(E9="N/A", J9, IF(OR(K9=0, ISBLANK(K9), K9=""), 0, J9-K9)) -> 0
A10: MA | B10: Convênio | C10: 938277 | D10: 2022 | E10: ESCOLA PENAL | F10: CUSTEIO | G10: Headphone/Fone de ouvido | H10: 1.0 | I10: 332 | J10: 332 | L10: =J10-K10 -> 332 | M10: =IF(E10="N/A", J10, IF(OR(K10=0, ISBLANK(K10), K10=""), 0, J10-K10)) -> 0
A11: MA | B11: Convênio | C11: 938277 | D11: 2022 | E11: ESCOLA PENAL | F11: CUSTEIO | G11: Microfone | H11: 1.0 | I11: 694 | J11: 694 | L11: =J11-K11 -> 694 | M11: =IF(E11="N/A", J11, IF(OR(K11=0, ISBLANK(K11), K11=""), 0, J11-K11)) -> 0
A12: MA | B12: Convênio | C12: 938277 | D12: 2022 | E12: ESCOLA PENAL | F12: CUSTEIO | G12: Microfone de lapela | H12: 1.0 | I12: 890 | J12: 890 | K12: 890 | L12: =J12-K12 -> 0 | M12: =IF(E12="N/A", J12, IF(OR(K12=0, ISBLANK(K12), K12=""), 0, J12-K12)) -> 0
A13: MA | B13: Convênio | C13: 938277 | D13: 2022 | E13: N/A | F13: CUSTEIO | G13: SALDO REMANESCENTE | H13: 1.0 | I13: 5924.45 | J13: 5924.45 | K13: 0 | L13: =J13-K13 -> 5924.45 | M13: =IF(E13="N/A", J13, IF(OR(K13=0, ISBLANK(K13), K13=""), 0, J13-K13)) -> 5924.45
A14: MA | B14: Convênio | C14: 938277 | D14: 2022 | E14: ESCOLA PENAL | F14: CUSTEIO | G14: Suporte fundo infinito + Chroma Key 3X2 | H14: 1.0 | I14: 286 | J14: 286 | L14: =J14-K14 -> 286 | M14: =IF(E14="N/A", J14, IF(OR(K14=0, ISBLANK(K14), K14=""), 0, J14-K14)) -> 0
A15: MA | B15: Convênio | C15: 938277 | D15: 2022 | E15: ESCOLA PENAL | F15: CUSTEIO | G15: Tecido Chroma Key 3X2 para estúdio fotog | H15: 1.0 | I15: 79.99 | J15: 79.99 | L15: =J15-K15 -> 79.99 | M15: =IF(E15="N/A", J15, IF(OR(K15=0, ISBLANK(K15), K15=""), 0, J15-K15)) -> 0
A16: MA | B16: Convênio | C16: 938277 | D16: 2022 | E16: ESCOLA PENAL | F16: CUSTEIO | G16: abafador auricular | H16: 57.0 | I16: 70 | J16: 3990 | K16: 3990 | L16: =J16-K16 -> 0 | M16: =IF(E16="N/A", J16, IF(OR(K16=0, ISBLANK(K16), K16=""), 0, J16-K16)) -> 0
A17: MA | B17: Convênio | C17: 938277 | D17: 2022 | E17: ESCOLA PENAL | F17: CUSTEIO | G17: cinto de guarnição com porta tonfa, cold | H17: 60.0 | I17: 117.5 | J17: 7050 | L17: =J17-K17 -> 7050 | M17: =IF(E17="N/A", J17, IF(OR(K17=0, ISBLANK(K17), K17=""), 0, J17-K17)) -> 0
A18: MA | B18: Convênio | C18: 938277 | D18: 2022 | E18: CORREGEDORIA | F18: CUSTEIO | G18: coldre | H18: 10.0 | I18: 219 | J18: 2190 | L18: =J18-K18 -> 2190 | M18: =IF(E18="N/A", J18, IF(OR(K18=0, ISBLANK(K18), K18=""), 0, J18-K18)) -> 0
A19: MA | B19: Convênio | C19: 938277 | D19: 2022 | E19: ESCOLA PENAL | F19: CUSTEIO | G19: tonfa | H19: 70.0 | I19: 40 | J19: 2800 | K19: 2800 | L19: =J19-K19 -> 0 | M19: =IF(E19="N/A", J19, IF(OR(K19=0, ISBLANK(K19), K19=""), 0, J19-K19)) -> 0
A20: MA | B20: Convênio | C20: 938277 | D20: 2022 | E20: ESCOLA PENAL | F20: CUSTEIO | G20: Óculos de Proteção | H20: 100 | I20: 10 | J20: =H20*I20 -> 1000 | L20: =J20-K20 -> 1000 | M20: =IF(E20="N/A", J20, IF(OR(K20=0, ISBLANK(K20), K20=""), 0, J20-K20)) -> 0
A21: MA | B21: Convênio | C21: 938277 | D21: 2022 | E21: CORREGEDORIA | F21: CUSTEIO | G21: Óculos de Proteção | H21: 7 | I21: 10 | J21: =H21*I21 -> 70 | L21: =J21-K21 -> 70 | M21: =IF(E21="N/A", J21, IF(OR(K21=0, ISBLANK(K21), K21=""), 0, J21-K21)) -> 0
A22: MA | B22: Convênio | C22: 938277 | D22: 2022 | E22: OUVIDORIA | F22: CUSTEIO | G22: Curso de capacitação em VCQB (MODULO I) | H22: 4.0 | I22: 4221.04 | J22: 16884.14 | K22: 1999.98 | L22: =J22-K22 -> 14884.16 | M22: =IF(E22="N/A", J22, IF(OR(K22=0, ISBLANK(K22), K22=""), 0, J22-K22)) -> 14884.16
A23: MA | B23: Convênio | C23: 938277 | D23: 2022 | E23: CORREGEDORIA | F23: CUSTEIO | G23: Curso: Licitações e contratos conforme a | H23: 4.0 | I23: 3450 | J23: 13800 | K23: 3000 | L23: =J23-K23 -> 10800 | M23: =IF(E23="N/A", J23, IF(OR(K23=0, ISBLANK(K23), K23=""), 0, J23-K23)) -> 10800
A24: MA | B24: Convênio | C24: 938277 | D24: 2022 | E24: OUVIDORIA | F24: CUSTEIO | G24: curso Gestão de Risco, Compliance e Audi | H24: 2.0 | I24: 9924.3 | J24: 19848.6 | K24: 9800 | L24: =J24-K24 -> 10048.6 | M24: =IF(E24="N/A", J24, IF(OR(K24=0, ISBLANK(K24), K24=""), 0, J24-K24)) -> 10048.6
A25: MA | B25: Convênio | C25: 938277 | D25: 2022 | E25: OUVIDORIA | F25: CUSTEIO | G25: curso Negociação e Administração de Conf | H25: 6.0 | I25: 980 | J25: 5880 | L25: =J25-K25 -> 5880 | M25: =IF(E25="N/A", J25, IF(OR(K25=0, ISBLANK(K25), K25=""), 0, J25-K25)) -> 0
A26: MA | B26: Convênio | C26: 938277 | D26: 2022 | E26: ESCOLA PENAL | F26: CAPITAL | G26: Aparelho de TV | H26: 1.0 | I26: 2500 | J26: 2500 | K26: 2500 | L26: =J26-K26 -> 0 | M26: =IF(E26="N/A", J26, IF(OR(K26=0, ISBLANK(K26), K26=""), 0, J26-K26)) -> 0
A27: MA | B27: Convênio | C27: 938277 | D27: 2022 | E27: CORREGEDORIA | F27: CAPITAL | G27: Caixas de som | H27: 16 | I27: 70.89 | J27: =H27*I27 -> 1134.24 | K27: 1134.24 | L27: =J27-K27 -> 0 | M27: =IF(E27="N/A", J27, IF(OR(K27=0, ISBLANK(K27), K27=""), 0, J27-K27)) -> 0
A28: MA | B28: Convênio | C28: 938277 | D28: 2022 | E28: OUVIDORIA | F28: CAPITAL | G28: Caixas de som | H28: 8 | I28: 70.89 | J28: =H28*I28 -> 567.12 | K28: 567.12 | L28: =J28-K28 -> 0 | M28: =IF(E28="N/A", J28, IF(OR(K28=0, ISBLANK(K28), K28=""), 0, J28-K28)) -> 0
A29: MA | B29: Convênio | C29: 938277 | D29: 2022 | E29: CORREGEDORIA | F29: CAPITAL | G29: Camera para pc com microfone com tecnolo | H29: 10 | I29: 218 | J29: =H29*I29 -> 2180 | K29: 2180 | L29: =J29-K29 -> 0 | M29: =IF(E29="N/A", J29, IF(OR(K29=0, ISBLANK(K29), K29=""), 0, J29-K29)) -> 0
A30: MA | B30: Convênio | C30: 938277 | D30: 2022 | E30: OUVIDORIA | F30: CAPITAL | G30: Camera para pc com microfone com tecnolo | H30: 10 | I30: 218 | J30: =H30*I30 -> 2180 | K30: 2180 | L30: =J30-K30 -> 0 | M30: =IF(E30="N/A", J30, IF(OR(K30=0, ISBLANK(K30), K30=""), 0, J30-K30)) -> 0
A31: MA | B31: Convênio | C31: 938277 | D31: 2022 | E31: ESCOLA PENAL | F31: CAPITAL | G31: Cartão de memória 512 GB | H31: 3.0 | I31: 279 | J31: 837 | L31: =J31-K31 -> 837 | M31: =IF(E31="N/A", J31, IF(OR(K31=0, ISBLANK(K31), K31=""), 0, J31-K31)) -> 0
A32: MA | B32: Convênio | C32: 938277 | D32: 2022 | E32: ESCOLA PENAL | F32: CAPITAL | G32: Câmera fotográfica profissional | H32: 1.0 | I32: 10998 | J32: 10998 | L32: =J32-K32 -> 10998 | M32: =IF(E32="N/A", J32, IF(OR(K32=0, ISBLANK(K32), K32=""), 0, J32-K32)) -> 0
A33: MA | B33: Convênio | C33: 938277 | D33: 2022 | E33: ESCOLA PENAL | F33: CAPITAL | G33: DRONE | H33: 3.0 | I33: 8543.13 | J33: 25629.39 | K33: 25629.39 | L33: =J33-K33 -> 0 | M33: =IF(E33="N/A", J33, IF(OR(K33=0, ISBLANK(K33), K33=""), 0, J33-K33)) -> 0
A34: MA | B34: Convênio | C34: 938277 | D34: 2022 | E34: ESCOLA PENAL | F34: CAPITAL | G34: Filmadora profissional | H34: 1.0 | I34: 12354 | J34: 12354 | L34: =J34-K34 -> 12354 | M34: =IF(E34="N/A", J34, IF(OR(K34=0, ISBLANK(K34), K34=""), 0, J34-K34)) -> 0
A35: MA | B35: Convênio | C35: 938277 | D35: 2022 | E35: ESCOLA PENAL | F35: CAPITAL | G35: HD externo | H35: 1.0 | I35: 890 | J35: 890 | K35: 890 | L35: =J35-K35 -> 0 | M35: =IF(E35="N/A", J35, IF(OR(K35=0, ISBLANK(K35), K35=""), 0, J35-K35)) -> 0
A36: MA | B36: Convênio | C36: 938277 | D36: 2022 | E36: ESCOLA PENAL | F36: CAPITAL | G36: Lente: EF 50 MM F/ 1.8 STM | H36: 1.0 | I36: 999 | J36: 999 | L36: =J36-K36 -> 999 | M36: =IF(E36="N/A", J36, IF(OR(K36=0, ISBLANK(K36), K36=""), 0, J36-K36)) -> 0
A37: MA | B37: Convênio | C37: 938277 | D37: 2022 | E37: ESCOLA PENAL | F37: CAPITAL | G37: Lente: EF-S 18-135MM F/3.5-5.6 IS STM | H37: 1.0 | I37: 3642.19 | J37: 3642.19 | L37: =J37-K37 -> 3642.19 | M37: =IF(E37="N/A", J37, IF(OR(K37=0, ISBLANK(K37), K37=""), 0, J37-K37)) -> 0
A38: MA | B38: Convênio | C38: 938277 | D38: 2022 | E38: ESCOLA PENAL | F38: CAPITAL | G38: Mesa de som | H38: 1.0 | I38: 3361.9 | J38: 3361.9 | L38: =J38-K38 -> 3361.9 | M38: =IF(E38="N/A", J38, IF(OR(K38=0, ISBLANK(K38), K38=""), 0, J38-K38)) -> 0
A39: MA | B39: Convênio | C39: 938277 | D39: 2022 | E39: ESCOLA PENAL | F39: CAPITAL | G39: Mesa de vídeo | H39: 1.0 | I39: 10091.88 | J39: 10091.88 | L39: =J39-K39 -> 10091.88 | M39: =IF(E39="N/A", J39, IF(OR(K39=0, ISBLANK(K39), K39=""), 0, J39-K39)) -> 0
A40: MA | B40: Convênio | C40: 938277 | D40: 2022 | E40: ESCOLA PENAL | F40: CAPITAL | G40: Monitor de áudio | H40: 1.0 | I40: 4639.54 | J40: 4639.54 | K40: 4639.54 | L40: =J40-K40 -> 0 | M40: =IF(E40="N/A", J40, IF(OR(K40=0, ISBLANK(K40), K40=""), 0, J40-K40)) -> 0
A41: MA | B41: Convênio | C41: 938277 | D41: 2022 | E41: N/A | F41: CAPITAL | G41: SALDO REMANESCENTE | H41: 1.0 | I41: 7267.88 | J41: 7267.88 | K41: 0 | L41: =J41-K41 -> 7267.88 | M41: =IF(E41="N/A", J41, IF(OR(K41=0, ISBLANK(K41), K41=""), 0, J41-K41)) -> 7267.88
A42: MA | B42: Convênio | C42: 938277 | D42: 2022 | E42: CORREGEDORIA | F42: CAPITAL | G42: Scanner de mesa | H42: 16.0 | I42: 2110 | J42: 33760 | L42: =J42-K42 -> 33760 | M42: =IF(E42="N/A", J42, IF(OR(K42=0, ISBLANK(K42), K42=""), 0, J42-K42)) -> 0
A43: MA | B43: Convênio | C43: 938277 | D43: 2022 | E43: ESCOLA PENAL | F43: CAPITAL | G43: Teleprompter | H43: 1.0 | I43: 3480 | J43: 3480 | L43: =J43-K43 -> 3480 | M43: =IF(E43="N/A", J43, IF(OR(K43=0, ISBLANK(K43), K43=""), 0, J43-K43)) -> 0
A44: MA | B44: Convênio | C44: 938277 | D44: 2022 | E44: ESCOLA PENAL | F44: CAPITAL | G44: Tripé profissional com cabeça semi-hidrá | H44: 1.0 | I44: 865.18 | J44: 865.18 | L44: =J44-K44 -> 865.18 | M44: =IF(E44="N/A", J44, IF(OR(K44=0, ISBLANK(K44), K44=""), 0, J44-K44)) -> 0
A45: MA | B45: Convênio | C45: 938277 | D45: 2022 | E45: ESCOLA PENAL | F45: CAPITAL | G45: caixa de som 600w rms | H45: 1.0 | I45: 799.99 | J45: 799.99 | K45: 799.99 | L45: =J45-K45 -> 0 | M45: =IF(E45="N/A", J45, IF(OR(K45=0, ISBLANK(K45), K45=""), 0, J45-K45)) -> 0
A46: MA | B46: Convênio | C46: 938277 | D46: 2022 | E46: ESCOLA PENAL | F46: CAPITAL | G46: cofre de armas | H46: 1.0 | I46: 3835.59 | J46: 3835.59 | K46: 3835.59 | L46: =J46-K46 -> 0 | M46: =IF(E46="N/A", J46, IF(OR(K46=0, ISBLANK(K46), K46=""), 0, J46-K46)) -> 0
A47: MA | B47: Convênio | C47: 938277 | D47: 2022 | E47: ESCOLA PENAL | F47: CAPITAL | G47: computador tipo básico | H47: 1 | I47: 5068 | J47: =H47*I47 -> 5068 | L47: =J47-K47 -> 5068 | M47: =IF(E47="N/A", J47, IF(OR(K47=0, ISBLANK(K47), K47=""), 0, J47-K47)) -> 0
A48: MA | B48: Convênio | C48: 938277 | D48: 2022 | E48: CORREGEDORIA | F48: CAPITAL | G48: computador tipo básico | H48: 2 | I48: 5068 | J48: =H48*I48 -> 10136 | L48: =J48-K48 -> 10136 | M48: =IF(E48="N/A", J48, IF(OR(K48=0, ISBLANK(K48), K48=""), 0, J48-K48)) -> 0
A49: MA | B49: Convênio | C49: 938277 | D49: 2022 | E49: OUVIDORIA | F49: CAPITAL | G49: computador tipo básico | H49: 10 | I49: 5068 | J49: =H49*I49 -> 50680 | L49: =J49-K49 -> 50680 | M49: =IF(E49="N/A", J49, IF(OR(K49=0, ISBLANK(K49), K49=""), 0, J49-K49)) -> 0
A50: MA | B50: Convênio | C50: 938277 | D50: 2022 | E50: ESCOLA PENAL | F50: CAPITAL | G50: data show | H50: 1.0 | I50: 2650 | J50: 2650 | K50: 2650 | L50: =J50-K50 -> 0 | M50: =IF(E50="N/A", J50, IF(OR(K50=0, ISBLANK(K50), K50=""), 0, J50-K50)) -> 0
A51: MA | B51: Convênio | C51: 938277 | D51: 2022 | E51: ESCOLA PENAL | F51: CAPITAL | G51: notebook básico | H51: 2 | I51: 4500 | J51: =H51*I51 -> 9000 | L51: =J51-K51 -> 9000 | M51: =IF(E51="N/A", J51, IF(OR(K51=0, ISBLANK(K51), K51=""), 0, J51-K51)) -> 0
A52: MA | B52: Convênio | C52: 938277 | D52: 2022 | E52: CORREGEDORIA | F52: CAPITAL | G52: notebook básico | H52: 10 | I52: 4500 | J52: =H52*I52 -> 45000 | L52: =J52-K52 -> 45000 | M52: =IF(E52="N/A", J52, IF(OR(K52=0, ISBLANK(K52), K52=""), 0, J52-K52)) -> 0
A53: MA | B53: Convênio | C53: 938277 | D53: 2022 | E53: OUVIDORIA | F53: CAPITAL | G53: notebook básico | H53: 2 | I53: 4500 | J53: =H53*I53 -> 9000 | L53: =J53-K53 -> 9000 | M53: =IF(E53="N/A", J53, IF(OR(K53=0, ISBLANK(K53), K53=""), 0, J53-K53)) -> 0

Sheet PB
A1: UF | B1: INSTRUMENTO | C1: NÚMERO | D1: ANO | E1: ÁREA | F1: NATUREZA | G1: DESCRIÇÃO | H1: QUANTIDADE | I1: VALOR UNITÁRIO | J1: VALOR TOTAL PREVISTO | K1: VALOR TOTAL EXECUTADO | L1: SALDO | M1: SALDO ECONOMICIDADE
A2: PB | B2: Convênio | C2: 937818 | D2: 2022 | E2: CORREGEDORIA | F2: CUSTEIO | G2: CONTRATAÇÃO de instituição de ensino par | H2: 1.0 | I2: 76333.33 | J2: 76333.33 | L2: 76333.33 | M2: =IF(E2="N/A", J2, IF(OR(K2=0, ISBLANK(K2), K2=""), 0, J2-K2)) -> 0
A3: PB | B3: Convênio | C3: 937818 | D3: 2022 | E3: OUVIDORIA | F3: CAPITAL | G3: CAIXA de som amplificada com potência má | H3: 2 | I3: 1399 | J3: =H3*I3 -> 2798 | L3: 2798 | M3: =IF(E3="N/A", J3, IF(OR(K3=0, ISBLANK(K3), K3=""), 0, J3-K3)) -> 0
A4: PB | B4: Convênio | C4: 937818 | D4: 2022 | E4: ESCOLA PENAL | F4: CAPITAL | G4: CAIXA de som amplificada com potência má | H4: 8 | I4: 1399 | J4: =H4*I4 -> 11192 | L4: 11192 | M4: =IF(E4="N/A", J4, IF(OR(K4=0, ISBLANK(K4), K4=""), 0, J4-K4)) -> 0
A5: PB | B5: Convênio | C5: 937818 | D5: 2022 | E5: ESCOLA PENAL | F5: CAPITAL | G5: NOTEBOOK TIPO II Processador: AMD Ryzen | H5: 19.0 | I5: 2464 | J5: 46816 | L5: 46816 | M5: =IF(E5="N/A", J5, IF(OR(K5=0, ISBLANK(K5), K5=""), 0, J5-K5)) -> 0
A6: PB | B6: Convênio | C6: 937818 | D6: 2022 | E6: ESCOLA PENAL | F6: CAPITAL | G6: NOTEBOOK TIPO II Processador: AMD Ryzen | H6: 10 | I6: 2573.7 | J6: =H6*I6 -> 25737 | L6: 25737 | M6: =IF(E6="N/A", J6, IF(OR(K6=0, ISBLANK(K6), K6=""), 0, J6-K6)) -> 0
A7: PB | B7: Convênio | C7: 937818 | D7: 2022 | E7: CORREGEDORIA | F7: CAPITAL | G7: NOTEBOOK TIPO II Processador: AMD Ryzen | H7: 6 | I7: 2573.7 | J7: =H7*I7 -> 15442.2 | L7: 15442.2 | M7: =IF(E7="N/A", J7, IF(OR(K7=0, ISBLANK(K7), K7=""), 0, J7-K7)) -> 0
A8: PB | B8: Convênio | C8: 937818 | D8: 2022 | E8: OUVIDORIA | F8: CAPITAL | G8: NOTEBOOK TIPO III Processador: AMD Ryze | H8: 2.0 | I8: 8498 | J8: 16996 | L8: 16996 | M8: =IF(E8="N/A", J8, IF(OR(K8=0, ISBLANK(K8), K8=""), 0, J8-K8)) -> 0
A9: PB | B9: Convênio | C9: 937818 | D9: 2022 | E9: OUVIDORIA | F9: CAPITAL | G9: PROJETOR Multimídia 3500 lumens 1024 x 7 | H9: 2 | I9: 2490.01 | J9: =H9*I9 -> 4980.02 | L9: 4980.02 | M9: =IF(E9="N/A", J9, IF(OR(K9=0, ISBLANK(K9), K9=""), 0, J9-K9)) -> 0
A10: PB | B10: Convênio | C10: 937818 | D10: 2022 | E10: ESCOLA PENAL | F10: CAPITAL | G10: PROJETOR Multimídia 3500 lumens 1024 x 7 | H10: 8 | I10: 2490.01 | J10: =H10*I10 -> 19920.08 | L10: 19920.08 | M10: =IF(E10="N/A", J10, IF(OR(K10=0, ISBLANK(K10), K10=""), 0, J10-K10)) -> 0
A11: PB | B11: Convênio | C11: 937818 | D11: 2022 | E11: ESCOLA PENAL | F11: CAPITAL | G11: CONDICIONADOR de ar tipo split Hi Wall, | H11: 13.0 | I11: 1895 | J11: 24635 | K11: 24635 | L11: 0 | M11: =IF(E11="N/A", J11, IF(OR(K11=0, ISBLANK(K11), K11=""), 0, J11-K11)) -> 0
A12: PB | B12: Convênio | C12: 937818 | D12: 2022 | E12: ESCOLA PENAL | F12: CAPITAL | G12: CONDICIONADOR de ar tipo split Hi Wall, | H12: 2.0 | I12: 1895 | J12: 3790 | L12: 3790 | M12: =IF(E12="N/A", J12, IF(OR(K12=0, ISBLANK(K12), K12=""), 0, J12-K12)) -> 0
A13: PB | B13: Convênio | C13: 937818 | D13: 2022 | E13: ESCOLA PENAL | F13: CAPITAL | G13: CONDICIONADOR de ar tipo split Hi Wall, | H13: 2.0 | I13: 1895 | J13: 3790 | K13: 3790 | L13: 0 | M13: =IF(E13="N/A", J13, IF(OR(K13=0, ISBLANK(K13), K13=""), 0, J13-K13)) -> 0
A14: PB | B14: Convênio | C14: 937818 | D14: 2022 | E14: ESCOLA PENAL | F14: CAPITAL | G14: CONDICIONADOR de ar tipo split, capacida | H14: 10.0 | I14: 4599 | J14: 45990 | L14: 45990 | M14: =IF(E14="N/A", J14, IF(OR(K14=0, ISBLANK(K14), K14=""), 0, J14-K14)) -> 0
A15: PB | B15: Convênio | C15: 937818 | D15: 2022 | E15: CORREGEDORIA | F15: CAPITAL | G15: Câmera profissional digital de lente cam | H15: 1 | I15: 3759.52 | J15: 3759.52 | L15: 3759.52 | M15: =IF(E15="N/A", J15, IF(OR(K15=0, ISBLANK(K15), K15=""), 0, J15-K15)) -> 0
A16: PB | B16: Convênio | C16: 937818 | D16: 2022 | E16: ESCOLA PENAL | F16: CAPITAL | G16: Câmera profissional digital de lente cam | H16: 2 | I16: 3759.52 | J16: =H16*I16 -> 7519.04 | L16: 7519.04 | M16: =IF(E16="N/A", J16, IF(OR(K16=0, ISBLANK(K16), K16=""), 0, J16-K16)) -> 0
A17: PB | B17: Convênio | C17: 937818 | D17: 2022 | E17: ESCOLA PENAL | F17: CAPITAL | G17: NOTEBOOK Avançado com as seguintes Carac | H17: 1.0 | I17: 5398.9 | J17: 5398.9 | L17: 5398.9 | M17: =IF(E17="N/A", J17, IF(OR(K17=0, ISBLANK(K17), K17=""), 0, J17-K17)) -> 0
A18: PB | B18: Convênio | C18: 937818 | D18: 2022 | E18: OUVIDORIA | F18: CAPITAL | G18: Smart TV Led 55, Televisor 55 Polegadas, | H18: 1.0 | I18: 2660 | J18: 2660 | K18: 2660 | L18: 0 | M18: =IF(E18="N/A", J18, IF(OR(K18=0, ISBLANK(K18), K18=""), 0, J18-K18)) -> 0

Sheet PI
A1: UF | B1: INSTRUMENTO | C1: NÚMERO | D1: ANO | E1: ÁREA | F1: NATUREZA | G1: DESCRIÇÃO | H1: QUANTIDADE | I1: VALOR UNITÁRIO | J1: VALOR TOTAL PREVISTO | K1: VALOR TOTAL EXECUTADO | L1: SALDO | M1: SALDO ECONOMICIDADE
A2: PI | B2: Convênio | C2: 937780 | D2: 2022 | E2: ESCOLA PENAL | F2: CUSTEIO | G2: Alvo para Stand de Tiro | H2: 500.0 | I2: 2.06 | J2: 1030 | K2: 1030 | L2: 0 | M2: =IF(E2="N/A", J2, IF(OR(K2=0, ISBLANK(K2), K2=""), 0, J2-K2)) -> 0
A3: PI | B3: Convênio | C3: 937780 | D3: 2022 | E3: ESCOLA PENAL | F3: CUSTEIO | G3: Camisa manga longa/Instrutor | H3: 60.0 | I3: 46.98 | J3: 2818.8 | K3: 2818.8 | L3: 0 | M3: =IF(E3="N/A", J3, IF(OR(K3=0, ISBLANK(K3), K3=""), 0, J3-K3)) -> 0
A4: PI | B4: Convênio | C4: 937780 | D4: 2022 | E4: OUVIDORIA | F4: CUSTEIO | G4: Camiseta | H4: 40.0 | I4: 40.26 | J4: 1610.4 | L4: 1610.4 | M4: =IF(E4="N/A", J4, IF(OR(K4=0, ISBLANK(K4), K4=""), 0, J4-K4)) -> 0
A5: PI | B5: Convênio | C5: 937780 | D5: 2022 | E5: OUVIDORIA | F5: CUSTEIO | G5: Banner | H5: 18.0 | I5: 107.33 | J5: 1931.94 | L5: 1931.94 | M5: =IF(E5="N/A", J5, IF(OR(K5=0, ISBLANK(K5), K5=""), 0, J5-K5)) -> 0
A6: PI | B6: Convênio | C6: 937780 | D6: 2022 | E6: OUVIDORIA | F6: CUSTEIO | G6: Cartilha | H6: 2000.0 | I6: 2.35 | J6: 4700 | L6: 4700 | M6: =IF(E6="N/A", J6, IF(OR(K6=0, ISBLANK(K6), K6=""), 0, J6-K6)) -> 0
A7: PI | B7: Convênio | C7: 937780 | D7: 2022 | E7: OUVIDORIA | F7: CUSTEIO | G7: Folder | H7: 2000.0 | I7: 0.52 | J7: 1040 | L7: 1040 | M7: =IF(E7="N/A", J7, IF(OR(K7=0, ISBLANK(K7), K7=""), 0, J7-K7)) -> 0
A8: PI | B8: Convênio | C8: 937780 | D8: 2022 | E8: ESCOLA PENAL | F8: CUSTEIO | G8: Bluegun - G17 - Pró Laser | H8: 5.0 | I8: 837.3 | J8: 4186.5 | L8: 4186.5 | M8: =IF(E8="N/A", J8, IF(OR(K8=0, ISBLANK(K8), K8=""), 0, J8-K8)) -> 0
A9: PI | B9: Convênio | C9: 937780 | D9: 2022 | E9: ESCOLA PENAL | F9: CUSTEIO | G9: Bluegun - G17 - Pró shock | H9: 6.0 | I9: 276.66 | J9: 1659.96 | L9: 1659.96 | M9: =IF(E9="N/A", J9, IF(OR(K9=0, ISBLANK(K9), K9=""), 0, J9-K9)) -> 0
A10: PI | B10: Convênio | C10: 937780 | D10: 2022 | E10: ESCOLA PENAL | F10: CUSTEIO | G10: Tatames/Placas 1mx1mx0,40m. | H10: 70.0 | I10: 133.7 | J10: 9359 | L10: 9359 | M10: =IF(E10="N/A", J10, IF(OR(K10=0, ISBLANK(K10), K10=""), 0, J10-K10)) -> 0
A11: PI | B11: Convênio | C11: 937780 | D11: 2022 | E11: OUVIDORIA | F11: CUSTEIO | G11: Urnas de Acrílico | H11: 18.0 | I11: 189.38 | J11: 3408.8 | L11: 3408.8 | M11: =IF(E11="N/A", J11, IF(OR(K11=0, ISBLANK(K11), K11=""), 0, J11-K11)) -> 0
A12: PI | B12: Convênio | C12: 937780 | D12: 2022 | E12: CORREGEDORIA | F12: CUSTEIO | G12: Curso de Pós Graduação latu sensu em Pro | H12: 8.0 | I12: 2017.25 | J12: 16138 | L12: 16138 | M12: =IF(E12="N/A", J12, IF(OR(K12=0, ISBLANK(K12), K12=""), 0, J12-K12)) -> 0
A13: PI | B13: Convênio | C13: 937780 | D13: 2022 | E13: ESCOLA PENAL | F13: CUSTEIO | G13: Curso de Pós-Graduação latu sensu em Ges | H13: 12.0 | I13: 1893.6 | J13: 22723.2 | K13: 22625 | L13: 98.2 | M13: =IF(E13="N/A", J13, IF(OR(K13=0, ISBLANK(K13), K13=""), 0, J13-K13)) -> 98.2
A14: PI | B14: Convênio | C14: 937780 | D14: 2022 | E14: OUVIDORIA | F14: CAPITAL | G14: Smartphone | H14: 2.0 | I14: 3607.33 | J14: 7214.66 | L14: 7214.66 | M14: =IF(E14="N/A", J14, IF(OR(K14=0, ISBLANK(K14), K14=""), 0, J14-K14)) -> 0
A15: PI | B15: Convênio | C15: 937780 | D15: 2022 | E15: OUVIDORIA | F15: CAPITAL | G15: Armário baixo 800 x 500 x 740 mm | H15: 1.0 | I15: 977.22 | J15: 977.22 | L15: 977.22 | M15: =IF(E15="N/A", J15, IF(OR(K15=0, ISBLANK(K15), K15=""), 0, J15-K15)) -> 0
A16: PI | B16: Convênio | C16: 937780 | D16: 2022 | E16: OUVIDORIA | F16: CAPITAL | G16: Cadeira fixa média com braços | H16: 6.0 | I16: 895.51 | J16: 5373.06 | L16: 5373.06 | M16: =IF(E16="N/A", J16, IF(OR(K16=0, ISBLANK(K16), K16=""), 0, J16-K16)) -> 0
A17: PI | B17: Convênio | C17: 937780 | D17: 2022 | E17: OUVIDORIA | F17: CAPITAL | G17: Cadeira operacional espaldar alto, com b | H17: 3.0 | I17: 1358.33 | J17: 4074.99 | L17: 4074.99 | M17: =IF(E17="N/A", J17, IF(OR(K17=0, ISBLANK(K17), K17=""), 0, J17-K17)) -> 0
A18: PI | B18: Convênio | C18: 937780 | D18: 2022 | E18: OUVIDORIA | F18: CAPITAL | G18: Cadeira operacional espaldar médio, com | H18: 5.0 | I18: 1048.72 | J18: 5243.6 | L18: 5243.6 | M18: =IF(E18="N/A", J18, IF(OR(K18=0, ISBLANK(K18), K18=""), 0, J18-K18)) -> 0
A19: PI | B19: Convênio | C19: 937780 | D19: 2022 | E19: OUVIDORIA | F19: CAPITAL | G19: Headset Fone | H19: 3.0 | I19: 255.23 | J19: 765.69 | L19: 765.69 | M19: =IF(E19="N/A", J19, IF(OR(K19=0, ISBLANK(K19), K19=""), 0, J19-K19)) -> 0
A20: PI | B20: Convênio | C20: 937780 | D20: 2022 | E20: OUVIDORIA | F20: CAPITAL | G20: Longarina de 2 lugares com brçaos | H20: 3.0 | I20: 1760.37 | J20: 5281.11 | L20: 5281.11 | M20: =IF(E20="N/A", J20, IF(OR(K20=0, ISBLANK(K20), K20=""), 0, J20-K20)) -> 0
A21: PI | B21: Convênio | C21: 937780 | D21: 2022 | E21: OUVIDORIA | F21: CAPITAL | G21: Mesa em L, dimensões: 1400 x 600 x 1400 | H21: 1.0 | I21: 1603.77 | J21: 1603.77 | L21: 1603.77 | M21: =IF(E21="N/A", J21, IF(OR(K21=0, ISBLANK(K21), K21=""), 0, J21-K21)) -> 0
A22: PI | B22: Convênio | C22: 937780 | D22: 2022 | E22: OUVIDORIA | F22: CAPITAL | G22: Mesa reunião redonda, dimensões: 1200 x | H22: 1.0 | I22: 1225.53 | J22: 1225.53 | L22: 1225.53 | M22: =IF(E22="N/A", J22, IF(OR(K22=0, ISBLANK(K22), K22=""), 0, J22-K22)) -> 0
A23: PI | B23: Convênio | C23: 937780 | D23: 2022 | E23: N/A | F23: CAPITAL | G23: Saldo Residual após o ajuste do PT | H23: 1.0 | I23: 5.03 | J23: 5.03 | K23: 0 | L23: 5.03 | M23: =IF(E23="N/A", J23, IF(OR(K23=0, ISBLANK(K23), K23=""), 0, J23-K23)) -> 5.03
A24: PI | B24: Convênio | C24: 937780 | D24: 2022 | E24: ESCOLA PENAL | F24: CAPITAL | G24: Veículo Administrativo, Modelo SUV | H24: 1 | I24: 153000 | J24: 153000 | L24: 153000 | M24: =IF(E24="N/A", J24, IF(OR(K24=0, ISBLANK(K24), K24=""), 0, J24-K24)) -> 0
A25: PI | B25: Convênio | C25: 937780 | D25: 2022 | E25: CORREGEDORIA | F25: CAPITAL | G25: Veículo Administrativo, Modelo SUV | H25: 1 | I25: 153000 | J25: 153000 | L25: 153000 | M25: =IF(E25="N/A", J25, IF(OR(K25=0, ISBLANK(K25), K25=""), 0, J25-K25)) -> 0

Sheet RO
A1: UF | B1: INSTRUMENTO | C1: NÚMERO | D1: ANO | E1: ÁREA | F1: NATUREZA | G1: DESCRIÇÃO | H1: QUANTIDADE | I1: VALOR UNITÁRIO | J1: VALOR TOTAL PREVISTO | K1: VALOR TOTAL EXECUTADO | L1: SALDO | M1: SALDO ECONOMICIDADE
A2: RO | B2: Convênio | C2: 937917 | D2: 2022 | E2: CORREGEDORIA | F2: CUSTEIO | G2: Descanso Ergonômico Apoio de punho para | H2: 25.0 | I2: 99.9 | J2: 2497.42 | L2: 2497.42 | M2: =IF(E2="N/A", J2, IF(OR(K2=0, ISBLANK(K2), K2=""), 0, J2-K2)) -> 0
A3: RO | B3: Convênio | C3: 937917 | D3: 2022 | E3: OUVIDORIA | F3: CUSTEIO | G3: Adesivo 60 x 50 | H3: 400.0 | I3: 43 | J3: 17200 | K3: 4000 | L3: 13200 | M3: =IF(E3="N/A", J3, IF(OR(K3=0, ISBLANK(K3), K3=""), 0, J3-K3)) -> 13200
A4: RO | B4: Convênio | C4: 937917 | D4: 2022 | E4: OUVIDORIA | F4: CUSTEIO | G4: Banner 0,60 x 0,50 | H4: 275.0 | I4: 21.17 | J4: 5820.83 | K4: 4950 | L4: 870.83 | M4: =IF(E4="N/A", J4, IF(OR(K4=0, ISBLANK(K4), K4=""), 0, J4-K4)) -> 870.83
A5: RO | B5: Convênio | C5: 937917 | D5: 2022 | E5: OUVIDORIA | F5: CUSTEIO | G5: Placa PVC 70 x 60 | H5: 100.0 | I5: 54.33 | J5: 5433.33 | K5: 4500 | L5: 933.33 | M5: =IF(E5="N/A", J5, IF(OR(K5=0, ISBLANK(K5), K5=""), 0, J5-K5)) -> 933.33
A6: RO | B6: Convênio | C6: 937917 | D6: 2022 | E6: CORREGEDORIA | F6: CAPITAL | G6: Mesa de escritório em L com gavetas | H6: 6.0 | I6: 668.73 | J6: 4012.38 | L6: 4012.38 | M6: =IF(E6="N/A", J6, IF(OR(K6=0, ISBLANK(K6), K6=""), 0, J6-K6)) -> 0
A7: RO | B7: Convênio | C7: 937917 | D7: 2022 | E7: ESCOLA PENAL | F7: CAPITAL | G7: Caixa amplificada de som 300w | H7: 2.0 | I7: 3435.74 | J7: 6871.47 | L7: 6871.47 | M7: =IF(E7="N/A", J7, IF(OR(K7=0, ISBLANK(K7), K7=""), 0, J7-K7)) -> 0
A8: RO | B8: Convênio | C8: 937917 | D8: 2022 | E8: ESCOLA PENAL | F8: CAPITAL | G8: Câmera de Vídeo Profissional | H8: 1.0 | I8: 8322.54 | J8: 8322.54 | L8: 8322.54 | M8: =IF(E8="N/A", J8, IF(OR(K8=0, ISBLANK(K8), K8=""), 0, J8-K8)) -> 0
A9: RO | B9: Convênio | C9: 937917 | D9: 2022 | E9: ESCOLA PENAL | F9: CAPITAL | G9: Gravador de Áudio Portátil Profissional | H9: 2.0 | I9: 2246.25 | J9: 4492.5 | L9: 4492.5 | M9: =IF(E9="N/A", J9, IF(OR(K9=0, ISBLANK(K9), K9=""), 0, J9-K9)) -> 0
A10: RO | B10: Convênio | C10: 937917 | D10: 2022 | E10: ESCOLA PENAL | F10: CAPITAL | G10: Microfone Direcional | H10: 2.0 | I10: 1211.84 | J10: 2423.68 | L10: 2423.68 | M10: =IF(E10="N/A", J10, IF(OR(K10=0, ISBLANK(K10), K10=""), 0, J10-K10)) -> 0
A11: RO | B11: Convênio | C11: 937917 | D11: 2022 | E11: ESCOLA PENAL | F11: CAPITAL | G11: Microfone de Lapela sem fio | H11: 2.0 | I11: 3566.85 | J11: 7133.69 | L11: 7133.69 | M11: =IF(E11="N/A", J11, IF(OR(K11=0, ISBLANK(K11), K11=""), 0, J11-K11)) -> 0
A12: RO | B12: Convênio | C12: 937917 | D12: 2022 | E12: ESCOLA PENAL | F12: CAPITAL | G12: Projetor 3.400 lumens, Hdmi. | H12: 2.0 | I12: 4646.18 | J12: 9292.36 | L12: 9292.36 | M12: =IF(E12="N/A", J12, IF(OR(K12=0, ISBLANK(K12), K12=""), 0, J12-K12)) -> 0
A13: RO | B13: Convênio | C13: 937917 | D13: 2022 | E13: ESCOLA PENAL | F13: CAPITAL | G13: Teleprompter Profissional com Led | H13: 1.0 | I13: 3634.44 | J13: 3634.44 | L13: 3634.44 | M13: =IF(E13="N/A", J13, IF(OR(K13=0, ISBLANK(K13), K13=""), 0, J13-K13)) -> 0
A14: RO | B14: Convênio | C14: 937917 | D14: 2022 | E14: ESCOLA PENAL | F14: CAPITAL | G14: Tripé para Câmera de Vídeo | H14: 1.0 | I14: 1295.52 | J14: 1295.52 | L14: 1295.52 | M14: =IF(E14="N/A", J14, IF(OR(K14=0, ISBLANK(K14), K14=""), 0, J14-K14)) -> 0
A15: RO | B15: Convênio | C15: 937917 | D15: 2022 | E15: CORREGEDORIA | F15: CAPITAL | G15: Monitor 23 polegadas | H15: 8.0 | I15: 1053.33 | J15: 8426.64 | L15: 8426.64 | M15: =IF(E15="N/A", J15, IF(OR(K15=0, ISBLANK(K15), K15=""), 0, J15-K15)) -> 0
A16: RO | B16: Convênio | C16: 937917 | D16: 2022 | E16: ESCOLA PENAL | F16: CAPITAL | G16: Notebook core i7 8GB 512GB SSD Tela Full | H16: 2.0 | I16: 6546.04 | J16: 13092.07 | L16: 13092.07 | M16: =IF(E16="N/A", J16, IF(OR(K16=0, ISBLANK(K16), K16=""), 0, J16-K16)) -> 0
A17: RO | B17: Convênio | C17: 937917 | D17: 2022 | E17: ESCOLA PENAL | F17: CAPITAL | G17: Cadeira Longarina 3 lugares | H17: 4.0 | I17: 858.03 | J17: 3432.11 | L17: 3432.11 | M17: =IF(E17="N/A", J17, IF(OR(K17=0, ISBLANK(K17), K17=""), 0, J17-K17)) -> 0
... A38: RO | B38: Convênio | C38: 937917 | D38: 2022 | E38: OUVIDORIA | F38: CAPITAL | G38: Webcam Full Hd 4k Microfone Conexão | H38: 12.0 | I38: 246.65 | J38: 2959.8 | L38: 2959.8 | M38: =IF(E38="N/A", J38, IF(OR(K38=0, ISBLANK(K38), K38=""), 0, J38-K38)) -> 0

Sheet TO
A1: UF | B1: INSTRUMENTO | C1: NÚMERO | D1: ANO | E1: ÁREA | F1: NATUREZA | G1: DESCRIÇÃO | H1: QUANTIDADE | I1: VALOR UNITÁRIO | J1: VALOR TOTAL PREVISTO | K1: VALOR TOTAL EXECUTADO | L1: SALDO | M1: SALDO ECONOMICIDADE
A2: TO | B2: Convênio | C2: 937468 | D2: 2022 | E2: N/A | F2: CUSTEIO | G2: Saldo de Economicidade - despesas de custeio | H2: 1.0 | I2: 13594.58 | J2: 13594.58 | K2: 0 | L2: 13594.58 | M2: =IF(E2="N/A", J2, IF(OR(K2=0, ISBLANK(K2), K2=""), 0, J2-K2)) -> 13594.58
A3: TO | B3: Convênio | C3: 937468 | D3: 2022 | E3: OUVIDORIA | F3: CUSTEIO | G3: ETAPA 1 - OUVIDORIA - Apoio ergonômico p | H3: 3.0 | I3: 70 | J3: 210 | L3: 210 | M3: =IF(E3="N/A", J3, IF(OR(K3=0, ISBLANK(K3), K3=""), 0, J3-K3)) -> 0
A4: TO | B4: Convênio | C4: 937468 | D4: 2022 | E4: OUVIDORIA | F4: CUSTEIO | G4: ETAPA 1 - OUVIDORIA - Caixa de som para | H4: 3.0 | I4: 55.77 | J4: 167.31 | L4: 167.31 | M4: =IF(E4="N/A", J4, IF(OR(K4=0, ISBLANK(K4), K4=""), 0, J4-K4)) -> 0
A5: TO | B5: Convênio | C5: 937468 | D5: 2022 | E5: OUVIDORIA | F5: CUSTEIO | G5: ETAPA 1 - OUVIDORIA - Headset Microfone | H5: 3.0 | I5: 166.33 | J5: 499 | L5: 499 | M5: =IF(E5="N/A", J5, IF(OR(K5=0, ISBLANK(K5), K5=""), 0, J5-K5)) -> 0
A6: TO | B6: Convênio | C6: 937468 | D6: 2022 | E6: OUVIDORIA | F6: CUSTEIO | G6: ETAPA 1 - OUVIDORIA - Webcam: Câmera Web | H6: 3.0 | I6: 104 | J6: 312 | L6: 312 | M6: =IF(E6="N/A", J6, IF(OR(K6=0, ISBLANK(K6), K6=""), 0, J6-K6)) -> 0
A7: TO | B7: Convênio | C7: 937468 | D7: 2022 | E7: CORREGEDORIA | F7: CUSTEIO | G7: ETAPA 2 - CORREGEDORIA - Apoio ergonômic | H7: 7.0 | I7: 70 | J7: 490 | L7: 490 | M7: =IF(E7="N/A", J7, IF(OR(K7=0, ISBLANK(K7), K7=""), 0, J7-K7)) -> 0
A8: TO | B8: Convênio | C8: 937468 | D8: 2022 | E8: CORREGEDORIA | F8: CUSTEIO | G8: ETAPA 2 - CORREGEDORIA - Fone de ouvido | H8: 15.0 | I8: 171.68 | J8: 2575.2 | L8: 2575.2 | M8: =IF(E8="N/A", J8, IF(OR(K8=0, ISBLANK(K8), K8=""), 0, J8-K8)) -> 0
A9: TO | B9: Convênio | C9: 937468 | D9: 2022 | E9: CORREGEDORIA | F9: CUSTEIO | G9: ETAPA 2 - CORREGEDORIA - Headset Microfone | H9: 7.0 | I9: 166.33 | J9: 1164.31 | L9: 1164.31 | M9: =IF(E9="N/A", J9, IF(OR(K9=0, ISBLANK(K9), K9=""), 0, J9-K9)) -> 0
A10: TO | B10: Convênio | C10: 937468 | D10: 2022 | E10: CORREGEDORIA | F10: CUSTEIO | G10: ETAPA 2 - CORREGEDORIA - Webcam: Câmera | H10: 7.0 | I10: 104 | J10: 728 | L10: 728 | M10: =IF(E10="N/A", J10, IF(OR(K10=0, ISBLANK(K10), K10=""), 0, J10-K10)) -> 0
A11: TO | B11: Convênio | C11: 937468 | D11: 2022 | E11: ESCOLA PENAL | F11: CUSTEIO | G11: ETAPA 3 ESCOLA - BASTÃO POLICIAL PR-24 | H11: 32.0 | I11: 61.82 | J11: 1978.13 | L11: 1978.13 | M11: =IF(E11="N/A", J11, IF(OR(K11=0, ISBLANK(K11), K11=""), 0, J11-K11)) -> 0
A12: TO | B12: Convênio | C12: 937468 | D12: 2022 | E12: ESCOLA PENAL | F12: CUSTEIO | G12: ETAPA 3 ESCOLA - BATERIA DE PISTOLA AIR | H12: 15.0 | I12: 191.98 | J12: 2879.7 | L12: 2879.7 | M12: =IF(E12="N/A", J12, IF(OR(K12=0, ISBLANK(K12), K12=""), 0, J12-K12)) -> 0
A13: TO | B13: Convênio | C13: 937468 | D13: 2022 | E13: ESCOLA PENAL | F13: CUSTEIO | G13: ETAPA 3 ESCOLA - BATERIA P/CARABINA AIR | H13: 15.0 | I13: 240.71 | J13: 3610.65 | L13: 3610.65 | M13: =IF(E13="N/A", J13, IF(OR(K13=0, ISBLANK(K13), K13=""), 0, J13-K13)) -> 0
A14: TO | B14: Convênio | C14: 937468 | D14: 2022 | E14: ESCOLA PENAL | F14: CUSTEIO | G14: ETAPA 3 ESCOLA - CADEIRA PLASTICA | H14: 50.0 | I14: 49 | J14: 2450 | L14: 2450 | M14: =IF(E14="N/A", J14, IF(OR(K14=0, ISBLANK(K14), K14=""), 0, J14-K14)) -> 0
... A37: TO | B37: Convênio | C37: 937468 | D37: 2022 | E37: OUVIDORIA | F37: CAPITAL | G37: ETAPA 1 - OUVIDORIA - Monitor | H37: 3.0 | I37: 1179.99 | J37: 3539.97 | L37: 3539.97 | M37: =IF(E37="N/A", J37, IF(OR(K37=0, ISBLANK(K37), K37=""), 0, J37-K37)) -> 0
A38: TO | B38: Convênio | C38: 937468 | D38: 2022 | E38: OUVIDORIA | F38: CAPITAL | G38: ETAPA 1 - OUVIDORIA - Nobreak: Peça/Comp | H38: 3.0 | I38: 448 | J38: 1344 | K38: 1344 | L38: 1344 | M38: =IF(E38="N/A", J38, IF(OR(K38=0, ISBLANK(K38), K38=""), 0, J38-K38)) -> 0
A39: TO | B39: Convênio | C39: 937468 | D39: 2022 | E39: OUVIDORIA | F39: CAPITAL | G39: ETAPA 1 - OUVIDORIA - Notebook: Bateria: | H39: 3.0 | I39: 7446 | J39: 22338 | L39: 22338 | M39: =IF(E39="N/A", J39, IF(OR(K39=0, ISBLANK(K39), K39=""), 0, J39-K39)) -> 0
A40: TO | B40: Convênio | C40: 937468 | D40: 2022 | E40: CORREGEDORIA | F40: CAPITAL | G40: ETAPA 2 - CORREGEDORIA - CPU: Microcompu | H40: 3.0 | I40: 9163.33 | J40: 27489.99 | L40: 27489.99 | M40: =IF(E40="N/A", J40, IF(OR(K40=0, ISBLANK(K40), K40=""), 0, J40-K40)) -> 0
A41: TO | B41: Convênio | C41: 937468 | D41: 2022 | E41: CORREGEDORIA | F41: CAPITAL | G41: ETAPA 2 - CORREGEDORIA - Cadeira giratór | H41: 16.0 | I41: 1200 | J41: 19200 | L41: 19200 | M41: =IF(E41="N/A", J41, IF(OR(K41=0, ISBLANK(K41), K41=""), 0, J41-K41)) -> 0
A42: TO | B42: Convênio | C42: 937468 | D42: 2022 | E42: CORREGEDORIA | F42: CAPITAL | G42: ETAPA 2 - CORREGEDORIA - Mesa reta: esta | H42: 17.0 | I42: 506.15 | J42: 8604.55 | L42: 8604.55 | M42: =IF(E42="N/A", J42, IF(OR(K42=0, ISBLANK(K42), K42=""), 0, J42-K42)) -> 0
A43: TO | B43: Convênio | C43: 937468 | D43: 2022 | E43: CORREGEDORIA | F43: CAPITAL | G43: ETAPA 2 - CORREGEDORIA - Monitor | H43: 6.0 | I43: 1179.99 | J43: 7079.94 | K43: 10619.91 | L43: -3539.97 | M43: =IF(E43="N/A", J43, IF(OR(K43=0, ISBLANK(K43), K43=""), 0, J43-K43)) -> -3539.97
A44: TO | B44: Convênio | C44: 937468 | D44: 2022 | E44: CORREGEDORIA | F44: CAPITAL | G44: ETAPA 2 - CORREGEDORIA - Nobreak: Peça/ | H44: 3.0 | I44: 448 | J44: 1344 | K44: 1344 | L44: 1344 | M44: =IF(E44="N/A", J44, IF(OR(K44=0, ISBLANK(K44), K44=""), 0, J44-K44)) -> 0
A45: TO | B45: Convênio | C45: 937468 | D45: 2022 | E45: CORREGEDORIA | F45: CAPITAL | G45: ETAPA 2 - CORREGEDORIA - Televisão: - 50 | H45: 1.0 | I45: 2332.67 | J45: 2332.67 | L45: 2332.67 | M45: =IF(E45="N/A", J45, IF(OR(K45=0, ISBLANK(K45), K45=""), 0, J45-K45)) -> 0
A46: TO | B46: Convênio | C46: 937468 | D46: 2022 | E46: ESCOLA PENAL | F46: CAPITAL | G46: ETAPA 3 ESCOLA - BEBEDOURO DE ALUMINIO | H46: 1.0 | I46: 3020.33 | J46: 3020.33 | L46: 3020.33 | M46: =IF(E46="N/A", J46, IF(OR(K46=0, ISBLANK(K46), K46=""), 0, J46-K46)) -> 0
A47: TO | B47: Convênio | C47: 937468 | D47: 2022 | E47: ESCOLA PENAL | F47: CAPITAL | G47: ETAPA 3 ESCOLA - CAFETEIRA INDUSTRIAL | H47: 1.0 | I47: 929.38 | J47: 929.38 | L47: 929.38 | M47: =IF(E47="N/A", J47, IF(OR(K47=0, ISBLANK(K47), K47=""), 0, J47-K47)) -> 0
A48: TO | B48: Convênio | C48: 937468 | D48: 2022 | E48: ESCOLA PENAL | F48: CAPITAL | G48: ETAPA 3 ESCOLA - CARABINA AIRSOFT-ELÉTR | H48: 6.0 | I48: 1837.7 | J48: 11026.2 | L48: 11026.2 | M48: =IF(E48="N/A", J48, IF(OR(K48=0, ISBLANK(K48), K48=""), 0, J48-K48)) -> 0
A49: TO | B49: Convênio | C49: 937468 | D49: 2022 | E49: ESCOLA PENAL | F49: CAPITAL | G49: ETAPA 3 ESCOLA - GELADEIRA 340 LITROS | H49: 1.0 | I49: 2500 | J49: 2500 | K49: 2500 | L49: 0 | M49: =IF(E49="N/A", J49, IF(OR(K49=0, ISBLANK(K49), K49=""), 0, J49-K49)) -> 0
A50: TO | B50: Convênio | C50: 937468 | D50: 2022 | E50: ESCOLA PENAL | F50: CAPITAL | G50: ETAPA 3 ESCOLA - MEGAFONE PROFISSIONAL | H50: 2.0 | I50: 332.1 | J50: 664.2 | L50: 664.2 | M50: =IF(E50="N/A", J50, IF(OR(K50=0, ISBLANK(K50), K50=""), 0, J50-K50)) -> 0
A51: TO | B51: Convênio | C51: 937468 | D51: 2022 | E51: ESCOLA PENAL | F51: CAPITAL | G51: ETAPA 3 ESCOLA - MICROONDAS | H51: 2.0 | I51: 659 | J51: 1318 | K51: 1318 | L51: 0 | M51: =IF(E51="N/A", J51, IF(OR(K51=0, ISBLANK(K51), K51=""), 0, J51-K51)) -> 0
A52: TO | B52: Convênio | C52: 937468 | D52: 2022 | E52: ESCOLA PENAL | F52: CAPITAL | G52: ETAPA 3 ESCOLA - NOTEBOOK: Ultraportáti | H52: 4.0 | I52: 8171.54 | J52: 32686.16 | L52: 32686.16 | M52: =IF(E52="N/A", J52, IF(OR(K52=0, ISBLANK(K52), K52=""), 0, J52-K52)) -> 0
A53: TO | B53: Convênio | C53: 937468 | D53: 2022 | E53: ESCOLA PENAL | F53: CAPITAL | G53: ETAPA 3 ESCOLA - PISTOLA AIRSOFT-ELÉTRI | H53: 8.0 | I53: 1278.83 | J53: 10230.67 | L53: 10230.67 | M53: =IF(E53="N/A", J53, IF(OR(K53=0, ISBLANK(K53), K53=""), 0, J53-K53)) -> 0
A54: TO | B54: Convênio | C54: 937468 | D54: 2022 | E54: ESCOLA PENAL | F54: CAPITAL | G54: ETAPA 3 ESCOLA - PROJETOR DE 34000 - EN | H54: 2.0 | I54: 2499 | J54: 4998 | L54: 4998 | M54: =IF(E54="N/A", J54, IF(OR(K54=0, ISBLANK(K54), K54=""), 0, J54-K54)) -> 0
A55: TO | B55: Convênio | C55: 937468 | D55: 2022 | E55: N/A | F55: CAPITAL | G55: Saldo de Economicidade - Despesas de Inv | H55: 1.0 | I55: 2421 | J55: 2421 | K55: 0 | L55: 2421 | M55: =IF(E55="N/A", J55, IF(OR(K55=0, ISBLANK(K55), K55=""), 0, J55-K55)) -> 2421
A56: TO | B56: Convênio | C56: 937468 | D56: 2022 | E56: CORREGEDORIA | F56: CAPITAL | G56: ETAPA 2 - CORREGEDORIA - Tablet, tela su | H56: 7 | I56: 3124 | J56: =H56*I56 -> 21868 | K56: 0 | L56: 2422 | M56: =IF(E56="N/A", J56, IF(OR(K56=0, ISBLANK(K56), K56=""), 0, J56-K56)) -> 0

Sheet RJ
A1: UF | B1: INSTRUMENTO | C1: NÚMERO | D1: ANO | E1: ÁREA | F1: NATUREZA | G1: DESCRIÇÃO | H1: QUANTIDADE | I1: VALOR UNITÁRIO | J1: VALOR TOTAL PREVISTO | K1: VALOR TOTAL EXECUTADO | L1: SALDO | M1: SALDO ECONOMICIDADE
A2: RJ | B2: Convênio | C2: 937817 | D2: 2022 | E2: ESCOLA PENAL | F2: CUSTEIO | G2: ABAFADOR ELETRONICO TIRO ESPORTIVO | H2: 45.0 | I2: 386.8 | J2: 17406.15 | K2: 16000 | L2: =J2-K2 -> 1406.15 | M2: =IF(E2="N/A", J2, IF(OR(K2=0, ISBLANK(K2), K2=""), 0, J2-K2)) -> 1406.15
A3: RJ | B3: Convênio | C3: 937817 | D3: 2022 | E3: ESCOLA PENAL | F3: CUSTEIO | G3: ALVOS SILHUETA HUMANOIDE 100 UNIDADES | H3: 100.0 | I3: 117.05 | J3: 11705 | L3: 11705 | M3: =IF(E3="N/A", J3, IF(OR(K3=0, ISBLANK(K3), K3=""), 0, J3-K3)) -> 0
A4: RJ | B4: Convênio | C4: 937817 | D4: 2022 | E4: ESCOLA PENAL | F4: CUSTEIO | G4: APARADOR DE CHUTE | H4: 10.0 | I4: 237.6 | J4: 2375.97 | K4: 1616.24 | L4: 759.73 | M4: =IF(E4="N/A", J4, IF(OR(K4=0, ISBLANK(K4), K4=""), 0, J4-K4)) -> 759.73
A5: RJ | B5: Convênio | C5: 937817 | D5: 2022 | E5: ESCOLA PENAL | F5: CUSTEIO | G5: BOLSO MDIVO APH | H5: 2.0 | I5: 78.74 | J5: 157.47 | K5: 540 | L5: =J5-K5 -> -382.53 | M5: =IF(E5="N/A", J5, IF(OR(K5=0, ISBLANK(K5), K5=""), 0, J5-K5)) -> -382.53
A6: RJ | B6: Convênio | C6: 937817 | D6: 2022 | E6: ESCOLA PENAL | F6: CUSTEIO | G6: BONECO SIMULDOR DE TREINO | H6: 1.0 | I6: 3968.1 | J6: 3968.1 | L6: 3968.1 | M6: =IF(E6="N/A", J6, IF(OR(K6=0, ISBLANK(K6), K6=""), 0, J6-K6)) -> 0
A7: RJ | B7: Convênio | C7: 937817 | D7: 2022 | E7: ESCOLA PENAL | F7: CUSTEIO | G7: CAIXAS DE GRAMPO COM 4000 UNIDADES | H7: 50.0 | I7: 27.08 | J7: 1353.83 | L7: 1353.83 | M7: =IF(E7="N/A", J7, IF(OR(K7=0, ISBLANK(K7), K7=""), 0, J7-K7)) -> 0
A8: RJ | B8: Convênio | C8: 937817 | D8: 2022 | E8: ESCOLA PENAL | F8: CUSTEIO | G8: CAPACETE PROTETOR | H8: 20.0 | I8: 217 | J8: 4340.07 | L8: -539.73 | M8: =IF(E8="N/A", J8, IF(OR(K8=0, ISBLANK(K8), K8=""), 0, J8-K8)) -> 0
A9: RJ | B9: Convênio | C9: 937817 | D9: 2022 | E9: ESCOLA PENAL | F9: CUSTEIO | G9: FACA DE TREINO | H9: 30.0 | I9: 169.53 | J9: 5086 | L9: 5086 | M9: =IF(E9="N/A", J9, IF(OR(K9=0, ISBLANK(K9), K9=""), 0, J9-K9)) -> 0
A10: RJ | B10: Convênio | C10: 937817 | D10: 2022 | E10: ESCOLA PENAL | F10: CUSTEIO | G10: GRAMPEADOR PROFISSIONAL PARA MADEIRA | H10: 10.0 | I10: 94.67 | J10: 946.66 | L10: 946.66 | M10: =IF(E10="N/A", J10, IF(OR(K10=0, ISBLANK(K10), K10=""), 0, J10-K10)) -> 0
A11: RJ | B11: Convênio | C11: 937817 | D11: 2022 | E11: ESCOLA PENAL | F11: CUSTEIO | G11: LUVA DE BOXE | H11: 27.0 | I11: 262.8 | J11: 7095.51 | K11: 5270 | L11: 1825.51 | M11: =IF(E11="N/A", J11, IF(OR(K11=0, ISBLANK(K11), K11=""), 0, J11-K11)) -> 1825.51
A12: RJ | B12: Convênio | C12: 937817 | D12: 2022 | E12: ESCOLA PENAL | F12: CUSTEIO | G12: LUVA DE MMA | H12: 15.0 | I12: 182.8 | J12: 2742 | L12: =J12-K12 -> 2742 | M12: =IF(E12="N/A", J12, IF(OR(K12=0, ISBLANK(K12), K12=""), 0, J12-K12)) -> 0
A13: RJ | B13: Convênio | C13: 937817 | D13: 2022 | E13: ESCOLA PENAL | F13: CUSTEIO | G13: MACA TATICA TEMS | H13: 4.0 | I13: 165.02 | J13: 660.07 | K13: 880 | L13: =J13-K13 -> -219.93 | M13: =IF(E13="N/A", J13, IF(OR(K13=0, ISBLANK(K13), K13=""), 0, J13-K13)) -> -219.93
A14: RJ | B14: Convênio | C14: 937817 | D14: 2022 | E14: ESCOLA PENAL | F14: CUSTEIO | G14: MALETA PRIMEIROS SOCORROS | H14: 2.0 | I14: 83.8 | J14: 167.59 | K14: 206 | L14: =J14-K14 -> -38.41 | M14: =IF(E14="N/A", J14, IF(OR(K14=0, ISBLANK(K14), K14=""), 0, J14-K14)) -> -38.41
A15: RJ | B15: Convênio | C15: 937817 | D15: 2022 | E15: ESCOLA PENAL | F15: CUSTEIO | G15: MANOPLA DE FOCO | H15: 10.0 | I15: 166.63 | J15: 1666.3 | K15: 1001.28 | L15: =J15-K15 -> 665.02 | M15: =IF(E15="N/A", J15, IF(OR(K15=0, ISBLANK(K15), K15=""), 0, J15-K15)) -> 665.02
A16: RJ | B16: Convênio | C16: 937817 | D16: 2022 | E16: ESCOLA PENAL | F16: CUSTEIO | G16: OCULOS DE PROTEÇÃO TIRO ESPORTIVO | H16: 45.0 | I16: 62.46 | J16: 2810.7 | L16: =J16-K16 -> 2810.7 | M16: =IF(E16="N/A", J16, IF(OR(K16=0, ISBLANK(K16), K16=""), 0, J16-K16)) -> 0
A17: RJ | B17: Convênio | C17: 937817 | D17: 2022 | E17: ESCOLA PENAL | F17: CUSTEIO | G17: PLACAS DE TATAME DE 40MM | H17: 40.0 | I17: 584.43 | J17: 23377.33 | K17: 7150 | L17: =J17-K17 -> 16227.33 | M17: =IF(E17="N/A", J17, IF(OR(K17=0, ISBLANK(K17), K17=""), 0, J17-K17)) -> 16227.33
A18: RJ | B18: Convênio | C18: 937817 | D18: 2022 | E18: ESCOLA PENAL | F18: CUSTEIO | G18: ROLOS DE OBREIA BRANCA | H18: 100.0 | I18: 22.06 | J18: 2206 | L18: =J18-K18 -> 2206 | M18: =IF(E18="N/A", J18, IF(OR(K18=0, ISBLANK(K18), K18=""), 0, J18-K18)) -> 0
A19: RJ | B19: Convênio | C19: 937817 | D19: 2022 | E19: ESCOLA PENAL | F19: CUSTEIO | G19: SIMULACRO DE PISTOLA | H19: 30.0 | I19: 699 | J19: 20970 | L19: =J19-K19 -> 20970 | M19: =IF(E19="N/A", J19, IF(OR(K19=0, ISBLANK(K19), K19=""), 0, J19-K19)) -> 0
A20: RJ | B20: Convênio | C20: 937817 | D20: 2022 | E20: ESCOLA PENAL | F20: CUSTEIO | G20: SUPORTE PARA SACO DE PANCADA | H20: 3.0 | I20: 92.65 | J20: 277.95 | L20: =J20-K20 -> 277.95 | M20: =IF(E20="N/A", J20, IF(OR(K20=0, ISBLANK(K20), K20=""), 0, J20-K20)) -> 0
A21: RJ | B21: Convênio | C21: 937817 | D21: 2022 | E21: ESCOLA PENAL | F21: CUSTEIO | G21: TONIQUETE | H21: 40.0 | I21: 258.01 | J21: 10320.4 | K21: 3100 | L21: =J21-K21 -> 7220.4 | M21: =IF(E21="N/A", J21, IF(OR(K21=0, ISBLANK(K21), K21=""), 0, J21-K21)) -> 7220.4
A22: RJ | B22: Convênio | C22: 937817 | D22: 2022 | E22: ESCOLA PENAL | F22: CAPITAL | G22: AR CONDICIONADO JANELA 18.000 BTUs | H22: 5.0 | I22: 3137.95 | J22: 15689.73 | L22: =J22-K22 -> 15689.73 | M22: =IF(E22="N/A", J22, IF(OR(K22=0, ISBLANK(K22), K22=""), 0, J22-K22)) -> 0
A23: RJ | B23: Convênio | C23: 937817 | D23: 2022 | E23: ESCOLA PENAL | F23: CAPITAL | G23: AR CONDICIONADO SPLIT 18.000 BTUs | H23: 10.0 | I23: 2782.3 | J23: 27822.97 | L23: =J23-K23 -> 27822.97 | M23: =IF(E23="N/A", J23, IF(OR(K23=0, ISBLANK(K23), K23=""), 0, J23-K23)) -> 0
A24: RJ | B24: Convênio | C24: 937817 | D24: 2022 | E24: ESCOLA PENAL | F24: CAPITAL | G24: AR CONDICIONADO SPLIT 50.000 BTUs | H24: 2.0 | I24: 8641.01 | J24: 17282.02 | L24: =J24-K24 -> 17282.02 | M24: =IF(E24="N/A", J24, IF(OR(K24=0, ISBLANK(K24), K24=""), 0, J24-K24)) -> 0
A25: RJ | B25: Convênio | C25: 937817 | D25: 2022 | E25: ESCOLA PENAL | F25: CAPITAL | G25: ARMÁRIO ESCRITÓRIO 2 PORTAS | H25: 2.0 | I25: 1643 | J25: 3286 | L25: =J25-K25 -> 3286 | M25: =IF(E25="N/A", J25, IF(OR(K25=0, ISBLANK(K25), K25=""), 0, J25-K25)) -> 0
A26: RJ | B26: Convênio | C26: 937817 | D26: 2022 | E26: ESCOLA PENAL | F26: CAPITAL | G26: ARQUIVO DE FERRO 4 GAVETAS | H26: 4.0 | I26: 877.77 | J26: 3511.08 | L26: =J26-K26 -> 3511.08 | M26: =IF(E26="N/A", J26, IF(OR(K26=0, ISBLANK(K26), K26=""), 0, J26-K26)) -> 0
A27: RJ | B27: Convênio | C27: 937817 | D27: 2022 | E27: ESCOLA PENAL | F27: CAPITAL | G27: BEBEDOURO INDUSTRIAL 100L | H27: 1.0 | I27: 2533.99 | J27: 2533.99 | L27: =J27-K27 -> 2533.99 | M27: =IF(E27="N/A", J27, IF(OR(K27=0, ISBLANK(K27), K27=""), 0, J27-K27)) -> 0
A28: RJ | B28: Convênio | C28: 937817 | D28: 2022 | E28: ESCOLA PENAL | F28: CAPITAL | G28: BEBEDOURO INDUSTRIAL 50L | H28: 2.0 | I28: 2294.3 | J28: 4588.6 | L28: =J28-K28 -> 4588.6 | M28: =IF(E28="N/A", J28, IF(OR(K28=0, ISBLANK(K28), K28=""), 0, J28-K28)) -> 0
A29: RJ | B29: Convênio | C29: 937817 | D29: 2022 | E29: ESCOLA PENAL | F29: CAPITAL | G29: BEBEDOURO PURIFICADOR COLUNA | H29: 7.0 | I29: 1098.41 | J29: 7688.87 | L29: =J29-K29 -> 7688.87 | M29: =IF(E29="N/A", J29, IF(OR(K29=0, ISBLANK(K29), K29=""), 0, J29-K29)) -> 0
A30: RJ | B30: Convênio | C30: 937817 | D30: 2022 | E30: ESCOLA PENAL | F30: CAPITAL | G30: BOMBA AUTO ASPIRANTE 2CV | H30: 1.0 | I30: 1549.63 | J30: 1549.63 | K30: 1850.37 | L30: =J30-K30 -> -300.74 | M30: =IF(E30="N/A", J30, IF(OR(K30=0, ISBLANK(K30), K30=""), 0, J30-K30)) -> -300.74
A31: RJ | B31: Convênio | C31: 937817 | D31: 2022 | E31: ESCOLA PENAL | F31: CAPITAL | G31: CADEIRA ESCRITÓRIO PRESIDENTE | H31: 26.0 | I31: 1069 | J31: 27794 | L31: =J31-K31 -> 27794 | M31: =IF(E31="N/A", J31, IF(OR(K31=0, ISBLANK(K31), K31=""), 0, J31-K31)) -> 0
A32: RJ | B32: Convênio | C32: 937817 | D32: 2022 | E32: ESCOLA PENAL | F32: CAPITAL | G32: CAMERA EOSREBEL SL3 COM LENTE EF-S18-55MM | H32: 2.0 | I32: 5099.66 | J32: 10199.32 | K32: 8194.58 | L32: =J32-K32 -> 2004.74 | M32: =IF(E32="N/A", J32, IF(OR(K32=0, ISBLANK(K32), K32=""), 0, J32-K32)) -> 2004.74
A33: RJ | B33: Convênio | C33: 937817 | D33: 2022 | E33: ESCOLA PENAL | F33: CAPITAL | G33: COLCHÃO DESOLTEIRO | H33: 5.0 | I33: 249 | J33: 1245 | L33: =J33-K33 -> 1245 | M33: =IF(E33="N/A", J33, IF(OR(K33=0, ISBLANK(K33), K33=""), 0, J33-K33)) -> 0
A34: RJ | B34: Convênio | C34: 937817 | D34: 2022 | E34: ESCOLA PENAL | F34: CAPITAL | G34: CONJUNTO MESA ECADEIRA ESCOLAR | H34: 30.0 | I34: 867 | J34: 26010 | L34: =J34-K34 -> 26010 | M34: =IF(E34="N/A", J34, IF(OR(K34=0, ISBLANK(K34), K34=""), 0, J34-K34)) -> 0
A35: RJ | B35: Convênio | C35: 937817 | D35: 2022 | E35: ESCOLA PENAL | F35: CAPITAL | G35: DESFIBRILADOR EXTERNO AUTOMÁTICO DEA) | H35: 2.0 | I35: 8686.33 | J35: 17372.66 | K35: 13060 | L35: =J35-K35 -> 4312.66 | M35: =IF(E35="N/A", J35, IF(OR(K35=0, ISBLANK(K35), K35=""), 0, J35-K35)) -> 4312.66
A36: RJ | B36: Convênio | C36: 937817 | D36: 2022 | E36: ESCOLA PENAL | F36: CAPITAL | G36: ESTABILIZADOR | H36: 30.0 | I36: 81.88 | J36: 2456.4 | L36: =J36-K36 -> 2456.4 | M36: =IF(E36="N/A", J36, IF(OR(K36=0, ISBLANK(K36), K36=""), 0, J36-K36)) -> 0
A37: RJ | B37: Convênio | C37: 937817 | D37: 2022 | E37: ESCOLA PENAL | F37: CAPITAL | G37: FRIGOBAR | H37: 7.0 | I37: 1365.31 | J37: 9557.17 | L37: =J37-K37 -> 9557.17 | M37: =IF(E37="N/A", J37, IF(OR(K37=0, ISBLANK(K37), K37=""), 0, J37-K37)) -> 0
A38: RJ | B38: Convênio | C38: 937817 | D38: 2022 | E38: ESCOLA PENAL | F38: CAPITAL | G38: GAVETEIRO 4 GAVETAS | H38: 4.0 | I38: 1026 | J38: 4104 | L38: =J38-K38 -> 4104 | M38: =IF(E38="N/A", J38, IF(OR(K38=0, ISBLANK(K38), K38=""), 0, J38-K38)) -> 0
A39: RJ | B39: Convênio | C39: 937817 | D39: 2022 | E39: ESCOLA PENAL | F39: CAPITAL | G39: GRAVADOR ZOOM H4NPRO | H39: 2.0 | I39: 1804.1 | J39: 3608.19 | K39: 2392 | L39: =J39-K39 -> 1216.19 | M39: =IF(E39="N/A", J39, IF(OR(K39=0, ISBLANK(K39), K39=""), 0, J39-K39)) -> 1216.19
A40: RJ | B40: Convênio | C40: 937817 | D40: 2022 | E40: ESCOLA PENAL | F40: CAPITAL | G40: LONGARINA 4 LUGARES | H40: 36.0 | I40: 1645 | J40: 59220 | L40: =J40-K40 -> 59220 | M40: =IF(E40="N/A", J40, IF(OR(K40=0, ISBLANK(K40), K40=""), 0, J40-K40)) -> 0
A41: RJ | B41: Convênio | C41: 937817 | D41: 2022 | E41: ESCOLA PENAL | F41: CAPITAL | G41: MANEQUIM DE TREINAMENTO RCP | H41: 4.0 | I41: 5737.91 | J41: 22951.65 | L41: =J41-K41 -> 22951.65 | M41: =IF(E41="N/A", J41, IF(OR(K41=0, ISBLANK(K41), K41=""), 0, J41-K41)) -> 0
A42: RJ | B42: Convênio | C42: 937817 | D42: 2022 | E42: ESCOLA PENAL | F42: CAPITAL | G42: MANEQUIM DE TREINAMENTO RCPBEBE | H42: 4.0 | I42: 2196.3 | J42: 8785.2 | K42: 23130 | L42: =J42-K42 -> -14344.8 | M42: =IF(E42="N/A", J42, IF(OR(K42=0, ISBLANK(K42), K42=""), 0, J42-K42)) -> -14344.8
A43: RJ | B43: Convênio | C43: 937817 | D43: 2022 | E43: ESCOLA PENAL | F43: CAPITAL | G43: MESA ESCRITÓRIOCOM GAVETA | H43: 13.0 | I43: 1331.37 | J43: 17307.81 | L43: =J43-K43 -> 17307.81 | M43: =IF(E43="N/A", J43, IF(OR(K43=0, ISBLANK(K43), K43=""), 0, J43-K43)) -> 0
A44: RJ | B44: Convênio | C44: 937817 | D44: 2022 | E44: ESCOLA PENAL | F44: CAPITAL | G44: MESA REFEITÓRIO 8 LUGARES | H44: 1.0 | I44: 2800 | J44: 2800 | L44: =J44-K44 -> 2800 | M44: =IF(E44="N/A", J44, IF(OR(K44=0, ISBLANK(K44), K44=""), 0, J44-K44)) -> 0
A45: RJ | B45: Convênio | C45: 937817 | D45: 2022 | E45: ESCOLA PENAL | F45: CAPITAL | G45: MICROFONE LAPELA | H45: 4.0 | I45: 290.54 | J45: 1162.16 | K45: 555.44 | L45: =J45-K45 -> 606.72 | M45: =IF(E45="N/A", J45, IF(OR(K45=0, ISBLANK(K45), K45=""), 0, J45-K45)) -> 606.72
A46: RJ | B46: Convênio | C46: 937817 | D46: 2022 | E46: ESCOLA PENAL | F46: CAPITAL | G46: MICROONDAS | H46: 8.0 | I46: 701.62 | J46: 5612.96 | K46: 5350 | L46: =J46-K46 -> 262.96 | M46: =IF(E46="N/A", J46, IF(OR(K46=0, ISBLANK(K46), K46=""), 0, J46-K46)) -> 262.96
A47: RJ | B47: Convênio | C47: 937817 | D47: 2022 | E47: OUVIDORIA | F47: CAPITAL | G47: MINIBUS PARA ATENDIMENTO DE CIDADÕES IN | H47: 1.0 | I47: 323838.9 | J47: 323838.9 | L47: =J47-K47 -> 323838.9 | M47: =IF(E47="N/A", J47, IF(OR(K47=0, ISBLANK(K47), K47=""), 0, J47-K47)) -> 0
A48: RJ | B48: Convênio | C48: 937817 | D48: 2022 | E48: ESCOLA PENAL | F48: CAPITAL | G48: NOTEBOOK 14' | H48: 4.0 | I48: 8909.06 | J48: 35636.24 | K48: 19599 | L48: =J48-K48 -> 16037.24 | M48: =IF(E48="N/A", J48, IF(OR(K48=0, ISBLANK(K48), K48=""), 0, J48-K48)) -> 16037.24
A49: RJ | B49: Convênio | C49: 937817 | D49: 2022 | E49: CORREGEDORIA | F49: CAPITAL | G49: PICK UP | H49: 2.0 | I49: 300895.4 | J49: 601790.9 | L49: =J49-K49 -> 601790.9 | M49: =IF(E49="N/A", J49, IF(OR(K49=0, ISBLANK(K49), K49=""), 0, J49-K49)) -> 0
A50: RJ | B50: Convênio | C50: 937817 | D50: 2022 | E50: ESCOLA PENAL | F50: CAPITAL | G50: PLACA PABX 16RAMAIS | H50: 1.0 | I50: 1024.55 | J50: 1024.55 | L50: =J50-K50 -> 1024.55 | M50: =IF(E50="N/A", J50, IF(OR(K50=0, ISBLANK(K50), K50=""), 0, J50-K50)) -> 0
A51: RJ | B51: Convênio | C51: 937817 | D51: 2022 | E51: ESCOLA PENAL | F51: CAPITAL | G51: PROJETOR INTERATIVO | H51: 3.0 | I51: 20765.67 | J51: 62297 | K51: 8499 | L51: =J51-K51 -> 53798 | M51: =IF(E51="N/A", J51, IF(OR(K51=0, ISBLANK(K51), K51=""), 0, J51-K51)) -> 53798
A52: RJ | B52: Convênio | C52: 937817 | D52: 2022 | E52: ESCOLA PENAL | F52: CAPITAL | G52: RING LIGHT 18' +TRIPÉ | H52: 4.0 | I52: 584.76 | J52: 2339.04 | K52: 555.44 | L52: =J52-K52 -> 1783.6 | M52: =IF(E52="N/A", J52, IF(OR(K52=0, ISBLANK(K52), K52=""), 0, J52-K52)) -> 1783.6
A53: RJ | B53: Convênio | C53: 937817 | D53: 2022 | E53: ESCOLA PENAL | F53: CAPITAL | G53: SALDO DE RENDIMENTO COMPLEMENTAÇÃO DOS V | H53: 1 | I53: 101341.43 | J53: 101341.43 | K53: 14780.1 | L53: =J53-K53 -> 86561.33 | M53: -
A54: RJ | B54: Convênio | C54: 937817 | D54: 2022 | E54: N/A | F54: CAPITAL | G54: SALDO REMANESCENTE - AQUISIÇÃO | H54: 1.0 | I54: 183.4 | J54: 183.4 | K54: 0 | L54: =J54-K54 -> 183.4 | M54: =IF(E54="N/A", J54, IF(OR(K54=0, ISBLANK(K54), K54=""), 0, J54-K54)) -> 183.4
A55: RJ | B55: Convênio | C55: 937817 | D55: 2022 | E55: ESCOLA PENAL | F55: CAPITAL | G55: SIMULADORDEA | H55: 4.0 | I55: 1959.25 | J55: 7837 | L55: =J55-K55 -> 7837 | M55: =IF(E55="N/A", J55, IF(OR(K55=0, ISBLANK(K55), K55=""), 0, J55-K55)) -> 0
A56: RJ | B56: Convênio | C56: 937817 | D56: 2022 | E56: ESCOLA PENAL | F56: CAPITAL | G56: TELEFONE SEM FIO | H56: 12.0 | I56: 209.63 | J56: 2515.52 | K56: 1812 | L56: =J56-K56 -> 703.52 | M56: =IF(E56="N/A", J56, IF(OR(K56=0, ISBLANK(K56), K56=""), 0, J56-K56)) -> 703.52
A57: RJ | B57: Convênio | C57: 937817 | D57: 2022 | E57: ESCOLA PENAL | F57: CAPITAL | G57: TENDAS BRANCAS DE PRAIA 3X3M | H57: 5.0 | I57: 253.07 | J57: 1265.33 | K57: 1500 | L57: =J57-K57 -> -234.67 | M57: =IF(E57="N/A", J57, IF(OR(K57=0, ISBLANK(K57), K57=""), 0, J57-K57)) -> -234.67
A58: RJ | B58: Convênio | C58: 937817 | D58: 2022 | E58: ESCOLA PENAL | F58: CAPITAL | G58: TRIPÉ MANFROTTOBEFREE ADVANCEDMK BFRLA4BK-BH | H58: 2.0 | I58: 1934.19 | J58: 3868.38 | K58: 2000 | L58: =J58-K58 -> 1868.38 | M58: =IF(E58="N/A", J58, IF(OR(K58=0, ISBLANK(K58), K58=""), 0, J58-K58)) -> 1868.38
A59: RJ | B59: Convênio | C59: 937817 | D59: 2022 | E59: ESCOLA PENAL | F59: CAPITAL | G59: TV SMART 55' 4K | H59: 5.0 | I59: 2706.66 | J59: 13533.3 | K59: 11650 | L59: =J59-K59 -> 1883.3 | M59: =IF(E59="N/A", J59, IF(OR(K59=0, ISBLANK(K59), K59=""), 0, J59-K59)) -> 1883.3
A60: RJ | B60: Convênio | C60: 937817 | D60: 2022 | E60: ESCOLA PENAL | F60: CAPITAL | G60: VENTILADOR 50 CM PAREDE | H60: 10.0 | I60: 177.55 | J60: 1775.47 | K60: 2388 | L60: =J60-K60 -> -612.53 | M60: =IF(E60="N/A", J60, IF(OR(K60=0, ISBLANK(K60), K60=""), 0, J60-K60)) -> -612.53

Sheet AL
A1: UF | B1: INSTRUMENTO | C1: NÚMERO | D1: ANO | E1: ÁREA | F1: NATUREZA | G1: DESCRIÇÃO | H1: QUANTIDADE | I1: VALOR UNITÁRIO | J1: VALOR TOTAL PREVISTO | K1: VALOR TOTAL EXECUTADO | L1: SALDO | M1: SALDO ECONOMICIDADE
A2: AL | B2: Convênio | C2: 937221 | D2: 2022 | E2: ESCOLA PENAL | F2: CUSTEIO | G2: Contratação de Serviços de Desenvolvimen | H2: 1.0 | I2: 42900 | J2: 42900 | L2: 42900 | M2: =IF(E2="N/A", J2, IF(OR(K2=0, ISBLANK(K2), K2=""), 0, J2-K2)) -> 0
A3: AL | B3: Convênio | C3: 937221 | D3: 2022 | E3: OUVIDORIA | F3: CAPITAL | G3: Ar Condicionado Split 9000 BTUs (OUVIDORIA) | H3: 1.0 | I3: 1349.62 | J3: 1349.62 | L3: 1349.62 | M3: =IF(E3="N/A", J3, IF(OR(K3=0, ISBLANK(K3), K3=""), 0, J3-K3)) -> 0
A4: AL | B4: Convênio | C4: 937221 | D4: 2022 | E4: ESCOLA PENAL | F4: CAPITAL | G4: Ar condicionado Split 18000 BTUs (ESCOLA) | H4: 2.0 | I4: 2783.72 | J4: 5567.44 | L4: 5567.44 | M4: =IF(E4="N/A", J4, IF(OR(K4=0, ISBLANK(K4), K4=""), 0, J4-K4)) -> 0
A5: AL | B5: Convênio | C5: 937221 | D5: 2022 | E5: CORREGEDORIA | F5: CAPITAL | G5: Ar condicionado Split 24000 BTUs (CORREG | H5: 2.0 | I5: 6368.24 | J5: 12736.48 | L5: 12736.48 | M5: =IF(E5="N/A", J5, IF(OR(K5=0, ISBLANK(K5), K5=""), 0, J5-K5)) -> 0
A6: AL | B6: Convênio | C6: 937221 | D6: 2022 | E6: ESCOLA PENAL | F6: CAPITAL | G6: Ar condicionado Split 36000 BTUs (ESCOLA) | H6: 1.0 | I6: 8168.19 | J6: 8168.19 | L6: 8168.19 | M6: =IF(E6="N/A", J6, IF(OR(K6=0, ISBLANK(K6), K6=""), 0, J6-K6)) -> 0
A7: AL | B7: Convênio | C7: 937221 | D7: 2022 | E7: OUVIDORIA | F7: CAPITAL | G7: Cadeira Longarina plástica 03 Lugares - | H7: 1.0 | I7: 703.26 | J7: 703.26 | L7: 703.26 | M7: =IF(E7="N/A", J7, IF(OR(K7=0, ISBLANK(K7), K7=""), 0, J7-K7)) -> 0
A8: AL | B8: Convênio | C8: 937221 | D8: 2022 | E8: OUVIDORIA | F8: CAPITAL | G8: Cadeira Secretária Fixa, Preta, pé palit | H8: 4.0 | I8: 145.59 | J8: 582.36 | L8: 582.36 | M8: =IF(E8="N/A", J8, IF(OR(K8=0, ISBLANK(K8), K8=""), 0, J8-K8)) -> 0
A9: AL | B9: Convênio | C9: 937221 | D9: 2022 | E9: OUVIDORIA | F9: CAPITAL | G9: Cafeteira Elétrica Tradicional Industria | H9: 1.0 | I9: 844.06 | J9: 844.06 | L9: 844.06 | M9: =IF(E9="N/A", J9, IF(OR(K9=0, ISBLANK(K9), K9=""), 0, J9-K9)) -> 0
A10: AL | B10: Convênio | C10: 937221 | D10: 2022 | E10: OUVIDORIA | F10: CAPITAL | G10: Computador Desktop (OUVIDORIA) | H10: 1.0 | I10: 1455.49 | J10: 1455.49 | L10: 1455.49 | M10: =IF(E10="N/A", J10, IF(OR(K10=0, ISBLANK(K10), K10=""), 0, J10-K10)) -> 0
A11: AL | B11: Convênio | C11: 937221 | D11: 2022 | E11: OUVIDORIA | F11: CAPITAL | G11: Forno de Microondas - 20L Branco (OUVID | H11: 1.0 | I11: 482.36 | J11: 482.36 | L11: 482.36 | M11: =IF(E11="N/A", J11, IF(OR(K11=0, ISBLANK(K11), K11=""), 0, J11-K11)) -> 0
A12: AL | B12: Convênio | C12: 937221 | D12: 2022 | E12: ESCOLA PENAL | F12: CAPITAL | G12: Forno de Microondas - 32 litros - Branco | H12: 1.0 | I12: 726 | J12: 726 | L12: 726 | M12: =IF(E12="N/A", J12, IF(OR(K12=0, ISBLANK(K12), K12=""), 0, J12-K12)) -> 0
A13: AL | B13: Convênio | C13: 937221 | D13: 2022 | E13: OUVIDORIA | F13: CAPITAL | G13: Fragmentadora de Papel 150 folhas (OUVI | H13: 1.0 | I13: 4438.14 | J13: 4438.14 | L13: 4438.14 | M13: =IF(E13="N/A", J13, IF(OR(K13=0, ISBLANK(K13), K13=""), 0, J13-K13)) -> 0
... A29: AL | B29: Convênio | C29: 937221 | D29: 2022 | E29: CORREGEDORIA | F29: CAPITAL | G29: Sofá 3 lugares (CORREGEDORIA) | H29: 1.0 | I29: 3650.84 | J29: 3650.84 | L29: 3650.84 | M29: =IF(E29="N/A", J29, IF(OR(K29=0, ISBLANK(K29), K29=""), 0, J29-K29)) -> 0
A30: AL | B30: Convênio | C30: 937221 | D30: 2022 | E30: N/A | F30: CAPITAL | G30: Suplementação de Valor - Aquisição de Fo | H30: 1.0 | I30: 3.5 | J30: 3.5 | K30: 0 | L30: 3.5 | M30: =IF(E30="N/A", J30, IF(OR(K30=0, ISBLANK(K30), K30=""), 0, J30-K30)) -> 3.5
A31: AL | B31: Convênio | C31: 937221 | D31: 2022 | E31: CORREGEDORIA | F31: CAPITAL | G31: Tapete (CORREGEDORIA) | H31: 1.0 | I31: 1690.82 | J31: 1690.82 | L31: 1690.82 | M31: =IF(E31="N/A", J31, IF(OR(K31=0, ISBLANK(K31), K31=""), 0, J31-K31)) -> 0
A32: AL | B32: Convênio | C32: 937221 | D32: 2022 | E32: OUVIDORIA | F32: CAPITAL | G32: Tela de projeção 2x2 retrátil com tripé | H32: 1.0 | I32: 1047.97 | J32: 1047.97 | L32: 1047.97 | M32: =IF(E32="N/A", J32, IF(OR(K32=0, ISBLANK(K32), K32=""), 0, J32-K32)) -> 0
A33: AL | B33: Convênio | C33: 937221 | D33: 2022 | E33: CORREGEDORIA | F33: CAPITAL | G33: Televisão 50 (CORREGEDORIA - 03 UN. E OU | H33: 5.0 | I33: 2174.86 | J33: 10874.3 | L33: 10874.3 | M33: =IF(E33="N/A", J33, IF(OR(K33=0, ISBLANK(K33), K33=""), 0, J33-K33)) -> 0
A34: AL | B34: Convênio | C34: 937221 | D34: 2022 | E34: OUVIDORIA | F34: CAPITAL | G34: Webcam full HD (OUVIDORIA) | H34: 2.0 | I34: 245.54 | J34: 491.08 | L34: 491.08 | M34: =IF(E34="N/A", J34, IF(OR(K34=0, ISBLANK(K34), K34=""), 0, J34-K34)) -> 0

Sheet SC
A1: UF | B1: INSTRUMENTO | C1: NÚMERO | D1: ANO | E1: ÁREA | F1: NATUREZA | G1: DESCRIÇÃO | H1: QUANTIDADE | I1: VALOR UNITÁRIO | J1: VALOR TOTAL PREVISTO | K1: VALOR TOTAL EXECUTADO | L1: SALDO | M1: SALDO ECONOMICIDADE
A2: SC | B2: Convênio | C2: 937783 | D2: 2022 | E2: CORREGEDORIA | F2: CUSTEIO | G2: Item 002 - Equipamento de captura de ima | H2: 16.0 | I2: 450 | J2: 7200 | L2: 7200 | M2: =IF(E2="N/A", J2, IF(OR(K2=0, ISBLANK(K2), K2=""), 0, J2-K2)) -> 0
A3: SC | B3: Convênio | C3: 937783 | D3: 2022 | E3: N/A | F3: CUSTEIO | G3: Item 021 - Saldo remanescente Consumo | H3: 1.0 | I3: 92886.88 | J3: 92886.88 | K3: 0 | L3: 92886.88 | M3: =IF(E3="N/A", J3, IF(OR(K3=0, ISBLANK(K3), K3=""), 0, J3-K3)) -> 92886.88
A4: SC | B4: Convênio | C4: 937783 | D4: 2022 | E4: OUVIDORIA | F4: CAPITAL | G4: Item 001 - Veículo Completo Automático, | H4: 1 | I4: 140216.7 | J4: 140216.7 | L4: 140216.7 | M4: =IF(E4="N/A", J4, IF(OR(K4=0, ISBLANK(K4), K4=""), 0, J4-K4)) -> 0
A5: SC | B5: Convênio | C5: 937783 | D5: 2022 | E5: CORREGEDORIA | F5: CAPITAL | G5: Item 001 - Veículo Completo Automático, | H5: 1 | I5: 140216.7 | J5: 140216.7 | L5: 140216.7 | M5: =IF(E5="N/A", J5, IF(OR(K5=0, ISBLANK(K5), K5=""), 0, J5-K5)) -> 0
A6: SC | B6: Convênio | C6: 937783 | D6: 2022 | E6: ESCOLA PENAL | F6: CAPITAL | G6: Item 003 - Câmera digital 4k 60 fps, 6k | H6: 1.0 | I6: 7000 | J6: 7000 | L6: 7000 | M6: =IF(E6="N/A", J6, IF(OR(K6=0, ISBLANK(K6), K6=""), 0, J6-K6)) -> 0
A7: SC | B7: Convênio | C7: 937783 | D7: 2022 | E7: ESCOLA PENAL | F7: CAPITAL | G7: Item 004 - Câmera de ação homônima à Pro | H7: 1.0 | I7: 1795.67 | J7: 1795.67 | L7: 1795.67 | M7: =IF(E7="N/A", J7, IF(OR(K7=0, ISBLANK(K7), K7=""), 0, J7-K7)) -> 0
A8: SC | B8: Convênio | C8: 937783 | D8: 2022 | E8: ESCOLA PENAL | F8: CAPITAL | G8: Item 005 - Automóvel zero quilômetro, an | H8: 1.0 | I8: 97456.67 | J8: 97456.67 | L8: 97456.67 | M8: =IF(E8="N/A", J8, IF(OR(K8=0, ISBLANK(K8), K8=""), 0, J8-K8)) -> 0
A9: SC | B9: Convênio | C9: 937783 | D9: 2022 | E9: ESCOLA PENAL | F9: CAPITAL | G9: Item 006 - Drone com resolução de captur | H9: 1.0 | I9: 4969 | J9: 4969 | K9: 4969 | L9: =J9-K9 -> 0 | M9: =IF(E9="N/A", J9, IF(OR(K9=0, ISBLANK(K9), K9=""), 0, J9-K9)) -> 0
A10: SC | B10: Convênio | C10: 937783 | D10: 2022 | E10: ESCOLA PENAL | F10: CAPITAL | G10: Item 007 - Filmadora profissional 4k com | H10: 1.0 | I10: 18200 | J10: 18200 | K10: 18200 | L10: =J10-K10 -> 0 | M10: =IF(E10="N/A", J10, IF(OR(K10=0, ISBLANK(K10), K10=""), 0, J10-K10)) -> 0
A11: SC | B11: Convênio | C11: 937783 | D11: 2022 | E11: ESCOLA PENAL | F11: CAPITAL | G11: Item 008 - Gravador e reprodutor digital | H11: 2.0 | I11: 419.99 | J11: 839.98 | K11: 839.98 | L11: =J11-K11 -> 0 | M11: =IF(E11="N/A", J11, IF(OR(K11=0, ISBLANK(K11), K11=""), 0, J11-K11)) -> 0
A12: SC | B12: Convênio | C12: 937783 | D12: 2022 | E12: ESCOLA PENAL | F12: CAPITAL | G12: Item 009 - Headset com microfone, driver | H12: 3.0 | I12: 450 | J12: 1350 | K12: 1350 | L12: =J12-K12 -> 0 | M12: =IF(E12="N/A", J12, IF(OR(K12=0, ISBLANK(K12), K12=""), 0, J12-K12)) -> 0
A13: SC | B13: Convênio | C13: 937783 | D13: 2022 | E13: ESCOLA PENAL | F13: CAPITAL | G13: Item 010 - Kit com 2 softbox quádruplos | H13: 1.0 | I13: 534.18 | J13: 534.18 | L13: =J13-K13 -> 534.18 | M13: =IF(E13="N/A", J13, IF(OR(K13=0, ISBLANK(K13), K13=""), 0, J13-K13)) -> 0
A14: SC | B14: Convênio | C14: 937783 | D14: 2022 | E14: ESCOLA PENAL | F14: CAPITAL | G14: Item 011 - Mesa de Som 12 canais profiss | H14: 1.0 | I14: 944.84 | J14: 944.84 | K14: 944.84 | L14: =J14-K14 -> 0 | M14: =IF(E14="N/A", J14, IF(OR(K14=0, ISBLANK(K14), K14=""), 0, J14-K14)) -> 0
A15: SC | B15: Convênio | C15: 937783 | D15: 2022 | E15: ESCOLA PENAL | F15: CAPITAL | G15: Item 012 - Microfone Condensador, microf | H15: 2.0 | I15: 997 | J15: 1994 | K15: 1994 | L15: =J15-K15 -> 0 | M15: =IF(E15="N/A", J15, IF(OR(K15=0, ISBLANK(K15), K15=""), 0, J15-K15)) -> 0
A16: SC | B16: Convênio | C16: 937783 | D16: 2022 | E16: ESCOLA PENAL | F16: CAPITAL | G16: Item 013 - Microfone Direcional Estéreo | H16: 2.0 | I16: 646.93 | J16: 1293.86 | L16: =J16-K16 -> 1293.86 | M16: =IF(E16="N/A", J16, IF(OR(K16=0, ISBLANK(K16), K16=""), 0, J16-K16)) -> 0
A17: SC | B17: Convênio | C17: 937783 | D17: 2022 | E17: ESCOLA PENAL | F17: CAPITAL | G17: Item 014 - Microfone lapela sem fio omni | H17: 2.0 | I17: 950 | J17: 1900 | L17: =J17-K17 -> 1900 | M17: =IF(E17="N/A", J17, IF(OR(K17=0, ISBLANK(K17), K17=""), 0, J17-K17)) -> 0
A18: SC | B18: Convênio | C18: 937783 | D18: 2022 | E18: ESCOLA PENAL | F18: CAPITAL | G18: Item 015 - Monitor de 34 ', resolução de | H18: 3.0 | I18: 2075.67 | J18: 6227.01 | L18: =J18-K18 -> 6227.01 | M18: =IF(E18="N/A", J18, IF(OR(K18=0, ISBLANK(K18), K18=""), 0, J18-K18)) -> 0
A19: SC | B19: Convênio | C19: 937783 | D19: 2022 | E19: ESCOLA PENAL | F19: CAPITAL | G19: Item 016 - Notebook com processador de n | H19: 2.0 | I19: 6250 | J19: 12500 | L19: =J19-K19 -> 12500 | M19: =IF(E19="N/A", J19, IF(OR(K19=0, ISBLANK(K19), K19=""), 0, J19-K19)) -> 0
A20: SC | B20: Convênio | C20: 937783 | D20: 2022 | E20: ESCOLA PENAL | F20: CAPITAL | G20: Item 017 - Microcomputador desktop com p | H20: 2.0 | I20: 8300 | J20: 16600 | K20: 16600 | L20: =J20-K20 -> 0 | M20: =IF(E20="N/A", J20, IF(OR(K20=0, ISBLANK(K20), K20=""), 0, J20-K20)) -> 0
A21: SC | B21: Convênio | C21: 937783 | D21: 2022 | E21: ESCOLA PENAL | F21: CAPITAL | G21: Item 018 - Refletor led com suporte trip | H21: 2.0 | I21: 368.32 | J21: 736.64 | L21: =J21-K21 -> 736.64 | M21: =IF(E21="N/A", J21, IF(OR(K21=0, ISBLANK(K21), K21=""), 0, J21-K21)) -> 0
A22: SC | B22: Convênio | C22: 937783 | D22: 2022 | E22: ESCOLA PENAL | F22: CAPITAL | G22: Item 019 - Tablet com no mínimo 512GB de | H22: 1.0 | I22: 5200 | J22: 5200 | L22: =J22-K22 -> 5200 | M22: =IF(E22="N/A", J22, IF(OR(K22=0, ISBLANK(K22), K22=""), 0, J22-K22)) -> 0
A23: SC | B23: Convênio | C23: 937783 | D23: 2022 | E23: ESCOLA PENAL | F23: CAPITAL | G23: Item 020 - Teleprompter portátil dobráve | H23: 2.0 | I23: 1235 | J23: 2470 | L23: =J23-K23 -> 2470 | M23: =IF(E23="N/A", J23, IF(OR(K23=0, ISBLANK(K23), K23=""), 0, J23-K23)) -> 0
A24: SC | B24: Convênio | C24: 937783 | D24: 2022 | E24: N/A | F24: CAPITAL | G24: Item 022 - Saldo remanescente Capital | H24: 1.0 | I24: 18488.15 | J24: 18488.15 | K24: 0 | L24: =J24-K24 -> 18488.15 | M24: =IF(E24="N/A", J24, IF(OR(K24=0, ISBLANK(K24), K24=""), 0, J24-K24)) -> 18488.15
